Workbook

Sheet 周期整合及其行业风格表现汇总
B2: 一、周期整合：根据股债相对表现重新划分经济周期。注，债券收益率可以类比中证债基指数，回报率上行指牛市。 ※衰退：对应周期2（景气值<0，方向下降）。经济衰退阶段往往通货膨胀周期下行、实际经济增长放缓。此时货币宽松利好股票估值，但经济放缓对股票盈利构成抑制，股票收益率由弱转为更弱；而货币政策宽松和资金需求转弱同时推动利率下行并形成债券牛市。综合来看，当前阶段股票收益率弱于债券，且趋势上股债收益差下降。 ※复苏：对应周期3（景气值<0，方向上升）。经济复苏阶段往往通货膨胀周期下行、实际经济增长周期上行。此时因为经济复苏和货币宽松，股票估值和盈利同时修复，股票收益率由弱转强；而央行维持偏宽松的货币政策利好债券利率下行，但经济增长预期升温会产生利率上行的预期，所以债市收益率由强转弱。综合来看，当前阶段股票收益率弱于债券，但趋势上股债收益差上升。 ※过热：对应周期4（景气值>0，方向上升）。经济过热阶段通货膨胀周期上行、实际经济增长周期上行。此时宏观环境有利于股票盈利，对股票估值构成抑制，综合来看股市呈震荡阶段；但央行一般收紧货币政策，资金需求也比较旺盛，易推动债券利率上行，利空债市。综合来看，当前阶段股票收益率强于债券，且趋势上股债收益差上升。 ※滞涨：对应周期1（景气值>0，方向下降）。经济滞胀阶段往往通货膨胀周期上行、实际经济增长放缓。此时宏观环境对股票估值和盈利均构成抑制，综合来看股票收益率由强转弱；而央行治理通胀推动债券短端利率上行，经济的悲观预期推动中长端利率下行，综合来看债市收益率呈震荡阶段。综合来看，当前阶段股票收益率强于债券，但趋势上股债收益差下行。 二、行业风格表现：对各周期内的行业风格绝对回报、超额回报进行统计（月度平均收益率）。 1. 从超额收益看行业/风格轮动更有效：相对收益率可以更好体现出风格板块/行业表现与基本面的偏离情况，我们在绝对收益基础上结合相对收益（即各个风格较全A的超额回报来测算）； 2. 从超额收益看，存在以下特征： （1）经济放缓配大盘，经济走强配小盘。从沪深300vs中证1000，巨潮大盘vs巨潮小盘看，小盘股在经济走强时（复苏、过热）表现较好，大盘股在经济放缓时（滞涨、衰退）表现更佳，体现出防御属性。 （2）风格板块看，消费与金融、稳定能形成有效对冲，可以用于考虑配对交易来平抑风险。 （3）红利思路和大盘具有共通之处，经济下行时（滞涨、衰退）表现更佳。 （4）相比低估值的逆周期对抗效果，高估值板块在盈利下行期更易迎来“戴维斯双杀”。
B8: 周期整合
B9: 阶段划分 | G9: 划分依据
B11: 所处阶段 | C11: 阶段起点 | D11: 阶段终点
B12: 衰退 | C12: 45078 | D12: 45443
C13: 44348 | D13: 44500
C14: 43191 | D14: 43373
C15: 41791 | D15: 42004
C16: 40848 | D16: 41060
B17: 复苏 | C17: 45444 | D17: 45688
C18: 44501 | D18: 45077
C19: 43374 | D19: 43890
C20: 42005 | D20: 42429
C21: 41061 | D21: 41182
B22: 过热 | C22: 43891 | D22: 44135
C23: 42430 | D23: 42613
C24: 41183 | D24: 41486
B25: 滞涨 | C25: 44136 | D25: 44347
C26: 42614 | D26: 43190
C27: 41487 | D27: 41790
C28: 40179 | D28: 40847
B31: 超额收益——分股票风格和行业
C33: 个数 | D33: 总月数 | E33: 平均月数 | F33: 时期占比 | G33: 万得全A | H33: 上证50指数 | I33: 沪深300指数 | J33: 中证500指数 | K33: 中证1000指数
B34: 衰退 | C34: 5 | D34: 37 | E34: 7.4 | F34: 0.21387283 | H34: {=INDEX(货币信用周期收益计算!$Q$26:$BT$30,MATCH($B34,货币信用周期收益计算!$Q$26:$Q$30,0),MATCH(H$33,货币信用周期收益计算!$Q$26:$BT$26,0))} -> 6.2711653 | I34: {=INDEX(货币信用周期收益计算!$Q$26:$BT$30,MATCH($B34,货币信用周期收益计算!$Q$26:$Q$30,0),MATCH(I$33,货币信用周期收益计算!$Q$26:$BT$26,0))} -> 1.6999442 | J34: {=INDEX(货币信用周期收益计算!$Q$26:$BT$30,MATCH($B34,货币信用周期收益计算!$Q$26:$Q$30,0),MATCH(J$33,货币信用周期收益计算!$Q$26:$BT$26,0))} -> -4.8075247 | K34: {=INDEX(货币信用周期收益计算!$Q$26:$BT$30,MATCH($B34,货币信用周期收益计算!$Q$26:$Q$30,0),MATCH(K$33,货币信用周期收益计算!$Q$26:$BT$26,0))} -> -8.9802067
B35: 复苏 | C35: 4 | D35: 54 | E35: 13.5 | F35: 0.31213873 | H35: {=INDEX(货币信用周期收益计算!$Q$26:$BT$30,MATCH($B35,货币信用周期收益计算!$Q$26:$Q$30,0),MATCH(H$33,货币信用周期收益计算!$Q$26:$BT$26,0))} -> -9.7688737 | I35: {=INDEX(货币信用周期收益计算!$Q$26:$BT$30,MATCH($B35,货币信用周期收益计算!$Q$26:$Q$30,0),MATCH(I$33,货币信用周期收益计算!$Q$26:$BT$26,0))} -> -7.0921684 | J35: {=INDEX(货币信用周期收益计算!$Q$26:$BT$30,MATCH($B35,货币信用周期收益计算!$Q$26:$Q$30,0),MATCH(J$33,货币信用周期收益计算!$Q$26:$BT$26,0))} -> -1.4082342 | K35: {=INDEX(货币信用周期收益计算!$Q$26:$BT$30,MATCH($B35,货币信用周期收益计算!$Q$26:$Q$30,0),MATCH(K$33,货币信用周期收益计算!$Q$26:$BT$26,0))} -> 4.9244886
B36: 过热 | C36: 4 | D36: 58 | E36: 14.5 | F36: 0.33526012 | H36: {=INDEX(货币信用周期收益计算!$Q$26:$BT$30,MATCH($B36,货币信用周期收益计算!$Q$26:$Q$30,0),MATCH(H$33,货币信用周期收益计算!$Q$26:$BT$26,0))} -> -6.4710778 | I36: {=INDEX(货币信用周期收益计算!$Q$26:$BT$30,MATCH($B36,货币信用周期收益计算!$Q$26:$Q$30,0),MATCH(I$33,货币信用周期收益计算!$Q$26:$BT$26,0))} -> -4.4345811 | J36: {=INDEX(货币信用周期收益计算!$Q$26:$BT$30,MATCH($B36,货币信用周期收益计算!$Q$26:$Q$30,0),MATCH(J$33,货币信用周期收益计算!$Q$26:$BT$26,0))} -> -1.3910279 | K36: {=INDEX(货币信用周期收益计算!$Q$26:$BT$30,MATCH($B36,货币信用周期收益计算!$Q$26:$Q$30,0),MATCH(K$33,货币信用周期收益计算!$Q$26:$BT$26,0))} -> 2.0976137
B37: 滞涨 | C37: 3 | D37: 24 | E37: 8 | F37: 0.13872832 | H37: {=INDEX(货币信用周期收益计算!$Q$26:$BT$30,MATCH($B37,货币信用周期收益计算!$Q$26:$Q$30,0),MATCH(H$33,货币信用周期收益计算!$Q$26:$BT$26,0))} -> -0.14662292 | I37: {=INDEX(货币信用周期收益计算!$Q$26:$BT$30,MATCH($B37,货币信用周期收益计算!$Q$26:$Q$30,0),MATCH(I$33,货币信用周期收益计算!$Q$26:$BT$26,0))} -> 0.48124983 | J37: {=INDEX(货币信用周期收益计算!$Q$26:$BT$30,MATCH($B37,货币信用周期收益计算!$Q$26:$Q$30,0),MATCH(J$33,货币信用周期收益计算!$Q$26:$BT$26,0))} -> 0.85859361 | K37: {=INDEX(货币信用周期收益计算!$Q$26:$BT$30,MATCH($B37,货币信用周期收益计算!$Q$26:$Q$30,0),MATCH(K$33,货币信用周期收益计算!$Q$26:$BT$26,0))} -> -0.66859444
C40: 巨潮大盘 | D40: 巨潮中盘 | E40: 巨潮小盘
B41: 衰退 | C41: {=INDEX(货币信用周期收益计算!$Q$26:$BT$30,MATCH($B41,货币信用周期收益计算!$Q$26:$Q$30,0),MATCH(C$40,货币信用周期收益计算!$Q$26:$BT$26,0))} -> 2.7109775 | D41: {=INDEX(货币信用周期收益计算!$Q$26:$BT$30,MATCH($B41,货币信用周期收益计算!$Q$26:$Q$30,0),MATCH(D$40,货币信用周期收益计算!$Q$26:$BT$26,0))} -> -4.3181068 | E41: {=INDEX(货币信用周期收益计算!$Q$26:$BT$30,MATCH($B41,货币信用周期收益计算!$Q$26:$Q$30,0),MATCH(E$40,货币信用周期收益计算!$Q$26:$BT$26,0))} -> -5.1590797
B42: 复苏 | C42: {=INDEX(货币信用周期收益计算!$Q$26:$BT$30,MATCH($B42,货币信用周期收益计算!$Q$26:$Q$30,0),MATCH(C$40,货币信用周期收益计算!$Q$26:$BT$26,0))} -> -6.7457552 | D42: {=INDEX(货币信用周期收益计算!$Q$26:$BT$30,MATCH($B42,货币信用周期收益计算!$Q$26:$Q$30,0),MATCH(D$40,货币信用周期收益计算!$Q$26:$BT$26,0))} -> -3.3032223 | E42: {=INDEX(货币信用周期收益计算!$Q$26:$BT$30,MATCH($B42,货币信用周期收益计算!$Q$26:$Q$30,0),MATCH(E$40,货币信用周期收益计算!$Q$26:$BT$26,0))} -> 0.89238212
B43: 过热 | C43: {=INDEX(货币信用周期收益计算!$Q$26:$BT$30,MATCH($B43,货币信用周期收益计算!$Q$26:$Q$30,0),MATCH(C$40,货币信用周期收益计算!$Q$26:$BT$26,0))} -> -3.5585631 | D43: {=INDEX(货币信用周期收益计算!$Q$26:$BT$30,MATCH($B43,货币信用周期收益计算!$Q$26:$Q$30,0),MATCH(D$40,货币信用周期收益计算!$Q$26:$BT$26,0))} -> -3.2906536 | E43: {=INDEX(货币信用周期收益计算!$Q$26:$BT$30,MATCH($B43,货币信用周期收益计算!$Q$26:$Q$30,0),MATCH(E$40,货币信用周期收益计算!$Q$26:$BT$26,0))} -> 0.42350762
B44: 滞涨 | C44: {=INDEX(货币信用周期收益计算!$Q$26:$BT$30,MATCH($B44,货币信用周期收益计算!$Q$26:$Q$30,0),MATCH(C$40,货币信用周期收益计算!$Q$26:$BT$26,0))} -> 1.804068 | D44: {=INDEX(货币信用周期收益计算!$Q$26:$BT$30,MATCH($B44,货币信用周期收益计算!$Q$26:$Q$30,0),MATCH(D$40,货币信用周期收益计算!$Q$26:$BT$26,0))} -> -0.90752372 | E44: {=INDEX(货币信用周期收益计算!$Q$26:$BT$30,MATCH($B44,货币信用周期收益计算!$Q$26:$Q$30,0),MATCH(E$40,货币信用周期收益计算!$Q$26:$BT$26,0))} -> -0.627679
C46: 周期 | D46: 消费 | E46: 金融 | F46: 稳定 | G46: 成长
B47: 衰退 | C47: {=INDEX(货币信用周期收益计算!$Q$26:$BT$30,MATCH($B47,货币信用周期收益计算!$Q$26:$Q$30,0),MATCH(C$46,货币信用周期收益计算!$Q$26:$BT$26,0))} -> 1.6325242 | D47: {=INDEX(货币信用周期收益计算!$Q$26:$BT$30,MATCH($B47,货币信用周期收益计算!$Q$26:$Q$30,0),MATCH(D$46,货币信用周期收益计算!$Q$26:$BT$26,0))} -> -8.1844213 | E47: {=INDEX(货币信用周期收益计算!$Q$26:$BT$30,MATCH($B47,货币信用周期收益计算!$Q$26:$Q$30,0),MATCH(E$46,货币信用周期收益计算!$Q$26:$BT$26,0))} -> 12.973694 | F47: {=INDEX(货币信用周期收益计算!$Q$26:$BT$30,MATCH($B47,货币信用周期收益计算!$Q$26:$Q$30,0),MATCH(F$46,货币信用周期收益计算!$Q$26:$BT$26,0))} -> 11.649308 | G47: {=INDEX(货币信用周期收益计算!$Q$26:$BT$30,MATCH($B47,货币信用周期收益计算!$Q$26:$Q$30,0),MATCH(G$46,货币信用周期收益计算!$Q$26:$BT$26,0))} -> -7.391588
B48: 复苏 | C48: {=INDEX(货币信用周期收益计算!$Q$26:$BT$30,MATCH($B48,货币信用周期收益计算!$Q$26:$Q$30,0),MATCH(C$46,货币信用周期收益计算!$Q$26:$BT$26,0))} -> -4.3443 | D48: {=INDEX(货币信用周期收益计算!$Q$26:$BT$30,MATCH($B48,货币信用周期收益计算!$Q$26:$Q$30,0),MATCH(D$46,货币信用周期收益计算!$Q$26:$BT$26,0))} -> 3.1181521 | E48: {=INDEX(货币信用周期收益计算!$Q$26:$BT$30,MATCH($B48,货币信用周期收益计算!$Q$26:$Q$30,0),MATCH(E$46,货币信用周期收益计算!$Q$26:$BT$26,0))} -> -2.8886725 | F48: {=INDEX(货币信用周期收益计算!$Q$26:$BT$30,MATCH($B48,货币信用周期收益计算!$Q$26:$Q$30,0),MATCH(F$46,货币信用周期收益计算!$Q$26:$BT$26,0))} -> -5.7442499 | G48: {=INDEX(货币信用周期收益计算!$Q$26:$BT$30,MATCH($B48,货币信用周期收益计算!$Q$26:$Q$30,0),MATCH(G$46,货币信用周期收益计算!$Q$26:$BT$26,0))} -> 6.4292889
B49: 过热 | C49: {=INDEX(货币信用周期收益计算!$Q$26:$BT$30,MATCH($B49,货币信用周期收益计算!$Q$26:$Q$30,0),MATCH(C$46,货币信用周期收益计算!$Q$26:$BT$26,0))} -> -3.6119672 | D49: {=INDEX(货币信用周期收益计算!$Q$26:$BT$30,MATCH($B49,货币信用周期收益计算!$Q$26:$Q$30,0),MATCH(D$46,货币信用周期收益计算!$Q$26:$BT$26,0))} -> 8.4513097 | E49: {=INDEX(货币信用周期收益计算!$Q$26:$BT$30,MATCH($B49,货币信用周期收益计算!$Q$26:$Q$30,0),MATCH(E$46,货币信用周期收益计算!$Q$26:$BT$26,0))} -> -3.8241406 | F49: {=INDEX(货币信用周期收益计算!$Q$26:$BT$30,MATCH($B49,货币信用周期收益计算!$Q$26:$Q$30,0),MATCH(F$46,货币信用周期收益计算!$Q$26:$BT$26,0))} -> -7.8242854 | G49: {=INDEX(货币信用周期收益计算!$Q$26:$BT$30,MATCH($B49,货币信用周期收益计算!$Q$26:$Q$30,0),MATCH(G$46,货币信用周期收益计算!$Q$26:$BT$26,0))} -> 8.9106603
B50: 滞涨 | C50: {=INDEX(货币信用周期收益计算!$Q$26:$BT$30,MATCH($B50,货币信用周期收益计算!$Q$26:$Q$30,0),MATCH(C$46,货币信用周期收益计算!$Q$26:$BT$26,0))} -> 0.5115954 | D50: {=INDEX(货币信用周期收益计算!$Q$26:$BT$30,MATCH($B50,货币信用周期收益计算!$Q$26:$Q$30,0),MATCH(D$46,货币信用周期收益计算!$Q$26:$BT$26,0))} -> 8.4511109 | E50: {=INDEX(货币信用周期收益计算!$Q$26:$BT$30,MATCH($B50,货币信用周期收益计算!$Q$26:$Q$30,0),MATCH(E$46,货币信用周期收益计算!$Q$26:$BT$26,0))} -> -5.0305913 | F50: {=INDEX(货币信用周期收益计算!$Q$26:$BT$30,MATCH($B50,货币信用周期收益计算!$Q$26:$Q$30,0),MATCH(F$46,货币信用周期收益计算!$Q$26:$BT$26,0))} -> -4.4765763 | G50: {=INDEX(货币信用周期收益计算!$Q$26:$BT$30,MATCH($B50,货币信用周期收益计算!$Q$26:$Q$30,0),MATCH(G$46,货币信用周期收益计算!$Q$26:$BT$26,0))} -> 1.8132762
C52: 红利指数 | D52: 国证红利 | E52: 深证红利 | F52: 万得红利 | G52: 中证红利
B53: 衰退 | C53: {=INDEX(货币信用周期收益计算!$Q$26:$BT$30,MATCH($B53,货币信用周期收益计算!$Q$26:$Q$30,0),MATCH(C$52,货币信用周期收益计算!$Q$26:$BT$26,0))} -> 5.0919474 | D53: {=INDEX(货币信用周期收益计算!$Q$26:$BT$30,MATCH($B53,货币信用周期收益计算!$Q$26:$Q$30,0),MATCH(D$52,货币信用周期收益计算!$Q$26:$BT$26,0))} -> 6.9185009 | E53: {=INDEX(货币信用周期收益计算!$Q$26:$BT$30,MATCH($B53,货币信用周期收益计算!$Q$26:$Q$30,0),MATCH(E$52,货币信用周期收益计算!$Q$26:$BT$26,0))} -> -0.54076634 | F53: {=INDEX(货币信用周期收益计算!$Q$26:$BT$30,MATCH($B53,货币信用周期收益计算!$Q$26:$Q$30,0),MATCH(F$52,货币信用周期收益计算!$Q$26:$BT$26,0))} -> -6.569286 | G53: {=INDEX(货币信用周期收益计算!$Q$26:$BT$30,MATCH($B53,货币信用周期收益计算!$Q$26:$Q$30,0),MATCH(G$52,货币信用周期收益计算!$Q$26:$BT$26,0))} -> 3.7629755
B54: 复苏 | C54: {=INDEX(货币信用周期收益计算!$Q$26:$BT$30,MATCH($B54,货币信用周期收益计算!$Q$26:$Q$30,0),MATCH(C$52,货币信用周期收益计算!$Q$26:$BT$26,0))} -> -5.1993841 | D54: {=INDEX(货币信用周期收益计算!$Q$26:$BT$30,MATCH($B54,货币信用周期收益计算!$Q$26:$Q$30,0),MATCH(D$52,货币信用周期收益计算!$Q$26:$BT$26,0))} -> -5.8254295 | E54: {=INDEX(货币信用周期收益计算!$Q$26:$BT$30,MATCH($B54,货币信用周期收益计算!$Q$26:$Q$30,0),MATCH(E$52,货币信用周期收益计算!$Q$26:$BT$26,0))} -> -2.8585997 | F54: {=INDEX(货币信用周期收益计算!$Q$26:$BT$30,MATCH($B54,货币信用周期收益计算!$Q$26:$Q$30,0),MATCH(F$52,货币信用周期收益计算!$Q$26:$BT$26,0))} -> 1.542416 | G54: {=INDEX(货币信用周期收益计算!$Q$26:$BT$30,MATCH($B54,货币信用周期收益计算!$Q$26:$Q$30,0),MATCH(G$52,货币信用周期收益计算!$Q$26:$BT$26,0))} -> -1.7998185
B55: 过热 | C55: {=INDEX(货币信用周期收益计算!$Q$26:$BT$30,MATCH($B55,货币信用周期收益计算!$Q$26:$Q$30,0),MATCH(C$52,货币信用周期收益计算!$Q$26:$BT$26,0))} -> -10.883368 | D55: {=INDEX(货币信用周期收益计算!$Q$26:$BT$30,MATCH($B55,货币信用周期收益计算!$Q$26:$Q$30,0),MATCH(D$52,货币信用周期收益计算!$Q$26:$BT$26,0))} -> -4.3221471 | E55: {=INDEX(货币信用周期收益计算!$Q$26:$BT$30,MATCH($B55,货币信用周期收益计算!$Q$26:$Q$30,0),MATCH(E$52,货币信用周期收益计算!$Q$26:$BT$26,0))} -> -1.659945 | F55: {=INDEX(货币信用周期收益计算!$Q$26:$BT$30,MATCH($B55,货币信用周期收益计算!$Q$26:$Q$30,0),MATCH(F$52,货币信用周期收益计算!$Q$26:$BT$26,0))} -> -11.480798 | G55: {=INDEX(货币信用周期收益计算!$Q$26:$BT$30,MATCH($B55,货币信用周期收益计算!$Q$26:$Q$30,0),MATCH(G$52,货币信用周期收益计算!$Q$26:$BT$26,0))} -> -8.1579475
B56: 滞涨 | C56: {=INDEX(货币信用周期收益计算!$Q$26:$BT$30,MATCH($B56,货币信用周期收益计算!$Q$26:$Q$30,0),MATCH(C$52,货币信用周期收益计算!$Q$26:$BT$26,0))} -> -1.0723652 | D56: {=INDEX(货币信用周期收益计算!$Q$26:$BT$30,MATCH($B56,货币信用周期收益计算!$Q$26:$Q$30,0),MATCH(D$52,货币信用周期收益计算!$Q$26:$BT$26,0))} -> 4.6730184 | E56: {=INDEX(货币信用周期收益计算!$Q$26:$BT$30,MATCH($B56,货币信用周期收益计算!$Q$26:$Q$30,0),MATCH(E$52,货币信用周期收益计算!$Q$26:$BT$26,0))} -> 7.2705765 | F56: {=INDEX(货币信用周期收益计算!$Q$26:$BT$30,MATCH($B56,货币信用周期收益计算!$Q$26:$Q$30,0),MATCH(F$52,货币信用周期收益计算!$Q$26:$BT$26,0))} -> 7.702316 | G56: {=INDEX(货币信用周期收益计算!$Q$26:$BT$30,MATCH($B56,货币信用周期收益计算!$Q$26:$Q$30,0),MATCH(G$52,货币信用周期收益计算!$Q$26:$BT$26,0))} -> 1.9189307
C58: 低估值指数(长江) | D58: 高估值指数(长江)
B59: 衰退 | C59: {=INDEX(货币信用周期收益计算!$Q$26:$BT$30,MATCH($B59,货币信用周期收益计算!$Q$26:$Q$30,0),MATCH(C$58,货币信用周期收益计算!$Q$26:$BT$26,0))} -> 7.4846877 | D59: {=INDEX(货币信用周期收益计算!$Q$26:$BT$30,MATCH($B59,货币信用周期收益计算!$Q$26:$Q$30,0),MATCH(D$58,货币信用周期收益计算!$Q$26:$BT$26,0))} -> -13.639966
B60: 复苏 | C60: {=INDEX(货币信用周期收益计算!$Q$26:$BT$30,MATCH($B60,货币信用周期收益计算!$Q$26:$Q$30,0),MATCH(C$58,货币信用周期收益计算!$Q$26:$BT$26,0))} -> -4.1831918 | D60: {=INDEX(货币信用周期收益计算!$Q$26:$BT$30,MATCH($B60,货币信用周期收益计算!$Q$26:$Q$30,0),MATCH(D$58,货币信用周期收益计算!$Q$26:$BT$26,0))} -> 7.1649212
B61: 过热 | C61: {=INDEX(货币信用周期收益计算!$Q$26:$BT$30,MATCH($B61,货币信用周期收益计算!$Q$26:$Q$30,0),MATCH(C$58,货币信用周期收益计算!$Q$26:$BT$26,0))} -> -9.3465334 | D61: {=INDEX(货币信用周期收益计算!$Q$26:$BT$30,MATCH($B61,货币信用周期收益计算!$Q$26:$Q$30,0),MATCH(D$58,货币信用周期收益计算!$Q$26:$BT$26,0))} -> 0.232842
B62: 滞涨 | C62: {=INDEX(货币信用周期收益计算!$Q$26:$BT$30,MATCH($B62,货币信用周期收益计算!$Q$26:$Q$30,0),MATCH(C$58,货币信用周期收益计算!$Q$26:$BT$26,0))} -> -0.23150899 | D62: {=INDEX(货币信用周期收益计算!$Q$26:$BT$30,MATCH($B62,货币信用周期收益计算!$Q$26:$Q$30,0),MATCH(D$58,货币信用周期收益计算!$Q$26:$BT$26,0))} -> -2.4273023
C65: 农林牧渔 | D65: 基础化工 | E65: 钢铁 | F65: 有色金属 | G65: 电子 | H65: 家用电器 | I65: 食品饮料 | J65: 纺织服饰 | K65: 轻工制造 | L65: 医药生物 | M65: 公用事业 | N65: 交通运输 | O65: 房地产 | P65: 商贸零售 | Q65: 社会服务 | R65: 综合 | S65: 建筑材料 | T65: 建筑装饰 | U65: 电力设备 | V65: 国防军工 | W65: 计算机 | X65: 传媒 | Y65: 通信 | Z65: 银行 | AA65: 非银金融 | AB65: 汽车 | AC65: 机械设备 | AD65: 煤炭 | AE65: 石油石化 | AF65: 环保 | AG65: 美容护理
B66: 衰退 | C66: {=INDEX(货币信用周期收益计算!$Q$26:$BT$30,MATCH($B66,货币信用周期收益计算!$Q$26:$Q$30,0),MATCH(C$65,货币信用周期收益计算!$Q$26:$BT$26,0))} -> -7.1514844 | D66: {=INDEX(货币信用周期收益计算!$Q$26:$BT$30,MATCH($B66,货币信用周期收益计算!$Q$26:$Q$30,0),MATCH(D$65,货币信用周期收益计算!$Q$26:$BT$26,0))} -> -2.1255847 | E66: {=INDEX(货币信用周期收益计算!$Q$26:$BT$30,MATCH($B66,货币信用周期收益计算!$Q$26:$Q$30,0),MATCH(E$65,货币信用周期收益计算!$Q$26:$BT$26,0))} -> 9.3287976 | F66: {=INDEX(货币信用周期收益计算!$Q$26:$BT$30,MATCH($B66,货币信用周期收益计算!$Q$26:$Q$30,0),MATCH(F$65,货币信用周期收益计算!$Q$26:$BT$26,0))} -> 1.6883924 | G66: {=INDEX(货币信用周期收益计算!$Q$26:$BT$30,MATCH($B66,货币信用周期收益计算!$Q$26:$Q$30,0),MATCH(G$65,货币信用周期收益计算!$Q$26:$BT$26,0))} -> -12.404261 | H66: {=INDEX(货币信用周期收益计算!$Q$26:$BT$30,MATCH($B66,货币信用周期收益计算!$Q$26:$Q$30,0),MATCH(H$65,货币信用周期收益计算!$Q$26:$BT$26,0))} -> -3.2889531 | I66: {=INDEX(货币信用周期收益计算!$Q$26:$BT$30,MATCH($B66,货币信用周期收益计算!$Q$26:$Q$30,0),MATCH(I$65,货币信用周期收益计算!$Q$26:$BT$26,0))} -> -4.7311593 | J66: {=INDEX(货币信用周期收益计算!$Q$26:$BT$30,MATCH($B66,货币信用周期收益计算!$Q$26:$Q$30,0),MATCH(J$65,货币信用周期收益计算!$Q$26:$BT$26,0))} -> -8.3051723 | ... AG66: {=INDEX(货币信用周期收益计算!$Q$26:$BT$30,MATCH($B66,货币信用周期收益计算!$Q$26:$Q$30,0),MATCH(AG$65,货币信用周期收益计算!$Q$26:$BT$26,0))} -> -18.204826
B67: 复苏 | C67: {=INDEX(货币信用周期收益计算!$Q$26:$BT$30,MATCH($B67,货币信用周期收益计算!$Q$26:$Q$30,0),MATCH(C$65,货币信用周期收益计算!$Q$26:$BT$26,0))} -> 9.0363704 | D67: {=INDEX(货币信用周期收益计算!$Q$26:$BT$30,MATCH($B67,货币信用周期收益计算!$Q$26:$Q$30,0),MATCH(D$65,货币信用周期收益计算!$Q$26:$BT$26,0))} -> -4.3394098 | E67: {=INDEX(货币信用周期收益计算!$Q$26:$BT$30,MATCH($B67,货币信用周期收益计算!$Q$26:$Q$30,0),MATCH(E$65,货币信用周期收益计算!$Q$26:$BT$26,0))} -> -18.431086 | F67: {=INDEX(货币信用周期收益计算!$Q$26:$BT$30,MATCH($B67,货币信用周期收益计算!$Q$26:$Q$30,0),MATCH(F$65,货币信用周期收益计算!$Q$26:$BT$26,0))} -> -7.8031532 | G67: {=INDEX(货币信用周期收益计算!$Q$26:$BT$30,MATCH($B67,货币信用周期收益计算!$Q$26:$Q$30,0),MATCH(G$65,货币信用周期收益计算!$Q$26:$BT$26,0))} -> 16.96234 | H67: {=INDEX(货币信用周期收益计算!$Q$26:$BT$30,MATCH($B67,货币信用周期收益计算!$Q$26:$Q$30,0),MATCH(H$65,货币信用周期收益计算!$Q$26:$BT$26,0))} -> 4.327144 | I67: {=INDEX(货币信用周期收益计算!$Q$26:$BT$30,MATCH($B67,货币信用周期收益计算!$Q$26:$Q$30,0),MATCH(I$65,货币信用周期收益计算!$Q$26:$BT$26,0))} -> 0.63629651 | J67: {=INDEX(货币信用周期收益计算!$Q$26:$BT$30,MATCH($B67,货币信用周期收益计算!$Q$26:$Q$30,0),MATCH(J$65,货币信用周期收益计算!$Q$26:$BT$26,0))} -> 3.7084232 | ... AG67: {=INDEX(货币信用周期收益计算!$Q$26:$BT$30,MATCH($B67,货币信用周期收益计算!$Q$26:$Q$30,0),MATCH(AG$65,货币信用周期收益计算!$Q$26:$BT$26,0))} -> 2.0307845
B68: 过热 | C68: {=INDEX(货币信用周期收益计算!$Q$26:$BT$30,MATCH($B68,货币信用周期收益计算!$Q$26:$Q$30,0),MATCH(C$65,货币信用周期收益计算!$Q$26:$BT$26,0))} -> -8.0865459 | D68: {=INDEX(货币信用周期收益计算!$Q$26:$BT$30,MATCH($B68,货币信用周期收益计算!$Q$26:$Q$30,0),MATCH(D$65,货币信用周期收益计算!$Q$26:$BT$26,0))} -> 1.731574 | E68: {=INDEX(货币信用周期收益计算!$Q$26:$BT$30,MATCH($B68,货币信用周期收益计算!$Q$26:$Q$30,0),MATCH(E$65,货币信用周期收益计算!$Q$26:$BT$26,0))} -> -14.904032 | F68: {=INDEX(货币信用周期收益计算!$Q$26:$BT$30,MATCH($B68,货币信用周期收益计算!$Q$26:$Q$30,0),MATCH(F$65,货币信用周期收益计算!$Q$26:$BT$26,0))} -> -12.516708 | G68: {=INDEX(货币信用周期收益计算!$Q$26:$BT$30,MATCH($B68,货币信用周期收益计算!$Q$26:$Q$30,0),MATCH(G$65,货币信用周期收益计算!$Q$26:$BT$26,0))} -> 7.4348767 | H68: {=INDEX(货币信用周期收益计算!$Q$26:$BT$30,MATCH($B68,货币信用周期收益计算!$Q$26:$Q$30,0),MATCH(H$65,货币信用周期收益计算!$Q$26:$BT$26,0))} -> 7.8135429 | I68: {=INDEX(货币信用周期收益计算!$Q$26:$BT$30,MATCH($B68,货币信用周期收益计算!$Q$26:$Q$30,0),MATCH(I$65,货币信用周期收益计算!$Q$26:$BT$26,0))} -> 13.026547 | J68: {=INDEX(货币信用周期收益计算!$Q$26:$BT$30,MATCH($B68,货币信用周期收益计算!$Q$26:$Q$30,0),MATCH(J$65,货币信用周期收益计算!$Q$26:$BT$26,0))} -> -13.647461 | ... AG68: {=INDEX(货币信用周期收益计算!$Q$26:$BT$30,MATCH($B68,货币信用周期收益计算!$Q$26:$Q$30,0),MATCH(AG$65,货币信用周期收益计算!$Q$26:$BT$26,0))} -> 18.443424
B69: 滞涨 | C69: {=INDEX(货币信用周期收益计算!$Q$26:$BT$30,MATCH($B69,货币信用周期收益计算!$Q$26:$Q$30,0),MATCH(C$65,货币信用周期收益计算!$Q$26:$BT$26,0))} -> -2.1564286 | D69: {=INDEX(货币信用周期收益计算!$Q$26:$BT$30,MATCH($B69,货币信用周期收益计算!$Q$26:$Q$30,0),MATCH(D$65,货币信用周期收益计算!$Q$26:$BT$26,0))} -> -1.9214108 | E69: {=INDEX(货币信用周期收益计算!$Q$26:$BT$30,MATCH($B69,货币信用周期收益计算!$Q$26:$Q$30,0),MATCH(E$65,货币信用周期收益计算!$Q$26:$BT$26,0))} -> 4.9983183 | F69: {=INDEX(货币信用周期收益计算!$Q$26:$BT$30,MATCH($B69,货币信用周期收益计算!$Q$26:$Q$30,0),MATCH(F$65,货币信用周期收益计算!$Q$26:$BT$26,0))} -> 10.259794 | G69: {=INDEX(货币信用周期收益计算!$Q$26:$BT$30,MATCH($B69,货币信用周期收益计算!$Q$26:$Q$30,0),MATCH(G$65,货币信用周期收益计算!$Q$26:$BT$26,0))} -> 6.1684242 | H69: {=INDEX(货币信用周期收益计算!$Q$26:$BT$30,MATCH($B69,货币信用周期收益计算!$Q$26:$Q$30,0),MATCH(H$65,货币信用周期收益计算!$Q$26:$BT$26,0))} -> 14.275673 | I69: {=INDEX(货币信用周期收益计算!$Q$26:$BT$30,MATCH($B69,货币信用周期收益计算!$Q$26:$Q$30,0),MATCH(I$65,货币信用周期收益计算!$Q$26:$BT$26,0))} -> 22.109569 | J69: {=INDEX(货币信用周期收益计算!$Q$26:$BT$30,MATCH($B69,货币信用周期收益计算!$Q$26:$Q$30,0),MATCH(J$65,货币信用周期收益计算!$Q$26:$BT$26,0))} -> -2.3410486 | ... AG69: {=INDEX(货币信用周期收益计算!$Q$26:$BT$30,MATCH($B69,货币信用周期收益计算!$Q$26:$Q$30,0),MATCH(AG$65,货币信用周期收益计算!$Q$26:$BT$26,0))} -> 9.2595095
B72: 绝对收益——分股票风格和行业
C74: 个数 | D74: 总月数 | E74: 平均月数 | F74: 时期占比 | G74: 万得全A | H74: 上证50指数 | I74: 沪深300指数 | J74: 中证500指数 | K74: 中证1000指数
B75: 衰退 | C75: 5 | D75: 37 | E75: 7.4 | F75: 0.21387283 | G75: 5.5086636 | H75: 11.779829 | I75: 7.2086078 | J75: 0.70113889 | K75: -3.4715431
B76: 复苏 | C76: 4 | D76: 54 | E76: 13.5 | F76: 0.31213873 | G76: -2.4082881 | H76: -12.686899 | I76: -9.8728081 | J76: -3.6406277 | K76: 2.9781269
B77: 过热 | C77: 4 | D77: 58 | E77: 14.5 | F77: 0.33526012 | G77: 0.62170339 | H77: 0.47508047 | I77: 1.1029532 | J77: 1.480297 | K77: -0.046891041
B78: 滞涨 | C78: 3 | D78: 24 | E78: 8 | F78: 0.13872832 | G78: 14.586233 | H78: 8.1151554 | I78: 10.151652 | J78: 13.195205 | K78: 16.683847
C81: 周期 | D81: 消费 | E81: 金融 | F81: 稳定 | G81: 成长
B82: 衰退 | C82: 7.1411878 | D82: -2.6757577 | E82: 18.482357 | F82: 17.157972 | G82: -1.8829245
B83: 复苏 | C83: -6.4050419 | D83: 3.391845 | E83: -7.1689466 | F83: -5.5720444 | G83: 3.9640715
B84: 过热 | C84: 1.1332988 | D84: 9.0728143 | E84: -4.408888 | F84: -3.8548729 | G84: 2.4349796
B85: 滞涨 | C85: 10.974266 | D85: 23.037543 | E85: 10.762093 | F85: 6.7619478 | G85: 23.496894
C87: 红利指数 | D87: 国证红利 | E87: 深证红利 | F87: 万得红利 | G87: 中证红利
B88: 衰退 | C88: 10.600611 | D88: 12.427164 | E88: 4.9678972 | F88: -1.7677041 | G88: 9.271639
B89: 复苏 | C89: -5.9294492 | D89: -7.8342782 | E89: -3.8776197 | F89: 3.1437247 | G89: -1.9168742
B90: 过热 | C90: -0.45066182 | D90: 5.2947218 | E90: 7.8922799 | F90: 16.648039 | G90: 2.5406341
B91: 滞涨 | C91: 3.7028649 | D91: 10.264086 | E91: 12.926288 | F91: 9.3163058 | G91: 6.4282857
C93: 低估值指数(长江) | D93: 高估值指数(长江)
B94: 衰退 | C94: 12.993351 | D94: -8.1313021
B95: 复苏 | C95: -7.7281761 | D95: 4.2812963
B96: 过热 | C96: 0.39019441 | D96: -1.8055989
B97: 滞涨 | C97: 5.2396998 | D97: 14.819075
C100: 巨潮大盘 | D100: 巨潮中盘 | E100: 巨潮小盘
B101: 衰退 | C101: 8.2196411 | D101: 1.1905568 | E101: 0.34958388
B102: 复苏 | C102: -9.5591807 | D102: -5.6539938 | E102: -0.82575814
B103: 过热 | C103: 2.4257713 | D103: -0.28582032 | E103: -0.0059756089
B104: 滞涨 | C104: 11.02767 | D104: 11.29558 | E104: 15.009741
C106: 农林牧渔 | D106: 基础化工 | E106: 钢铁 | F106: 有色金属 | G106: 电子 | H106: 家用电器 | I106: 食品饮料 | J106: 纺织服饰 | K106: 轻工制造 | L106: 医药生物 | M106: 公用事业 | N106: 交通运输 | O106: 房地产 | P106: 商贸零售 | Q106: 社会服务 | R106: 综合 | S106: 建筑材料 | T106: 建筑装饰 | U106: 电力设备 | V106: 国防军工 | W106: 计算机 | X106: 传媒 | Y106: 通信 | Z106: 银行 | AA106: 非银金融 | AB106: 汽车 | AC106: 机械设备 | AD106: 煤炭 | AE106: 石油石化 | AF106: 环保 | AG106: 美容护理
B107: 衰退 | C107: -1.6428209 | D107: 3.3830789 | E107: 14.837461 | F107: 7.197056 | G107: -6.8955977 | H107: 2.2197105 | I107: 0.77750429 | J107: -2.7965087 | K107: -7.7033305 | L107: -8.6619051 | M107: 11.35666 | N107: 7.858833 | O107: 2.7654868 | P107: -4.9001734 | Q107: -4.7424646 | R107: -4.98953 | S107: -3.0373909 | T107: 12.779766 | U107: 0.89386925 | V107: 6.5652462 | W107: -7.3244211 | X107: -14.181792 | Y107: -3.4902792 | Z107: 12.010075 | AA107: 24.346687 | AB107: 6.7302235 | AC107: 2.9123848 | AD107: 16.556072 | AE107: 7.5330408 | AF107: -1.1882705 | AG107: -12.696163
B108: 复苏 | C108: 13.19131 | D108: -6.4766258 | E108: -23.76348 | F108: -10.24638 | G108: 15.78173 | H108: 2.7468269 | I108: 1.5682567 | J108: 1.9749022 | K108: 1.0507593 | L108: 4.5030178 | M108: -7.7347174 | N108: -9.2271919 | O108: -4.8927603 | P108: -12.916825 | Q108: 2.758559 | R108: 7.7962374 | S108: -5.0407172 | T108: -8.292348 | U108: -4.9249001 | V108: -7.0991993 | W108: 19.959115 | X108: 13.745293 | Y108: 15.838321 | Z108: -10.707589 | AA108: -11.266044 | AB108: -7.675912 | AC108: -5.0129935 | AD108: -12.074965 | AE108: -14.89156 | AF108: -8.0668799 | AG108: 3.4176528
B109: 过热 | C109: -1.5347252 | D109: -1.2997074 | E109: 5.6200217 | F109: 10.881497 | G109: 6.7901276 | H109: 14.897376 | I109: 22.731273 | J109: -1.7193452 | K109: 1.1195779 | L109: 6.116325 | M109: -7.4634763 | N109: -0.99840929 | O109: -9.7068214 | P109: -4.0018429 | Q109: 16.944832 | R109: 0.0076464541 | S109: 9.112721 | T109: -6.2365081 | U109: 5.4200585 | V109: -0.40683416 | W109: 1.7237425 | X109: -10.309225 | Y109: -8.0883052 | Z109: 2.0466603 | AA109: -7.6585771 | AB109: -2.7955715 | AC109: 1.8949776 | AD109: -1.7114852 | AE109: -1.0366165 | AF109: -7.1246475 | AG109: 9.8812129
B110: 滞涨 | C110: 6.4996873 | D110: 16.317807 | E110: -0.31779926 | F110: 2.0695254 | G110: 22.02111 | H110: 22.399776 | I110: 27.612781 | J110: 0.93877176 | K110: 18.345211 | L110: 30.767779 | M110: 11.637218 | N110: 3.4933972 | O110: 7.3004533 | P110: 7.9841595 | Q110: 28.866832 | R110: 14.248417 | S110: 11.712802 | T110: 7.6285038 | U110: 28.411008 | V110: 20.519327 | W110: 17.021726 | X110: 34.285907 | Y110: 8.5664627 | Z110: 8.5245208 | AA110: 5.919039 | AB110: 22.57825 | AC110: 13.609347 | AD110: -6.7665195 | AE110: 3.7502779 | AF110: 27.90552 | AG110: 33.029658

Sheet 流程图
B2: 本页内容： 一、研究流程图 二、股债表现与经济周期对应图 三、风格指数汇总
B8: 研究流程图 | J8: 股债表现与经济周期对应图
B54: 风格指数汇总
B56: 风格 | C56: 代码 | D56: 指数
B57: 大中小盘 | C57: 399314.SZ | D57: 巨潮大盘
C58: 399315.SZ | D58: 巨潮中盘
C59: 399316.SZ | D59: 巨潮小盘
C60: 000016.SH | D60: 上证50指数
C61: 000300.SH | D61: 沪深300指数
C62: 000905.SH | D62: 中证500指数
C63: 000852.SH | D63: 中证1000指数
B64: 中信风格 | C64: CI005918.WI | D64: 周期
C65: CI005919.WI | D65: 消费
C66: CI005917.WI | D66: 金融
C67: CI005921.WI | D67: 稳定
C68: CI005920.WI | D68: 成长
B69: 红利 | C69: 399321.SZ | D69: 国证红利
C70: 399324.SZ | D70: 深证红利
C71: 867001.WI | D71: 万得红利
C72: 000922.CSI | D72: 中证红利
B73: 估值 | C73: 861101.CJ | D73: 低估值指数(长江)
C74: 861102.CJ | D74: 高估值指数(长江)
B75: 行业 | C75: 31个申万一级行业

Sheet 框架指示的股债胜率（综合）
J3: 美林时钟 | K3: 美林时钟 | L3: 货币信用周期 | M3: 货币信用周期 | N3: 财政货币周期 | O3: 财政货币周期 | P3: 信贷库存周期 | Q3: 信贷库存周期 | R3: 产能库存周期嵌套 | S3: 产能库存周期嵌套 | T3: 综合打分 | V3: 打分指示的股债强弱 | W3: 实际股债强弱（十年国债口径） | X3: 实际股债强弱（中证债基口径） | Y3: 打分指示的股债强弱(向前滚动5年、右轴) | Z3: 实际股债强弱（十年国债口径） | AA3: 实际股债强弱（中证债基口径）
B4: 万得全A:月:最后一条:环比 | C4: 中国:中债国债到期收益率:10年:月:平均值:环比增加:*100 | D4: 中证基金指数:债券基金:月:最后一条:环比 | E4: 美林时钟 | F4: 货币信用周期 | G4: 财政货币周期 | H4: 信贷库存周期 | I4: 产能库存周期嵌套 | J4: 股票 | K4: 债券 | L4: 股票 | M4: 债券 | N4: 股票 | O4: 债券 | P4: 股票 | Q4: 债券 | R4: 股票 | S4: 债券 | T4: 股票 | U4: 债券
A5: 46387 | E5: =VLOOKUP(A5,美林时钟!#REF!,28,TRUE) -> #REF! | F5: 宽货币紧信用 | G5: 紧货币宽财政 | H5: 被动去库存 | I5: 产能周期下行,主动补库存 | J5: {=INDEX(股债表现与四个维度!$A:$T,MATCH($A5,股债表现与四个维度!$A:$A,0),MATCH(J$3&J$4,股债表现与四个维度!$2:$2&股债表现与四个维度!$3:$3,0))} -> -0.076923077 | K5: {=INDEX(股债表现与四个维度!$A:$T,MATCH($A5,股债表现与四个维度!$A:$A,0),MATCH(K$3&K$4,股债表现与四个维度!$2:$2&股债表现与四个维度!$3:$3,0))} -> 0.15384615 | L5: {=INDEX(股债表现与四个维度!$A:$T,MATCH($A5,股债表现与四个维度!$A:$A,0),MATCH(L$3&L$4,股债表现与四个维度!$2:$2&股债表现与四个维度!$3:$3,0))} -> -0.083333333 | M5: {=INDEX(股债表现与四个维度!$A:$T,MATCH($A5,股债表现与四个维度!$A:$A,0),MATCH(M$3&M$4,股债表现与四个维度!$2:$2&股债表现与四个维度!$3:$3,0))} -> 0.56666667 | N5: {=INDEX(股债表现与四个维度!$A:$T,MATCH($A5,股债表现与四个维度!$A:$A,0),MATCH(N$3&N$4,股债表现与四个维度!$2:$2&股债表现与四个维度!$3:$3,0))} -> -0.043478261 | O5: {=INDEX(股债表现与四个维度!$A:$T,MATCH($A5,股债表现与四个维度!$A:$A,0),MATCH(O$3&O$4,股债表现与四个维度!$2:$2&股债表现与四个维度!$3:$3,0))} -> 0.95652174 | P5: {=INDEX(股债表现与四个维度!$A:$T,MATCH($A5,股债表现与四个维度!$A:$A,0),MATCH(P$3&P$4,股债表现与四个维度!$2:$2&股债表现与四个维度!$3:$3,0))} -> -0.076923077 | Q5: {=INDEX(股债表现与四个维度!$A:$T,MATCH($A5,股债表现与四个维度!$A:$A,0),MATCH(Q$3&Q$4,股债表现与四个维度!$2:$2&股债表现与四个维度!$3:$3,0))} -> 0.57692308 | ... S5: {=INDEX(股债表现与四个维度!$A:$T,MATCH($A5,股债表现与四个维度!$A:$A,0),MATCH(S$3&S$4,股债表现与四个维度!$2:$2&股债表现与四个维度!$3:$3,0))} -> 0.77777778 | T5: =SUMIFS($J5:$S5,$J5:$S5,"<>"&"#N/A",$J$4:$S$4,T$4) -> -0.3362133 | U5: =SUMIFS($J5:$S5,$J5:$S5,"<>"&"#N/A",$J$4:$S$4,U$4) -> 3.0317354 | V5: =T5-U5 -> -3.3679487
A6: 46356 | E6: =VLOOKUP(A6,美林时钟!#REF!,28,TRUE) -> #REF! | F6: 宽货币紧信用 | G6: 紧货币宽财政 | H6: 被动去库存 | I6: 产能周期下行,主动补库存 | J6: {=INDEX(股债表现与四个维度!$A:$T,MATCH($A6,股债表现与四个维度!$A:$A,0),MATCH(J$3&J$4,股债表现与四个维度!$2:$2&股债表现与四个维度!$3:$3,0))} -> -0.083333333 | K6: {=INDEX(股债表现与四个维度!$A:$T,MATCH($A6,股债表现与四个维度!$A:$A,0),MATCH(K$3&K$4,股债表现与四个维度!$2:$2&股债表现与四个维度!$3:$3,0))} -> 0.083333333 | L6: {=INDEX(股债表现与四个维度!$A:$T,MATCH($A6,股债表现与四个维度!$A:$A,0),MATCH(L$3&L$4,股债表现与四个维度!$2:$2&股债表现与四个维度!$3:$3,0))} -> -0.083333333 | M6: {=INDEX(股债表现与四个维度!$A:$T,MATCH($A6,股债表现与四个维度!$A:$A,0),MATCH(M$3&M$4,股债表现与四个维度!$2:$2&股债表现与四个维度!$3:$3,0))} -> 0.53333333 | N6: {=INDEX(股债表现与四个维度!$A:$T,MATCH($A6,股债表现与四个维度!$A:$A,0),MATCH(N$3&N$4,股债表现与四个维度!$2:$2&股债表现与四个维度!$3:$3,0))} -> -0.045454545 | O6: {=INDEX(股债表现与四个维度!$A:$T,MATCH($A6,股债表现与四个维度!$A:$A,0),MATCH(O$3&O$4,股债表现与四个维度!$2:$2&股债表现与四个维度!$3:$3,0))} -> 0.95454545 | P6: {=INDEX(股债表现与四个维度!$A:$T,MATCH($A6,股债表现与四个维度!$A:$A,0),MATCH(P$3&P$4,股债表现与四个维度!$2:$2&股债表现与四个维度!$3:$3,0))} -> -0.08 | Q6: {=INDEX(股债表现与四个维度!$A:$T,MATCH($A6,股债表现与四个维度!$A:$A,0),MATCH(Q$3&Q$4,股债表现与四个维度!$2:$2&股债表现与四个维度!$3:$3,0))} -> 0.56 | ... S6: {=INDEX(股债表现与四个维度!$A:$T,MATCH($A6,股债表现与四个维度!$A:$A,0),MATCH(S$3&S$4,股债表现与四个维度!$2:$2&股债表现与四个维度!$3:$3,0))} -> 0.77142857 | T6: =SUMIFS($J6:$S6,$J6:$S6,"<>"&"#N/A",$J$4:$S$4,T$4) -> -0.34926407 | U6: =SUMIFS($J6:$S6,$J6:$S6,"<>"&"#N/A",$J$4:$S$4,U$4) -> 2.9026407 | V6: =T6-U6 -> -3.2519048
A7: 46326 | E7: =VLOOKUP(A7,美林时钟!#REF!,28,TRUE) -> #REF! | F7: 宽货币紧信用 | G7: 紧货币宽财政 | H7: 被动去库存 | I7: 产能周期下行,主动补库存 | J7: {=INDEX(股债表现与四个维度!$A:$T,MATCH($A7,股债表现与四个维度!$A:$A,0),MATCH(J$3&J$4,股债表现与四个维度!$2:$2&股债表现与四个维度!$3:$3,0))} -> -0.090909091 | K7: {=INDEX(股债表现与四个维度!$A:$T,MATCH($A7,股债表现与四个维度!$A:$A,0),MATCH(K$3&K$4,股债表现与四个维度!$2:$2&股债表现与四个维度!$3:$3,0))} -> 0 | L7: {=INDEX(股债表现与四个维度!$A:$T,MATCH($A7,股债表现与四个维度!$A:$A,0),MATCH(L$3&L$4,股债表现与四个维度!$2:$2&股债表现与四个维度!$3:$3,0))} -> -0.1 | M7: {=INDEX(股债表现与四个维度!$A:$T,MATCH($A7,股债表现与四个维度!$A:$A,0),MATCH(M$3&M$4,股债表现与四个维度!$2:$2&股债表现与四个维度!$3:$3,0))} -> 0.51666667 | N7: {=INDEX(股债表现与四个维度!$A:$T,MATCH($A7,股债表现与四个维度!$A:$A,0),MATCH(N$3&N$4,股债表现与四个维度!$2:$2&股债表现与四个维度!$3:$3,0))} -> -0.047619048 | O7: {=INDEX(股债表现与四个维度!$A:$T,MATCH($A7,股债表现与四个维度!$A:$A,0),MATCH(O$3&O$4,股债表现与四个维度!$2:$2&股债表现与四个维度!$3:$3,0))} -> 0.95238095 | P7: {=INDEX(股债表现与四个维度!$A:$T,MATCH($A7,股债表现与四个维度!$A:$A,0),MATCH(P$3&P$4,股债表现与四个维度!$2:$2&股债表现与四个维度!$3:$3,0))} -> -0.083333333 | Q7: {=INDEX(股债表现与四个维度!$A:$T,MATCH($A7,股债表现与四个维度!$A:$A,0),MATCH(Q$3&Q$4,股债表现与四个维度!$2:$2&股债表现与四个维度!$3:$3,0))} -> 0.54166667 | ... S7: {=INDEX(股债表现与四个维度!$A:$T,MATCH($A7,股债表现与四个维度!$A:$A,0),MATCH(S$3&S$4,股债表现与四个维度!$2:$2&股债表现与四个维度!$3:$3,0))} -> 0.76470588 | T7: =SUMIFS($J7:$S7,$J7:$S7,"<>"&"#N/A",$J$4:$S$4,T$4) -> -0.380685 | U7: =SUMIFS($J7:$S7,$J7:$S7,"<>"&"#N/A",$J$4:$S$4,U$4) -> 2.7754202 | V7: =T7-U7 -> -3.1561052
A8: 46295 | E8: =VLOOKUP(A8,美林时钟!#REF!,28,TRUE) -> #REF! | F8: 宽货币紧信用 | G8: 紧货币宽财政 | H8: 被动去库存 | I8: 产能周期下行,主动补库存 | J8: {=INDEX(股债表现与四个维度!$A:$T,MATCH($A8,股债表现与四个维度!$A:$A,0),MATCH(J$3&J$4,股债表现与四个维度!$2:$2&股债表现与四个维度!$3:$3,0))} -> -0.1 | K8: {=INDEX(股债表现与四个维度!$A:$T,MATCH($A8,股债表现与四个维度!$A:$A,0),MATCH(K$3&K$4,股债表现与四个维度!$2:$2&股债表现与四个维度!$3:$3,0))} -> -0.1 | L8: {=INDEX(股债表现与四个维度!$A:$T,MATCH($A8,股债表现与四个维度!$A:$A,0),MATCH(L$3&L$4,股债表现与四个维度!$2:$2&股债表现与四个维度!$3:$3,0))} -> -0.083333333 | M8: {=INDEX(股债表现与四个维度!$A:$T,MATCH($A8,股债表现与四个维度!$A:$A,0),MATCH(M$3&M$4,股债表现与四个维度!$2:$2&股债表现与四个维度!$3:$3,0))} -> 0.51666667 | N8: {=INDEX(股债表现与四个维度!$A:$T,MATCH($A8,股债表现与四个维度!$A:$A,0),MATCH(N$3&N$4,股债表现与四个维度!$2:$2&股债表现与四个维度!$3:$3,0))} -> -0.05 | O8: {=INDEX(股债表现与四个维度!$A:$T,MATCH($A8,股债表现与四个维度!$A:$A,0),MATCH(O$3&O$4,股债表现与四个维度!$2:$2&股债表现与四个维度!$3:$3,0))} -> 0.95 | P8: {=INDEX(股债表现与四个维度!$A:$T,MATCH($A8,股债表现与四个维度!$A:$A,0),MATCH(P$3&P$4,股债表现与四个维度!$2:$2&股债表现与四个维度!$3:$3,0))} -> -0.086956522 | Q8: {=INDEX(股债表现与四个维度!$A:$T,MATCH($A8,股债表现与四个维度!$A:$A,0),MATCH(Q$3&Q$4,股债表现与四个维度!$2:$2&股债表现与四个维度!$3:$3,0))} -> 0.52173913 | ... S8: {=INDEX(股债表现与四个维度!$A:$T,MATCH($A8,股债表现与四个维度!$A:$A,0),MATCH(S$3&S$4,股债表现与四个维度!$2:$2&股债表现与四个维度!$3:$3,0))} -> 0.75757576 | T8: =SUMIFS($J8:$S8,$J8:$S8,"<>"&"#N/A",$J$4:$S$4,T$4) -> -0.38089592 | U8: =SUMIFS($J8:$S8,$J8:$S8,"<>"&"#N/A",$J$4:$S$4,U$4) -> 2.6459816 | V8: =T8-U8 -> -3.0268775
A9: 46265 | E9: =VLOOKUP(A9,美林时钟!#REF!,28,TRUE) -> #REF! | F9: 宽货币紧信用 | G9: 紧货币宽财政 | H9: 被动去库存 | I9: 产能周期下行,主动补库存 | J9: {=INDEX(股债表现与四个维度!$A:$T,MATCH($A9,股债表现与四个维度!$A:$A,0),MATCH(J$3&J$4,股债表现与四个维度!$2:$2&股债表现与四个维度!$3:$3,0))} -> -0.11111111 | K9: {=INDEX(股债表现与四个维度!$A:$T,MATCH($A9,股债表现与四个维度!$A:$A,0),MATCH(K$3&K$4,股债表现与四个维度!$2:$2&股债表现与四个维度!$3:$3,0))} -> -0.22222222 | L9: {=INDEX(股债表现与四个维度!$A:$T,MATCH($A9,股债表现与四个维度!$A:$A,0),MATCH(L$3&L$4,股债表现与四个维度!$2:$2&股债表现与四个维度!$3:$3,0))} -> -0.1 | M9: {=INDEX(股债表现与四个维度!$A:$T,MATCH($A9,股债表现与四个维度!$A:$A,0),MATCH(M$3&M$4,股债表现与四个维度!$2:$2&股债表现与四个维度!$3:$3,0))} -> 0.51666667 | N9: {=INDEX(股债表现与四个维度!$A:$T,MATCH($A9,股债表现与四个维度!$A:$A,0),MATCH(N$3&N$4,股债表现与四个维度!$2:$2&股债表现与四个维度!$3:$3,0))} -> -0.052631579 | O9: {=INDEX(股债表现与四个维度!$A:$T,MATCH($A9,股债表现与四个维度!$A:$A,0),MATCH(O$3&O$4,股债表现与四个维度!$2:$2&股债表现与四个维度!$3:$3,0))} -> 0.94736842 | P9: {=INDEX(股债表现与四个维度!$A:$T,MATCH($A9,股债表现与四个维度!$A:$A,0),MATCH(P$3&P$4,股债表现与四个维度!$2:$2&股债表现与四个维度!$3:$3,0))} -> -0.090909091 | Q9: {=INDEX(股债表现与四个维度!$A:$T,MATCH($A9,股债表现与四个维度!$A:$A,0),MATCH(Q$3&Q$4,股债表现与四个维度!$2:$2&股债表现与四个维度!$3:$3,0))} -> 0.5 | ... S9: {=INDEX(股债表现与四个维度!$A:$T,MATCH($A9,股债表现与四个维度!$A:$A,0),MATCH(S$3&S$4,股债表现与四个维度!$2:$2&股债表现与四个维度!$3:$3,0))} -> 0.75 | T9: =SUMIFS($J9:$S9,$J9:$S9,"<>"&"#N/A",$J$4:$S$4,T$4) -> -0.41715178 | U9: =SUMIFS($J9:$S9,$J9:$S9,"<>"&"#N/A",$J$4:$S$4,U$4) -> 2.4918129 | V9: =T9-U9 -> -2.9089646
A10: 46234 | E10: =VLOOKUP(A10,美林时钟!#REF!,28,TRUE) -> #REF! | F10: 宽货币紧信用 | G10: 紧货币宽财政 | H10: 被动去库存 | I10: 产能周期下行,主动补库存 | J10: {=INDEX(股债表现与四个维度!$A:$T,MATCH($A10,股债表现与四个维度!$A:$A,0),MATCH(J$3&J$4,股债表现与四个维度!$2:$2&股债表现与四个维度!$3:$3,0))} -> -0.125 | K10: {=INDEX(股债表现与四个维度!$A:$T,MATCH($A10,股债表现与四个维度!$A:$A,0),MATCH(K$3&K$4,股债表现与四个维度!$2:$2&股债表现与四个维度!$3:$3,0))} -> -0.375 | L10: {=INDEX(股债表现与四个维度!$A:$T,MATCH($A10,股债表现与四个维度!$A:$A,0),MATCH(L$3&L$4,股债表现与四个维度!$2:$2&股债表现与四个维度!$3:$3,0))} -> -0.083333333 | M10: {=INDEX(股债表现与四个维度!$A:$T,MATCH($A10,股债表现与四个维度!$A:$A,0),MATCH(M$3&M$4,股债表现与四个维度!$2:$2&股债表现与四个维度!$3:$3,0))} -> 0.51666667 | N10: {=INDEX(股债表现与四个维度!$A:$T,MATCH($A10,股债表现与四个维度!$A:$A,0),MATCH(N$3&N$4,股债表现与四个维度!$2:$2&股债表现与四个维度!$3:$3,0))} -> -0.055555556 | O10: {=INDEX(股债表现与四个维度!$A:$T,MATCH($A10,股债表现与四个维度!$A:$A,0),MATCH(O$3&O$4,股债表现与四个维度!$2:$2&股债表现与四个维度!$3:$3,0))} -> 0.94444444 | P10: {=INDEX(股债表现与四个维度!$A:$T,MATCH($A10,股债表现与四个维度!$A:$A,0),MATCH(P$3&P$4,股债表现与四个维度!$2:$2&股债表现与四个维度!$3:$3,0))} -> -0.095238095 | Q10: {=INDEX(股债表现与四个维度!$A:$T,MATCH($A10,股债表现与四个维度!$A:$A,0),MATCH(Q$3&Q$4,股债表现与四个维度!$2:$2&股债表现与四个维度!$3:$3,0))} -> 0.47619048 | ... S10: {=INDEX(股债表现与四个维度!$A:$T,MATCH($A10,股债表现与四个维度!$A:$A,0),MATCH(S$3&S$4,股债表现与四个维度!$2:$2&股债表现与四个维度!$3:$3,0))} -> 0.74193548 | T10: =SUMIFS($J10:$S10,$J10:$S10,"<>"&"#N/A",$J$4:$S$4,T$4) -> -0.42364311 | U10: =SUMIFS($J10:$S10,$J10:$S10,"<>"&"#N/A",$J$4:$S$4,U$4) -> 2.3042371 | V10: =T10-U10 -> -2.7278802
A11: 46203 | E11: =VLOOKUP(A11,美林时钟!#REF!,28,TRUE) -> #REF! | F11: 宽货币紧信用 | G11: 紧货币宽财政 | H11: 被动去库存 | I11: 产能周期下行,主动补库存 | J11: {=INDEX(股债表现与四个维度!$A:$T,MATCH($A11,股债表现与四个维度!$A:$A,0),MATCH(J$3&J$4,股债表现与四个维度!$2:$2&股债表现与四个维度!$3:$3,0))} -> -0.14285714 | K11: {=INDEX(股债表现与四个维度!$A:$T,MATCH($A11,股债表现与四个维度!$A:$A,0),MATCH(K$3&K$4,股债表现与四个维度!$2:$2&股债表现与四个维度!$3:$3,0))} -> -0.57142857 | L11: {=INDEX(股债表现与四个维度!$A:$T,MATCH($A11,股债表现与四个维度!$A:$A,0),MATCH(L$3&L$4,股债表现与四个维度!$2:$2&股债表现与四个维度!$3:$3,0))} -> -0.066666667 | M11: {=INDEX(股债表现与四个维度!$A:$T,MATCH($A11,股债表现与四个维度!$A:$A,0),MATCH(M$3&M$4,股债表现与四个维度!$2:$2&股债表现与四个维度!$3:$3,0))} -> 0.51666667 | N11: {=INDEX(股债表现与四个维度!$A:$T,MATCH($A11,股债表现与四个维度!$A:$A,0),MATCH(N$3&N$4,股债表现与四个维度!$2:$2&股债表现与四个维度!$3:$3,0))} -> -0.058823529 | O11: {=INDEX(股债表现与四个维度!$A:$T,MATCH($A11,股债表现与四个维度!$A:$A,0),MATCH(O$3&O$4,股债表现与四个维度!$2:$2&股债表现与四个维度!$3:$3,0))} -> 0.94117647 | P11: {=INDEX(股债表现与四个维度!$A:$T,MATCH($A11,股债表现与四个维度!$A:$A,0),MATCH(P$3&P$4,股债表现与四个维度!$2:$2&股债表现与四个维度!$3:$3,0))} -> -0.1 | Q11: {=INDEX(股债表现与四个维度!$A:$T,MATCH($A11,股债表现与四个维度!$A:$A,0),MATCH(Q$3&Q$4,股债表现与四个维度!$2:$2&股债表现与四个维度!$3:$3,0))} -> 0.45 | ... S11: {=INDEX(股债表现与四个维度!$A:$T,MATCH($A11,股债表现与四个维度!$A:$A,0),MATCH(S$3&S$4,股债表现与四个维度!$2:$2&股债表现与四个维度!$3:$3,0))} -> 0.73333333 | T11: =SUMIFS($J11:$S11,$J11:$S11,"<>"&"#N/A",$J$4:$S$4,T$4) -> -0.43501401 | U11: =SUMIFS($J11:$S11,$J11:$S11,"<>"&"#N/A",$J$4:$S$4,U$4) -> 2.0697479 | V11: =T11-U11 -> -2.5047619
A12: 46173 | E12: =VLOOKUP(A12,美林时钟!#REF!,28,TRUE) -> #REF! | F12: 宽货币紧信用 | G12: 紧货币宽财政 | H12: 被动去库存 | I12: 产能周期下行,主动补库存 | J12: {=INDEX(股债表现与四个维度!$A:$T,MATCH($A12,股债表现与四个维度!$A:$A,0),MATCH(J$3&J$4,股债表现与四个维度!$2:$2&股债表现与四个维度!$3:$3,0))} -> -0.14285714 | K12: {=INDEX(股债表现与四个维度!$A:$T,MATCH($A12,股债表现与四个维度!$A:$A,0),MATCH(K$3&K$4,股债表现与四个维度!$2:$2&股债表现与四个维度!$3:$3,0))} -> -0.57142857 | L12: {=INDEX(股债表现与四个维度!$A:$T,MATCH($A12,股债表现与四个维度!$A:$A,0),MATCH(L$3&L$4,股债表现与四个维度!$2:$2&股债表现与四个维度!$3:$3,0))} -> -0.05 | M12: {=INDEX(股债表现与四个维度!$A:$T,MATCH($A12,股债表现与四个维度!$A:$A,0),MATCH(M$3&M$4,股债表现与四个维度!$2:$2&股债表现与四个维度!$3:$3,0))} -> 0.51666667 | N12: {=INDEX(股债表现与四个维度!$A:$T,MATCH($A12,股债表现与四个维度!$A:$A,0),MATCH(N$3&N$4,股债表现与四个维度!$2:$2&股债表现与四个维度!$3:$3,0))} -> -0.0625 | O12: {=INDEX(股债表现与四个维度!$A:$T,MATCH($A12,股债表现与四个维度!$A:$A,0),MATCH(O$3&O$4,股债表现与四个维度!$2:$2&股债表现与四个维度!$3:$3,0))} -> 0.9375 | P12: {=INDEX(股债表现与四个维度!$A:$T,MATCH($A12,股债表现与四个维度!$A:$A,0),MATCH(P$3&P$4,股债表现与四个维度!$2:$2&股债表现与四个维度!$3:$3,0))} -> -0.10526316 | Q12: {=INDEX(股债表现与四个维度!$A:$T,MATCH($A12,股债表现与四个维度!$A:$A,0),MATCH(Q$3&Q$4,股债表现与四个维度!$2:$2&股债表现与四个维度!$3:$3,0))} -> 0.42105263 | ... S12: {=INDEX(股债表现与四个维度!$A:$T,MATCH($A12,股债表现与四个维度!$A:$A,0),MATCH(S$3&S$4,股债表现与四个维度!$2:$2&股债表现与四个维度!$3:$3,0))} -> 0.72413793 | T12: =SUMIFS($J12:$S12,$J12:$S12,"<>"&"#N/A",$J$4:$S$4,T$4) -> -0.42958582 | U12: =SUMIFS($J12:$S12,$J12:$S12,"<>"&"#N/A",$J$4:$S$4,U$4) -> 2.0279287 | V12: =T12-U12 -> -2.4575145
A13: 46142 | E13: =VLOOKUP(A13,美林时钟!#REF!,28,TRUE) -> #REF! | F13: 宽货币紧信用 | G13: 紧货币宽财政 | H13: 被动去库存 | I13: 产能周期下行,主动补库存 | J13: {=INDEX(股债表现与四个维度!$A:$T,MATCH($A13,股债表现与四个维度!$A:$A,0),MATCH(J$3&J$4,股债表现与四个维度!$2:$2&股债表现与四个维度!$3:$3,0))} -> -0.13333333 | K13: {=INDEX(股债表现与四个维度!$A:$T,MATCH($A13,股债表现与四个维度!$A:$A,0),MATCH(K$3&K$4,股债表现与四个维度!$2:$2&股债表现与四个维度!$3:$3,0))} -> 0.46666667 | L13: {=INDEX(股债表现与四个维度!$A:$T,MATCH($A13,股债表现与四个维度!$A:$A,0),MATCH(L$3&L$4,股债表现与四个维度!$2:$2&股债表现与四个维度!$3:$3,0))} -> -0.066666667 | M13: {=INDEX(股债表现与四个维度!$A:$T,MATCH($A13,股债表现与四个维度!$A:$A,0),MATCH(M$3&M$4,股债表现与四个维度!$2:$2&股债表现与四个维度!$3:$3,0))} -> 0.5 | N13: {=INDEX(股债表现与四个维度!$A:$T,MATCH($A13,股债表现与四个维度!$A:$A,0),MATCH(N$3&N$4,股债表现与四个维度!$2:$2&股债表现与四个维度!$3:$3,0))} -> -0.066666667 | O13: {=INDEX(股债表现与四个维度!$A:$T,MATCH($A13,股债表现与四个维度!$A:$A,0),MATCH(O$3&O$4,股债表现与四个维度!$2:$2&股债表现与四个维度!$3:$3,0))} -> 0.93333333 | P13: {=INDEX(股债表现与四个维度!$A:$T,MATCH($A13,股债表现与四个维度!$A:$A,0),MATCH(P$3&P$4,股债表现与四个维度!$2:$2&股债表现与四个维度!$3:$3,0))} -> -0.11111111 | Q13: {=INDEX(股债表现与四个维度!$A:$T,MATCH($A13,股债表现与四个维度!$A:$A,0),MATCH(Q$3&Q$4,股债表现与四个维度!$2:$2&股债表现与四个维度!$3:$3,0))} -> 0.38888889 | ... S13: {=INDEX(股债表现与四个维度!$A:$T,MATCH($A13,股债表现与四个维度!$A:$A,0),MATCH(S$3&S$4,股债表现与四个维度!$2:$2&股债表现与四个维度!$3:$3,0))} -> 0.71428571 | T13: =SUMIFS($J13:$S13,$J13:$S13,"<>"&"#N/A",$J$4:$S$4,T$4) -> -0.44920635 | U13: =SUMIFS($J13:$S13,$J13:$S13,"<>"&"#N/A",$J$4:$S$4,U$4) -> 3.0031746 | V13: =T13-U13 -> -3.452381
A14: 46112 | E14: =VLOOKUP(A14,美林时钟!#REF!,28,TRUE) -> #REF! | F14: 宽货币紧信用 | G14: 紧货币宽财政 | H14: 被动去库存 | I14: 产能周期下行,主动补库存 | J14: {=INDEX(股债表现与四个维度!$A:$T,MATCH($A14,股债表现与四个维度!$A:$A,0),MATCH(J$3&J$4,股债表现与四个维度!$2:$2&股债表现与四个维度!$3:$3,0))} -> 0 | K14: {=INDEX(股债表现与四个维度!$A:$T,MATCH($A14,股债表现与四个维度!$A:$A,0),MATCH(K$3&K$4,股债表现与四个维度!$2:$2&股债表现与四个维度!$3:$3,0))} -> 0.79166667 | L14: {=INDEX(股债表现与四个维度!$A:$T,MATCH($A14,股债表现与四个维度!$A:$A,0),MATCH(L$3&L$4,股债表现与四个维度!$2:$2&股债表现与四个维度!$3:$3,0))} -> -0.066666667 | M14: {=INDEX(股债表现与四个维度!$A:$T,MATCH($A14,股债表现与四个维度!$A:$A,0),MATCH(M$3&M$4,股债表现与四个维度!$2:$2&股债表现与四个维度!$3:$3,0))} -> 0.46666667 | N14: {=INDEX(股债表现与四个维度!$A:$T,MATCH($A14,股债表现与四个维度!$A:$A,0),MATCH(N$3&N$4,股债表现与四个维度!$2:$2&股债表现与四个维度!$3:$3,0))} -> -0.071428571 | O14: {=INDEX(股债表现与四个维度!$A:$T,MATCH($A14,股债表现与四个维度!$A:$A,0),MATCH(O$3&O$4,股债表现与四个维度!$2:$2&股债表现与四个维度!$3:$3,0))} -> 0.92857143 | P14: {=INDEX(股债表现与四个维度!$A:$T,MATCH($A14,股债表现与四个维度!$A:$A,0),MATCH(P$3&P$4,股债表现与四个维度!$2:$2&股债表现与四个维度!$3:$3,0))} -> -0.11111111 | Q14: {=INDEX(股债表现与四个维度!$A:$T,MATCH($A14,股债表现与四个维度!$A:$A,0),MATCH(Q$3&Q$4,股债表现与四个维度!$2:$2&股债表现与四个维度!$3:$3,0))} -> 0.38888889 | ... S14: {=INDEX(股债表现与四个维度!$A:$T,MATCH($A14,股债表现与四个维度!$A:$A,0),MATCH(S$3&S$4,股债表现与四个维度!$2:$2&股债表现与四个维度!$3:$3,0))} -> 0.71428571 | T14: =SUMIFS($J14:$S14,$J14:$S14,"<>"&"#N/A",$J$4:$S$4,T$4) -> -0.32063492 | U14: =SUMIFS($J14:$S14,$J14:$S14,"<>"&"#N/A",$J$4:$S$4,U$4) -> 3.2900794 | V14: =T14-U14 -> -3.6107143
A15: 46081 | E15: =VLOOKUP(A15,美林时钟!#REF!,28,TRUE) -> #REF! | F15: 宽货币紧信用 | G15: 紧货币宽财政 | H15: 被动去库存 | I15: 产能周期下行,主动补库存 | J15: {=INDEX(股债表现与四个维度!$A:$T,MATCH($A15,股债表现与四个维度!$A:$A,0),MATCH(J$3&J$4,股债表现与四个维度!$2:$2&股债表现与四个维度!$3:$3,0))} -> 0 | K15: {=INDEX(股债表现与四个维度!$A:$T,MATCH($A15,股债表现与四个维度!$A:$A,0),MATCH(K$3&K$4,股债表现与四个维度!$2:$2&股债表现与四个维度!$3:$3,0))} -> 0.7826087 | L15: {=INDEX(股债表现与四个维度!$A:$T,MATCH($A15,股债表现与四个维度!$A:$A,0),MATCH(L$3&L$4,股债表现与四个维度!$2:$2&股债表现与四个维度!$3:$3,0))} -> -0.066666667 | M15: {=INDEX(股债表现与四个维度!$A:$T,MATCH($A15,股债表现与四个维度!$A:$A,0),MATCH(M$3&M$4,股债表现与四个维度!$2:$2&股债表现与四个维度!$3:$3,0))} -> 0.46666667 | N15: {=INDEX(股债表现与四个维度!$A:$T,MATCH($A15,股债表现与四个维度!$A:$A,0),MATCH(N$3&N$4,股债表现与四个维度!$2:$2&股债表现与四个维度!$3:$3,0))} -> -0.071428571 | O15: {=INDEX(股债表现与四个维度!$A:$T,MATCH($A15,股债表现与四个维度!$A:$A,0),MATCH(O$3&O$4,股债表现与四个维度!$2:$2&股债表现与四个维度!$3:$3,0))} -> 0.92857143 | P15: {=INDEX(股债表现与四个维度!$A:$T,MATCH($A15,股债表现与四个维度!$A:$A,0),MATCH(P$3&P$4,股债表现与四个维度!$2:$2&股债表现与四个维度!$3:$3,0))} -> -0.5 | Q15: {=INDEX(股债表现与四个维度!$A:$T,MATCH($A15,股债表现与四个维度!$A:$A,0),MATCH(Q$3&Q$4,股债表现与四个维度!$2:$2&股债表现与四个维度!$3:$3,0))} -> 1 | ... S15: {=INDEX(股债表现与四个维度!$A:$T,MATCH($A15,股债表现与四个维度!$A:$A,0),MATCH(S$3&S$4,股债表现与四个维度!$2:$2&股债表现与四个维度!$3:$3,0))} -> 0.44444444 | T15: =SUMIFS($J15:$S15,$J15:$S15,"<>"&"#N/A",$J$4:$S$4,T$4) -> -0.86031746 | U15: =SUMIFS($J15:$S15,$J15:$S15,"<>"&"#N/A",$J$4:$S$4,U$4) -> 3.6222912 | V15: =T15-U15 -> -4.4826087
A16: 46053 | E16: =VLOOKUP(A16,美林时钟!A1:AB260,28,TRUE) -> 过热 | F16: 宽货币紧信用 | G16: 紧货币宽财政 | H16: 被动去库存 | I16: 产能周期下行,主动补库存 | J16: {=INDEX(股债表现与四个维度!$A:$T,MATCH($A16,股债表现与四个维度!$A:$A,0),MATCH(J$3&J$4,股债表现与四个维度!$2:$2&股债表现与四个维度!$3:$3,0))} -> 0 | K16: {=INDEX(股债表现与四个维度!$A:$T,MATCH($A16,股债表现与四个维度!$A:$A,0),MATCH(K$3&K$4,股债表现与四个维度!$2:$2&股债表现与四个维度!$3:$3,0))} -> 0.77272727 | L16: {=INDEX(股债表现与四个维度!$A:$T,MATCH($A16,股债表现与四个维度!$A:$A,0),MATCH(L$3&L$4,股债表现与四个维度!$2:$2&股债表现与四个维度!$3:$3,0))} -> -0.05 | M16: {=INDEX(股债表现与四个维度!$A:$T,MATCH($A16,股债表现与四个维度!$A:$A,0),MATCH(M$3&M$4,股债表现与四个维度!$2:$2&股债表现与四个维度!$3:$3,0))} -> 0.45 | N16: {=INDEX(股债表现与四个维度!$A:$T,MATCH($A16,股债表现与四个维度!$A:$A,0),MATCH(N$3&N$4,股债表现与四个维度!$2:$2&股债表现与四个维度!$3:$3,0))} -> -0.25 | O16: {=INDEX(股债表现与四个维度!$A:$T,MATCH($A16,股债表现与四个维度!$A:$A,0),MATCH(O$3&O$4,股债表现与四个维度!$2:$2&股债表现与四个维度!$3:$3,0))} -> 0.083333333 | P16: {=INDEX(股债表现与四个维度!$A:$T,MATCH($A16,股债表现与四个维度!$A:$A,0),MATCH(P$3&P$4,股债表现与四个维度!$2:$2&股债表现与四个维度!$3:$3,0))} -> -0.5 | Q16: {=INDEX(股债表现与四个维度!$A:$T,MATCH($A16,股债表现与四个维度!$A:$A,0),MATCH(Q$3&Q$4,股债表现与四个维度!$2:$2&股债表现与四个维度!$3:$3,0))} -> 1 | ... S16: {=INDEX(股债表现与四个维度!$A:$T,MATCH($A16,股债表现与四个维度!$A:$A,0),MATCH(S$3&S$4,股债表现与四个维度!$2:$2&股债表现与四个维度!$3:$3,0))} -> 0.44444444 | T16: =SUMIFS($J16:$S16,$J16:$S16,"<>"&"#N/A",$J$4:$S$4,T$4) -> -1.0222222 | U16: =SUMIFS($J16:$S16,$J16:$S16,"<>"&"#N/A",$J$4:$S$4,U$4) -> 2.7505051 | V16: =T16-U16 -> -3.7727273 | W16: 6.49 | Y16: -3.3160785
A17: 46022 | E17: =VLOOKUP(A17,美林时钟!A2:AB261,28,TRUE) -> 过热 | F17: 宽货币紧信用 | G17: 紧货币宽财政 | H17: 被动去库存 | I17: 产能周期下行,主动补库存 | J17: {=INDEX(股债表现与四个维度!$A:$T,MATCH($A17,股债表现与四个维度!$A:$A,0),MATCH(J$3&J$4,股债表现与四个维度!$2:$2&股债表现与四个维度!$3:$3,0))} -> 0 | K17: {=INDEX(股债表现与四个维度!$A:$T,MATCH($A17,股债表现与四个维度!$A:$A,0),MATCH(K$3&K$4,股债表现与四个维度!$2:$2&股债表现与四个维度!$3:$3,0))} -> 0.76190476 | L17: {=INDEX(股债表现与四个维度!$A:$T,MATCH($A17,股债表现与四个维度!$A:$A,0),MATCH(L$3&L$4,股债表现与四个维度!$2:$2&股债表现与四个维度!$3:$3,0))} -> -0.050847458 | M17: {=INDEX(股债表现与四个维度!$A:$T,MATCH($A17,股债表现与四个维度!$A:$A,0),MATCH(M$3&M$4,股债表现与四个维度!$2:$2&股债表现与四个维度!$3:$3,0))} -> 0.44067797 | N17: {=INDEX(股债表现与四个维度!$A:$T,MATCH($A17,股债表现与四个维度!$A:$A,0),MATCH(N$3&N$4,股债表现与四个维度!$2:$2&股债表现与四个维度!$3:$3,0))} -> -0.083333333 | O17: {=INDEX(股债表现与四个维度!$A:$T,MATCH($A17,股债表现与四个维度!$A:$A,0),MATCH(O$3&O$4,股债表现与四个维度!$2:$2&股债表现与四个维度!$3:$3,0))} -> 0.91666667 | P17: {=INDEX(股债表现与四个维度!$A:$T,MATCH($A17,股债表现与四个维度!$A:$A,0),MATCH(P$3&P$4,股债表现与四个维度!$2:$2&股债表现与四个维度!$3:$3,0))} -> 0 | Q17: {=INDEX(股债表现与四个维度!$A:$T,MATCH($A17,股债表现与四个维度!$A:$A,0),MATCH(Q$3&Q$4,股债表现与四个维度!$2:$2&股债表现与四个维度!$3:$3,0))} -> 0.37931034 | ... S17: {=INDEX(股债表现与四个维度!$A:$T,MATCH($A17,股债表现与四个维度!$A:$A,0),MATCH(S$3&S$4,股债表现与四个维度!$2:$2&股债表现与四个维度!$3:$3,0))} -> 0.69230769 | T17: =SUMIFS($J17:$S17,$J17:$S17,"<>"&"#N/A",$J$4:$S$4,T$4) -> -0.21110387 | U17: =SUMIFS($J17:$S17,$J17:$S17,"<>"&"#N/A",$J$4:$S$4,U$4) -> 3.1908674 | V17: =T17-U17 -> -3.4019713 | W17: 6.4860486 | X17: =C17+D17 -> 0 | Y17: =AVERAGE(V17:V22) -> -3.3160785
A18: 45991 | E18: =VLOOKUP(A18,美林时钟!A3:AB262,28,TRUE) -> 过热 | F18: 宽货币紧信用 | G18: 紧货币宽财政 | H18: 被动去库存 | I18: 产能周期下行,主动补库存 | J18: {=INDEX(股债表现与四个维度!$A:$T,MATCH($A18,股债表现与四个维度!$A:$A,0),MATCH(J$3&J$4,股债表现与四个维度!$2:$2&股债表现与四个维度!$3:$3,0))} -> 0 | K18: {=INDEX(股债表现与四个维度!$A:$T,MATCH($A18,股债表现与四个维度!$A:$A,0),MATCH(K$3&K$4,股债表现与四个维度!$2:$2&股债表现与四个维度!$3:$3,0))} -> 0.75 | L18: {=INDEX(股债表现与四个维度!$A:$T,MATCH($A18,股债表现与四个维度!$A:$A,0),MATCH(L$3&L$4,股债表现与四个维度!$2:$2&股债表现与四个维度!$3:$3,0))} -> -0.051724138 | M18: {=INDEX(股债表现与四个维度!$A:$T,MATCH($A18,股债表现与四个维度!$A:$A,0),MATCH(M$3&M$4,股债表现与四个维度!$2:$2&股债表现与四个维度!$3:$3,0))} -> 0.43103448 | N18: {=INDEX(股债表现与四个维度!$A:$T,MATCH($A18,股债表现与四个维度!$A:$A,0),MATCH(N$3&N$4,股债表现与四个维度!$2:$2&股债表现与四个维度!$3:$3,0))} -> -0.090909091 | O18: {=INDEX(股债表现与四个维度!$A:$T,MATCH($A18,股债表现与四个维度!$A:$A,0),MATCH(O$3&O$4,股债表现与四个维度!$2:$2&股债表现与四个维度!$3:$3,0))} -> 0.90909091 | P18: {=INDEX(股债表现与四个维度!$A:$T,MATCH($A18,股债表现与四个维度!$A:$A,0),MATCH(P$3&P$4,股债表现与四个维度!$2:$2&股债表现与四个维度!$3:$3,0))} -> 0 | Q18: {=INDEX(股债表现与四个维度!$A:$T,MATCH($A18,股债表现与四个维度!$A:$A,0),MATCH(Q$3&Q$4,股债表现与四个维度!$2:$2&股债表现与四个维度!$3:$3,0))} -> 0.37931034 | ... S18: {=INDEX(股债表现与四个维度!$A:$T,MATCH($A18,股债表现与四个维度!$A:$A,0),MATCH(S$3&S$4,股债表现与四个维度!$2:$2&股债表现与四个维度!$3:$3,0))} -> 0.68 | T18: =SUMIFS($J18:$S18,$J18:$S18,"<>"&"#N/A",$J$4:$S$4,T$4) -> -0.22263323 | U18: =SUMIFS($J18:$S18,$J18:$S18,"<>"&"#N/A",$J$4:$S$4,U$4) -> 3.1494357 | V18: =T18-U18 -> -3.372069 | W18: 5.740969 | X18: =C18+D18 -> 0 | Y18: =AVERAGE(V18:V23) -> -3.2575214
A19: 45961 | E19: =VLOOKUP(A19,美林时钟!A4:AB263,28,TRUE) -> 过热 | F19: 宽货币紧信用 | G19: 紧货币宽财政 | H19: 被动去库存 | I19: 产能周期下行,主动补库存 | J19: {=INDEX(股债表现与四个维度!$A:$T,MATCH($A19,股债表现与四个维度!$A:$A,0),MATCH(J$3&J$4,股债表现与四个维度!$2:$2&股债表现与四个维度!$3:$3,0))} -> 0 | K19: {=INDEX(股债表现与四个维度!$A:$T,MATCH($A19,股债表现与四个维度!$A:$A,0),MATCH(K$3&K$4,股债表现与四个维度!$2:$2&股债表现与四个维度!$3:$3,0))} -> 0.73684211 | L19: {=INDEX(股债表现与四个维度!$A:$T,MATCH($A19,股债表现与四个维度!$A:$A,0),MATCH(L$3&L$4,股债表现与四个维度!$2:$2&股债表现与四个维度!$3:$3,0))} -> -0.052631579 | M19: {=INDEX(股债表现与四个维度!$A:$T,MATCH($A19,股债表现与四个维度!$A:$A,0),MATCH(M$3&M$4,股债表现与四个维度!$2:$2&股债表现与四个维度!$3:$3,0))} -> 0.42105263 | N19: {=INDEX(股债表现与四个维度!$A:$T,MATCH($A19,股债表现与四个维度!$A:$A,0),MATCH(N$3&N$4,股债表现与四个维度!$2:$2&股债表现与四个维度!$3:$3,0))} -> -0.1 | O19: {=INDEX(股债表现与四个维度!$A:$T,MATCH($A19,股债表现与四个维度!$A:$A,0),MATCH(O$3&O$4,股债表现与四个维度!$2:$2&股债表现与四个维度!$3:$3,0))} -> 0.9 | P19: {=INDEX(股债表现与四个维度!$A:$T,MATCH($A19,股债表现与四个维度!$A:$A,0),MATCH(P$3&P$4,股债表现与四个维度!$2:$2&股债表现与四个维度!$3:$3,0))} -> -0.125 | Q19: {=INDEX(股债表现与四个维度!$A:$T,MATCH($A19,股债表现与四个维度!$A:$A,0),MATCH(Q$3&Q$4,股债表现与四个维度!$2:$2&股债表现与四个维度!$3:$3,0))} -> 0.3125 | ... S19: {=INDEX(股债表现与四个维度!$A:$T,MATCH($A19,股债表现与四个维度!$A:$A,0),MATCH(S$3&S$4,股债表现与四个维度!$2:$2&股债表现与四个维度!$3:$3,0))} -> 0.66666667 | T19: =SUMIFS($J19:$S19,$J19:$S19,"<>"&"#N/A",$J$4:$S$4,T$4) -> -0.36096491 | U19: =SUMIFS($J19:$S19,$J19:$S19,"<>"&"#N/A",$J$4:$S$4,U$4) -> 3.0370614 | V19: =T19-U19 -> -3.3980263 | W19: 7.013594 | X19: =C19+D19 -> 0 | Y19: =AVERAGE(V19:V24) -> -3.1881386
A20: 45930 | E20: =VLOOKUP(A20,美林时钟!A5:AB264,28,TRUE) -> 滞涨 | F20: 宽货币紧信用 | G20: 紧货币宽财政 | H20: 被动去库存 | I20: 产能周期下行,主动补库存 | J20: {=INDEX(股债表现与四个维度!$A:$T,MATCH($A20,股债表现与四个维度!$A:$A,0),MATCH(J$3&J$4,股债表现与四个维度!$2:$2&股债表现与四个维度!$3:$3,0))} -> 0 | K20: {=INDEX(股债表现与四个维度!$A:$T,MATCH($A20,股债表现与四个维度!$A:$A,0),MATCH(K$3&K$4,股债表现与四个维度!$2:$2&股债表现与四个维度!$3:$3,0))} -> 0.72222222 | L20: {=INDEX(股债表现与四个维度!$A:$T,MATCH($A20,股债表现与四个维度!$A:$A,0),MATCH(L$3&L$4,股债表现与四个维度!$2:$2&股债表现与四个维度!$3:$3,0))} -> -0.053571429 | M20: {=INDEX(股债表现与四个维度!$A:$T,MATCH($A20,股债表现与四个维度!$A:$A,0),MATCH(M$3&M$4,股债表现与四个维度!$2:$2&股债表现与四个维度!$3:$3,0))} -> 0.41071429 | N20: {=INDEX(股债表现与四个维度!$A:$T,MATCH($A20,股债表现与四个维度!$A:$A,0),MATCH(N$3&N$4,股债表现与四个维度!$2:$2&股债表现与四个维度!$3:$3,0))} -> -0.11111111 | O20: {=INDEX(股债表现与四个维度!$A:$T,MATCH($A20,股债表现与四个维度!$A:$A,0),MATCH(O$3&O$4,股债表现与四个维度!$2:$2&股债表现与四个维度!$3:$3,0))} -> 0.88888889 | P20: {=INDEX(股债表现与四个维度!$A:$T,MATCH($A20,股债表现与四个维度!$A:$A,0),MATCH(P$3&P$4,股债表现与四个维度!$2:$2&股债表现与四个维度!$3:$3,0))} -> -0.13333333 | Q20: {=INDEX(股债表现与四个维度!$A:$T,MATCH($A20,股债表现与四个维度!$A:$A,0),MATCH(Q$3&Q$4,股债表现与四个维度!$2:$2&股债表现与四个维度!$3:$3,0))} -> 0.26666667 | ... S20: {=INDEX(股债表现与四个维度!$A:$T,MATCH($A20,股债表现与四个维度!$A:$A,0),MATCH(S$3&S$4,股债表现与四个维度!$2:$2&股债表现与四个维度!$3:$3,0))} -> 0.65217391 | T20: =SUMIFS($J20:$S20,$J20:$S20,"<>"&"#N/A",$J$4:$S$4,T$4) -> -0.38497239 | U20: =SUMIFS($J20:$S20,$J20:$S20,"<>"&"#N/A",$J$4:$S$4,U$4) -> 2.940666 | V20: =T20-U20 -> -3.3256384 | W20: 4.4896607 | X20: =C20+D20 -> 0 | Y20: =AVERAGE(V20:V25) -> -2.9631337
A21: 45900 | E21: =VLOOKUP(A21,美林时钟!A6:AB265,28,TRUE) -> 滞涨 | F21: 宽货币紧信用 | G21: 紧货币宽财政 | H21: 被动去库存 | I21: 产能周期下行,主动补库存 | J21: {=INDEX(股债表现与四个维度!$A:$T,MATCH($A21,股债表现与四个维度!$A:$A,0),MATCH(J$3&J$4,股债表现与四个维度!$2:$2&股债表现与四个维度!$3:$3,0))} -> 0 | K21: {=INDEX(股债表现与四个维度!$A:$T,MATCH($A21,股债表现与四个维度!$A:$A,0),MATCH(K$3&K$4,股债表现与四个维度!$2:$2&股债表现与四个维度!$3:$3,0))} -> 0.70588235 | L21: {=INDEX(股债表现与四个维度!$A:$T,MATCH($A21,股债表现与四个维度!$A:$A,0),MATCH(L$3&L$4,股债表现与四个维度!$2:$2&股债表现与四个维度!$3:$3,0))} -> -0.054545455 | M21: {=INDEX(股债表现与四个维度!$A:$T,MATCH($A21,股债表现与四个维度!$A:$A,0),MATCH(M$3&M$4,股债表现与四个维度!$2:$2&股债表现与四个维度!$3:$3,0))} -> 0.4 | N21: {=INDEX(股债表现与四个维度!$A:$T,MATCH($A21,股债表现与四个维度!$A:$A,0),MATCH(N$3&N$4,股债表现与四个维度!$2:$2&股债表现与四个维度!$3:$3,0))} -> -0.125 | O21: {=INDEX(股债表现与四个维度!$A:$T,MATCH($A21,股债表现与四个维度!$A:$A,0),MATCH(O$3&O$4,股债表现与四个维度!$2:$2&股债表现与四个维度!$3:$3,0))} -> 0.875 | P21: {=INDEX(股债表现与四个维度!$A:$T,MATCH($A21,股债表现与四个维度!$A:$A,0),MATCH(P$3&P$4,股债表现与四个维度!$2:$2&股债表现与四个维度!$3:$3,0))} -> -0.14285714 | Q21: {=INDEX(股债表现与四个维度!$A:$T,MATCH($A21,股债表现与四个维度!$A:$A,0),MATCH(Q$3&Q$4,股债表现与四个维度!$2:$2&股债表现与四个维度!$3:$3,0))} -> 0.21428571 | ... S21: {=INDEX(股债表现与四个维度!$A:$T,MATCH($A21,股债表现与四个维度!$A:$A,0),MATCH(S$3&S$4,股债表现与四个维度!$2:$2&股债表现与四个维度!$3:$3,0))} -> 0.63636364 | T21: =SUMIFS($J21:$S21,$J21:$S21,"<>"&"#N/A",$J$4:$S$4,T$4) -> -0.41331169 | U21: =SUMIFS($J21:$S21,$J21:$S21,"<>"&"#N/A",$J$4:$S$4,U$4) -> 2.8315317 | V21: =T21-U21 -> -3.2448434 | W21: 4.5176469 | X21: =C21+D21 -> 0 | Y21: =AVERAGE(V21:V26) -> -2.8692679
A22: 45869 | E22: =VLOOKUP(A22,美林时钟!A7:AB266,28,TRUE) -> 滞涨 | F22: 宽货币紧信用 | G22: 紧货币宽财政 | H22: 被动去库存 | I22: 产能周期下行,主动补库存 | J22: {=INDEX(股债表现与四个维度!$A:$T,MATCH($A22,股债表现与四个维度!$A:$A,0),MATCH(J$3&J$4,股债表现与四个维度!$2:$2&股债表现与四个维度!$3:$3,0))} -> 0 | K22: {=INDEX(股债表现与四个维度!$A:$T,MATCH($A22,股债表现与四个维度!$A:$A,0),MATCH(K$3&K$4,股债表现与四个维度!$2:$2&股债表现与四个维度!$3:$3,0))} -> 0.6875 | L22: {=INDEX(股债表现与四个维度!$A:$T,MATCH($A22,股债表现与四个维度!$A:$A,0),MATCH(L$3&L$4,股债表现与四个维度!$2:$2&股债表现与四个维度!$3:$3,0))} -> -0.055555556 | M22: {=INDEX(股债表现与四个维度!$A:$T,MATCH($A22,股债表现与四个维度!$A:$A,0),MATCH(M$3&M$4,股债表现与四个维度!$2:$2&股债表现与四个维度!$3:$3,0))} -> 0.38888889 | N22: {=INDEX(股债表现与四个维度!$A:$T,MATCH($A22,股债表现与四个维度!$A:$A,0),MATCH(N$3&N$4,股债表现与四个维度!$2:$2&股债表现与四个维度!$3:$3,0))} -> -0.14285714 | O22: {=INDEX(股债表现与四个维度!$A:$T,MATCH($A22,股债表现与四个维度!$A:$A,0),MATCH(O$3&O$4,股债表现与四个维度!$2:$2&股债表现与四个维度!$3:$3,0))} -> 0.85714286 | P22: {=INDEX(股债表现与四个维度!$A:$T,MATCH($A22,股债表现与四个维度!$A:$A,0),MATCH(P$3&P$4,股债表现与四个维度!$2:$2&股债表现与四个维度!$3:$3,0))} -> -0.15384615 | Q22: {=INDEX(股债表现与四个维度!$A:$T,MATCH($A22,股债表现与四个维度!$A:$A,0),MATCH(Q$3&Q$4,股债表现与四个维度!$2:$2&股债表现与四个维度!$3:$3,0))} -> 0.15384615 | ... S22: {=INDEX(股债表现与四个维度!$A:$T,MATCH($A22,股债表现与四个维度!$A:$A,0),MATCH(S$3&S$4,股债表现与四个维度!$2:$2&股债表现与四个维度!$3:$3,0))} -> 0.61904762 | T22: =SUMIFS($J22:$S22,$J22:$S22,"<>"&"#N/A",$J$4:$S$4,T$4) -> -0.44749695 | U22: =SUMIFS($J22:$S22,$J22:$S22,"<>"&"#N/A",$J$4:$S$4,U$4) -> 2.7064255 | V22: =T22-U22 -> -3.1539225 | W22: 2.8260007 | X22: =C22+D22 -> 0 | Y22: =AVERAGE(V22:V27) -> -2.5582214
A23: 45838 | E23: =VLOOKUP(A23,美林时钟!A8:AB267,28,TRUE) -> 滞涨 | F23: 宽货币紧信用 | G23: 紧货币宽财政 | H23: 被动去库存 | I23: 产能周期下行,主动补库存 | J23: {=INDEX(股债表现与四个维度!$A:$T,MATCH($A23,股债表现与四个维度!$A:$A,0),MATCH(J$3&J$4,股债表现与四个维度!$2:$2&股债表现与四个维度!$3:$3,0))} -> 0 | K23: {=INDEX(股债表现与四个维度!$A:$T,MATCH($A23,股债表现与四个维度!$A:$A,0),MATCH(K$3&K$4,股债表现与四个维度!$2:$2&股债表现与四个维度!$3:$3,0))} -> 0.66666667 | L23: {=INDEX(股债表现与四个维度!$A:$T,MATCH($A23,股债表现与四个维度!$A:$A,0),MATCH(L$3&L$4,股债表现与四个维度!$2:$2&股债表现与四个维度!$3:$3,0))} -> -0.056603774 | M23: {=INDEX(股债表现与四个维度!$A:$T,MATCH($A23,股债表现与四个维度!$A:$A,0),MATCH(M$3&M$4,股债表现与四个维度!$2:$2&股债表现与四个维度!$3:$3,0))} -> 0.37735849 | N23: {=INDEX(股债表现与四个维度!$A:$T,MATCH($A23,股债表现与四个维度!$A:$A,0),MATCH(N$3&N$4,股债表现与四个维度!$2:$2&股债表现与四个维度!$3:$3,0))} -> -0.16666667 | O23: {=INDEX(股债表现与四个维度!$A:$T,MATCH($A23,股债表现与四个维度!$A:$A,0),MATCH(O$3&O$4,股债表现与四个维度!$2:$2&股债表现与四个维度!$3:$3,0))} -> 0.83333333 | P23: {=INDEX(股债表现与四个维度!$A:$T,MATCH($A23,股债表现与四个维度!$A:$A,0),MATCH(P$3&P$4,股债表现与四个维度!$2:$2&股债表现与四个维度!$3:$3,0))} -> -0.16666667 | Q23: {=INDEX(股债表现与四个维度!$A:$T,MATCH($A23,股债表现与四个维度!$A:$A,0),MATCH(Q$3&Q$4,股债表现与四个维度!$2:$2&股债表现与四个维度!$3:$3,0))} -> 0.083333333 | ... S23: {=INDEX(股债表现与四个维度!$A:$T,MATCH($A23,股债表现与四个维度!$A:$A,0),MATCH(S$3&S$4,股债表现与四个维度!$2:$2&股债表现与四个维度!$3:$3,0))} -> 0.6 | T23: =SUMIFS($J23:$S23,$J23:$S23,"<>"&"#N/A",$J$4:$S$4,T$4) -> -0.48993711 | U23: =SUMIFS($J23:$S23,$J23:$S23,"<>"&"#N/A",$J$4:$S$4,U$4) -> 2.5606918 | V23: =T23-U23 -> -3.0506289 | W23: -1.4990226 | X23: =C23+D23 -> 0 | Y23: =AVERAGE(V23:V28) -> -2.0756232
A24: 45808 | E24: =VLOOKUP(A24,美林时钟!A9:AB268,28,TRUE) -> 滞涨 | F24: 宽货币紧信用 | G24: 紧货币宽财政 | H24: 被动去库存 | I24: 产能周期下行,主动补库存 | J24: {=INDEX(股债表现与四个维度!$A:$T,MATCH($A24,股债表现与四个维度!$A:$A,0),MATCH(J$3&J$4,股债表现与四个维度!$2:$2&股债表现与四个维度!$3:$3,0))} -> 0 | K24: {=INDEX(股债表现与四个维度!$A:$T,MATCH($A24,股债表现与四个维度!$A:$A,0),MATCH(K$3&K$4,股债表现与四个维度!$2:$2&股债表现与四个维度!$3:$3,0))} -> 0.66666667 | L24: {=INDEX(股债表现与四个维度!$A:$T,MATCH($A24,股债表现与四个维度!$A:$A,0),MATCH(L$3&L$4,股债表现与四个维度!$2:$2&股债表现与四个维度!$3:$3,0))} -> -0.057692308 | M24: {=INDEX(股债表现与四个维度!$A:$T,MATCH($A24,股债表现与四个维度!$A:$A,0),MATCH(M$3&M$4,股债表现与四个维度!$2:$2&股债表现与四个维度!$3:$3,0))} -> 0.36538462 | N24: {=INDEX(股债表现与四个维度!$A:$T,MATCH($A24,股债表现与四个维度!$A:$A,0),MATCH(N$3&N$4,股债表现与四个维度!$2:$2&股债表现与四个维度!$3:$3,0))} -> -0.2 | O24: {=INDEX(股债表现与四个维度!$A:$T,MATCH($A24,股债表现与四个维度!$A:$A,0),MATCH(O$3&O$4,股债表现与四个维度!$2:$2&股债表现与四个维度!$3:$3,0))} -> 0.8 | P24: {=INDEX(股债表现与四个维度!$A:$T,MATCH($A24,股债表现与四个维度!$A:$A,0),MATCH(P$3&P$4,股债表现与四个维度!$2:$2&股债表现与四个维度!$3:$3,0))} -> -0.18181818 | Q24: {=INDEX(股债表现与四个维度!$A:$T,MATCH($A24,股债表现与四个维度!$A:$A,0),MATCH(Q$3&Q$4,股债表现与四个维度!$2:$2&股债表现与四个维度!$3:$3,0))} -> 0 | ... S24: {=INDEX(股债表现与四个维度!$A:$T,MATCH($A24,股债表现与四个维度!$A:$A,0),MATCH(S$3&S$4,股债表现与四个维度!$2:$2&股债表现与四个维度!$3:$3,0))} -> 0.57894737 | T24: =SUMIFS($J24:$S24,$J24:$S24,"<>"&"#N/A",$J$4:$S$4,T$4) -> -0.54477365 | U24: =SUMIFS($J24:$S24,$J24:$S24,"<>"&"#N/A",$J$4:$S$4,U$4) -> 2.4109987 | V24: =T24-U24 -> -2.9557723 | W24: -6.8973344 | X24: =C24+D24 -> 0 | Y24: =AVERAGE(V24:V29) -> -1.6159862
A25: 45777 | E25: =VLOOKUP(A25,美林时钟!A10:AB269,28,TRUE) -> 衰退 | F25: 宽货币紧信用 | G25: 紧货币宽财政 | H25: 被动去库存 | I25: 产能周期下行,主动补库存 | J25: {=INDEX(股债表现与四个维度!$A:$T,MATCH($A25,股债表现与四个维度!$A:$A,0),MATCH(J$3&J$4,股债表现与四个维度!$2:$2&股债表现与四个维度!$3:$3,0))} -> 0.13043478 | K25: {=INDEX(股债表现与四个维度!$A:$T,MATCH($A25,股债表现与四个维度!$A:$A,0),MATCH(K$3&K$4,股债表现与四个维度!$2:$2&股债表现与四个维度!$3:$3,0))} -> 0 | L25: {=INDEX(股债表现与四个维度!$A:$T,MATCH($A25,股债表现与四个维度!$A:$A,0),MATCH(L$3&L$4,股债表现与四个维度!$2:$2&股债表现与四个维度!$3:$3,0))} -> -0.058823529 | M25: {=INDEX(股债表现与四个维度!$A:$T,MATCH($A25,股债表现与四个维度!$A:$A,0),MATCH(M$3&M$4,股债表现与四个维度!$2:$2&股债表现与四个维度!$3:$3,0))} -> 0.35294118 | N25: {=INDEX(股债表现与四个维度!$A:$T,MATCH($A25,股债表现与四个维度!$A:$A,0),MATCH(N$3&N$4,股债表现与四个维度!$2:$2&股债表现与四个维度!$3:$3,0))} -> -0.25 | O25: {=INDEX(股债表现与四个维度!$A:$T,MATCH($A25,股债表现与四个维度!$A:$A,0),MATCH(O$3&O$4,股债表现与四个维度!$2:$2&股债表现与四个维度!$3:$3,0))} -> 0.75 | P25: {=INDEX(股债表现与四个维度!$A:$T,MATCH($A25,股债表现与四个维度!$A:$A,0),MATCH(P$3&P$4,股债表现与四个维度!$2:$2&股债表现与四个维度!$3:$3,0))} -> -0.2 | Q25: {=INDEX(股债表现与四个维度!$A:$T,MATCH($A25,股债表现与四个维度!$A:$A,0),MATCH(Q$3&Q$4,股债表现与四个维度!$2:$2&股债表现与四个维度!$3:$3,0))} -> -0.1 | ... S25: {=INDEX(股债表现与四个维度!$A:$T,MATCH($A25,股债表现与四个维度!$A:$A,0),MATCH(S$3&S$4,股债表现与四个维度!$2:$2&股债表现与四个维度!$3:$3,0))} -> 0.55555556 | T25: =SUMIFS($J25:$S25,$J25:$S25,"<>"&"#N/A",$J$4:$S$4,T$4) -> -0.48949986 | U25: =SUMIFS($J25:$S25,$J25:$S25,"<>"&"#N/A",$J$4:$S$4,U$4) -> 1.5584967 | V25: =T25-U25 -> -2.0479966 | W25: -8.2816599 | X25: =C25+D25 -> 0 | Y25: =AVERAGE(V25:V30) -> -1.2574154
A26: 45747 | E26: =VLOOKUP(A26,美林时钟!A11:AB270,28,TRUE) -> 复苏 | F26: 宽货币紧信用 | G26: 紧货币宽财政 | H26: 被动去库存 | I26: 产能周期下行,主动补库存 | J26: {=INDEX(股债表现与四个维度!$A:$T,MATCH($A26,股债表现与四个维度!$A:$A,0),MATCH(J$3&J$4,股债表现与四个维度!$2:$2&股债表现与四个维度!$3:$3,0))} -> 0 | K26: {=INDEX(股债表现与四个维度!$A:$T,MATCH($A26,股债表现与四个维度!$A:$A,0),MATCH(K$3&K$4,股债表现与四个维度!$2:$2&股债表现与四个维度!$3:$3,0))} -> 0.61538462 | L26: {=INDEX(股债表现与四个维度!$A:$T,MATCH($A26,股债表现与四个维度!$A:$A,0),MATCH(L$3&L$4,股债表现与四个维度!$2:$2&股债表现与四个维度!$3:$3,0))} -> -0.06 | M26: {=INDEX(股债表现与四个维度!$A:$T,MATCH($A26,股债表现与四个维度!$A:$A,0),MATCH(M$3&M$4,股债表现与四个维度!$2:$2&股债表现与四个维度!$3:$3,0))} -> 0.34 | N26: {=INDEX(股债表现与四个维度!$A:$T,MATCH($A26,股债表现与四个维度!$A:$A,0),MATCH(N$3&N$4,股债表现与四个维度!$2:$2&股债表现与四个维度!$3:$3,0))} -> -0.25 | O26: {=INDEX(股债表现与四个维度!$A:$T,MATCH($A26,股债表现与四个维度!$A:$A,0),MATCH(O$3&O$4,股债表现与四个维度!$2:$2&股债表现与四个维度!$3:$3,0))} -> 0.75 | P26: {=INDEX(股债表现与四个维度!$A:$T,MATCH($A26,股债表现与四个维度!$A:$A,0),MATCH(P$3&P$4,股债表现与四个维度!$2:$2&股债表现与四个维度!$3:$3,0))} -> -0.2 | Q26: {=INDEX(股债表现与四个维度!$A:$T,MATCH($A26,股债表现与四个维度!$A:$A,0),MATCH(Q$3&Q$4,股债表现与四个维度!$2:$2&股债表现与四个维度!$3:$3,0))} -> -0.1 | ... S26: {=INDEX(股债表现与四个维度!$A:$T,MATCH($A26,股债表现与四个维度!$A:$A,0),MATCH(S$3&S$4,股债表现与四个维度!$2:$2&股债表现与四个维度!$3:$3,0))} -> 0.52941176 | T26: =SUMIFS($J26:$S26,$J26:$S26,"<>"&"#N/A",$J$4:$S$4,T$4) -> -0.62764706 | U26: =SUMIFS($J26:$S26,$J26:$S26,"<>"&"#N/A",$J$4:$S$4,U$4) -> 2.1347964 | V26: =T26-U26 -> -2.7624434 | W26: -4.2268817 | X26: =C26+D26 -> 0 | Y26: =AVERAGE(V26:V31) -> -1.063367
A27: 45716 | B27: 4.6416175 | C27: -1.8484211 | D27: 0.12994035 | E27: =VLOOKUP(A27,美林时钟!A12:AB271,28,TRUE) -> 复苏 | F27: 宽货币紧信用 | G27: 双紧 | H27: 主动补库存 | I27: 产能周期下行,主动补库存 | J27: {=INDEX(股债表现与四个维度!$A:$T,MATCH($A27,股债表现与四个维度!$A:$A,0),MATCH(J$3&J$4,股债表现与四个维度!$2:$2&股债表现与四个维度!$3:$3,0))} -> 0 | K27: {=INDEX(股债表现与四个维度!$A:$T,MATCH($A27,股债表现与四个维度!$A:$A,0),MATCH(K$3&K$4,股债表现与四个维度!$2:$2&股债表现与四个维度!$3:$3,0))} -> 0.61538462 | L27: {=INDEX(股债表现与四个维度!$A:$T,MATCH($A27,股债表现与四个维度!$A:$A,0),MATCH(L$3&L$4,股债表现与四个维度!$2:$2&股债表现与四个维度!$3:$3,0))} -> -0.040816327 | M27: {=INDEX(股债表现与四个维度!$A:$T,MATCH($A27,股债表现与四个维度!$A:$A,0),MATCH(M$3&M$4,股债表现与四个维度!$2:$2&股债表现与四个维度!$3:$3,0))} -> 0.32653061 | N27: {=INDEX(股债表现与四个维度!$A:$T,MATCH($A27,股债表现与四个维度!$A:$A,0),MATCH(N$3&N$4,股债表现与四个维度!$2:$2&股债表现与四个维度!$3:$3,0))} -> 0.0625 | O27: {=INDEX(股债表现与四个维度!$A:$T,MATCH($A27,股债表现与四个维度!$A:$A,0),MATCH(O$3&O$4,股债表现与四个维度!$2:$2&股债表现与四个维度!$3:$3,0))} -> -0.4375 | P27: {=INDEX(股债表现与四个维度!$A:$T,MATCH($A27,股债表现与四个维度!$A:$A,0),MATCH(P$3&P$4,股债表现与四个维度!$2:$2&股债表现与四个维度!$3:$3,0))} -> 0 | Q27: {=INDEX(股债表现与四个维度!$A:$T,MATCH($A27,股债表现与四个维度!$A:$A,0),MATCH(Q$3&Q$4,股债表现与四个维度!$2:$2&股债表现与四个维度!$3:$3,0))} -> 0.33333333 | ... S27: {=INDEX(股债表现与四个维度!$A:$T,MATCH($A27,股债表现与四个维度!$A:$A,0),MATCH(S$3&S$4,股债表现与四个维度!$2:$2&股债表现与四个维度!$3:$3,0))} -> 0.5 | T27: =SUMIFS($J27:$S27,$J27:$S27,"<>"&"#N/A",$J$4:$S$4,T$4) -> -0.040816327 | U27: =SUMIFS($J27:$S27,$J27:$S27,"<>"&"#N/A",$J$4:$S$4,U$4) -> 1.3377486 | V27: =T27-U27 -> -1.3785649 | W27: -3.9967064 | X27: =C27+D27 -> -1.7184807 | Y27: =AVERAGE(V27:V32) -> -1.002581
A28: 45688 | B28: -2.3186982 | C28: -16.228852 | D28: 0.089306256 | E28: =VLOOKUP(A28,美林时钟!A13:AB272,28,TRUE) -> 过热 | F28: 宽货币紧信用 | G28: 双紧 | H28: 主动补库存 | I28: 产能周期下行,主动补库存 | J28: {=INDEX(股债表现与四个维度!$A:$T,MATCH($A28,股债表现与四个维度!$A:$A,0),MATCH(J$3&J$4,股债表现与四个维度!$2:$2&股债表现与四个维度!$3:$3,0))} -> 0.25 | K28: {=INDEX(股债表现与四个维度!$A:$T,MATCH($A28,股债表现与四个维度!$A:$A,0),MATCH(K$3&K$4,股债表现与四个维度!$2:$2&股债表现与四个维度!$3:$3,0))} -> 0.041666667 | L28: {=INDEX(股债表现与四个维度!$A:$T,MATCH($A28,股债表现与四个维度!$A:$A,0),MATCH(L$3&L$4,股债表现与四个维度!$2:$2&股债表现与四个维度!$3:$3,0))} -> -0.020833333 | M28: {=INDEX(股债表现与四个维度!$A:$T,MATCH($A28,股债表现与四个维度!$A:$A,0),MATCH(M$3&M$4,股债表现与四个维度!$2:$2&股债表现与四个维度!$3:$3,0))} -> 0.3125 | N28: {=INDEX(股债表现与四个维度!$A:$T,MATCH($A28,股债表现与四个维度!$A:$A,0),MATCH(N$3&N$4,股债表现与四个维度!$2:$2&股债表现与四个维度!$3:$3,0))} -> 0.13333333 | O28: {=INDEX(股债表现与四个维度!$A:$T,MATCH($A28,股债表现与四个维度!$A:$A,0),MATCH(O$3&O$4,股债表现与四个维度!$2:$2&股债表现与四个维度!$3:$3,0))} -> -0.53333333 | P28: {=INDEX(股债表现与四个维度!$A:$T,MATCH($A28,股债表现与四个维度!$A:$A,0),MATCH(P$3&P$4,股债表现与四个维度!$2:$2&股债表现与四个维度!$3:$3,0))} -> 0 | Q28: {=INDEX(股债表现与四个维度!$A:$T,MATCH($A28,股债表现与四个维度!$A:$A,0),MATCH(Q$3&Q$4,股债表现与四个维度!$2:$2&股债表现与四个维度!$3:$3,0))} -> 0.33333333 | ... S28: {=INDEX(股债表现与四个维度!$A:$T,MATCH($A28,股债表现与四个维度!$A:$A,0),MATCH(S$3&S$4,股债表现与四个维度!$2:$2&股债表现与四个维度!$3:$3,0))} -> 0.46666667 | T28: =SUMIFS($J28:$S28,$J28:$S28,"<>"&"#N/A",$J$4:$S$4,T$4) -> 0.3625 | U28: =SUMIFS($J28:$S28,$J28:$S28,"<>"&"#N/A",$J$4:$S$4,U$4) -> 0.62083333 | V28: =T28-U28 -> -0.25833333 | W28: -7.0871388 | X28: =C28+D28 -> -16.139545 | Y28: =AVERAGE(V28:V33) -> -1.4195336
A29: 45657 | B29: -1.9590725 | C29: -28.86368 | D29: 0.92221589 | E29: =VLOOKUP(A29,美林时钟!A14:AB273,28,TRUE) -> 过热 | F29: 宽货币紧信用 | G29: 双紧 | H29: 被动补库存 | I29: 产能周期下行,主动补库存 | J29: {=INDEX(股债表现与四个维度!$A:$T,MATCH($A29,股债表现与四个维度!$A:$A,0),MATCH(J$3&J$4,股债表现与四个维度!$2:$2&股债表现与四个维度!$3:$3,0))} -> 0.16666667 | K29: {=INDEX(股债表现与四个维度!$A:$T,MATCH($A29,股债表现与四个维度!$A:$A,0),MATCH(K$3&K$4,股债表现与四个维度!$2:$2&股债表现与四个维度!$3:$3,0))} -> 0 | L29: {=INDEX(股债表现与四个维度!$A:$T,MATCH($A29,股债表现与四个维度!$A:$A,0),MATCH(L$3&L$4,股债表现与四个维度!$2:$2&股债表现与四个维度!$3:$3,0))} -> -0.042553191 | M29: {=INDEX(股债表现与四个维度!$A:$T,MATCH($A29,股债表现与四个维度!$A:$A,0),MATCH(M$3&M$4,股债表现与四个维度!$2:$2&股债表现与四个维度!$3:$3,0))} -> 0.29787234 | N29: {=INDEX(股债表现与四个维度!$A:$T,MATCH($A29,股债表现与四个维度!$A:$A,0),MATCH(N$3&N$4,股债表现与四个维度!$2:$2&股债表现与四个维度!$3:$3,0))} -> 0.071428571 | O29: {=INDEX(股债表现与四个维度!$A:$T,MATCH($A29,股债表现与四个维度!$A:$A,0),MATCH(O$3&O$4,股债表现与四个维度!$2:$2&股债表现与四个维度!$3:$3,0))} -> -0.64285714 | P29: {=INDEX(股债表现与四个维度!$A:$T,MATCH($A29,股债表现与四个维度!$A:$A,0),MATCH(P$3&P$4,股债表现与四个维度!$2:$2&股债表现与四个维度!$3:$3,0))} -> 0 | Q29: {=INDEX(股债表现与四个维度!$A:$T,MATCH($A29,股债表现与四个维度!$A:$A,0),MATCH(Q$3&Q$4,股债表现与四个维度!$2:$2&股债表现与四个维度!$3:$3,0))} -> 0.33333333 | ... S29: {=INDEX(股债表现与四个维度!$A:$T,MATCH($A29,股债表现与四个维度!$A:$A,0),MATCH(S$3&S$4,股债表现与四个维度!$2:$2&股债表现与四个维度!$3:$3,0))} -> 0.42857143 | T29: =SUMIFS($J29:$S29,$J29:$S29,"<>"&"#N/A",$J$4:$S$4,T$4) -> 0.12411348 | U29: =SUMIFS($J29:$S29,$J29:$S29,"<>"&"#N/A",$J$4:$S$4,U$4) -> 0.41691996 | V29: =T29-U29 -> -0.29280648 | W29: -4.241618 | X29: =C29+D29 -> -27.941464 | Y29: =AVERAGE(V29:V34) -> -1.7174815 | Z29: =AVERAGE(W29:W34) -> 0.80849249 | AA29: =AVERAGE(X29:X34) -> -7.248321
A30: 45626 | B30: 1.3430445 | C30: -5.8158897 | D30: 0.59258383 | E30: =VLOOKUP(A30,美林时钟!A15:AB274,28,TRUE) -> 过热 | F30: 宽货币紧信用 | G30: 双紧 | H30: 被动补库存 | I30: 产能周期下行,主动补库存 | J30: {=INDEX(股债表现与四个维度!$A:$T,MATCH($A30,股债表现与四个维度!$A:$A,0),MATCH(J$3&J$4,股债表现与四个维度!$2:$2&股债表现与四个维度!$3:$3,0))} -> 0.13043478 | K30: {=INDEX(股债表现与四个维度!$A:$T,MATCH($A30,股债表现与四个维度!$A:$A,0),MATCH(K$3&K$4,股债表现与四个维度!$2:$2&股债表现与四个维度!$3:$3,0))} -> 0.043478261 | L30: {=INDEX(股债表现与四个维度!$A:$T,MATCH($A30,股债表现与四个维度!$A:$A,0),MATCH(L$3&L$4,股债表现与四个维度!$2:$2&股债表现与四个维度!$3:$3,0))} -> -0.065217391 | M30: {=INDEX(股债表现与四个维度!$A:$T,MATCH($A30,股债表现与四个维度!$A:$A,0),MATCH(M$3&M$4,股债表现与四个维度!$2:$2&股债表现与四个维度!$3:$3,0))} -> 0.32608696 | N30: {=INDEX(股债表现与四个维度!$A:$T,MATCH($A30,股债表现与四个维度!$A:$A,0),MATCH(N$3&N$4,股债表现与四个维度!$2:$2&股债表现与四个维度!$3:$3,0))} -> 0 | O30: {=INDEX(股债表现与四个维度!$A:$T,MATCH($A30,股债表现与四个维度!$A:$A,0),MATCH(O$3&O$4,股债表现与四个维度!$2:$2&股债表现与四个维度!$3:$3,0))} -> -0.61538462 | P30: {=INDEX(股债表现与四个维度!$A:$T,MATCH($A30,股债表现与四个维度!$A:$A,0),MATCH(P$3&P$4,股债表现与四个维度!$2:$2&股债表现与四个维度!$3:$3,0))} -> -0.038461538 | Q30: {=INDEX(股债表现与四个维度!$A:$T,MATCH($A30,股债表现与四个维度!$A:$A,0),MATCH(Q$3&Q$4,股债表现与四个维度!$2:$2&股债表现与四个维度!$3:$3,0))} -> 0.38461538 | ... S30: {=INDEX(股债表现与四个维度!$A:$T,MATCH($A30,股债表现与四个维度!$A:$A,0),MATCH(S$3&S$4,股债表现与四个维度!$2:$2&股债表现与四个维度!$3:$3,0))} -> 0.53846154 | T30: =SUMIFS($J30:$S30,$J30:$S30,"<>"&"#N/A",$J$4:$S$4,T$4) -> -0.1270903 | U30: =SUMIFS($J30:$S30,$J30:$S30,"<>"&"#N/A",$J$4:$S$4,U$4) -> 0.67725753 | V30: =T30-U30 -> -0.80434783 | W30: -0.7533162 | X30: =C30+D30 -> -5.2233059 | Y30: =AVERAGE(V30:V35) -> -2.0424001 | Z30: =AVERAGE(W30:W35) -> -0.13339469 | AA30: =AVERAGE(X30:X35) -> -3.3452051
A31: 45596 | B31: 2.2784563 | C31: 4.251604 | D31: 0.14691428 | E31: =VLOOKUP(A31,美林时钟!A16:AB275,28,TRUE) -> 复苏 | F31: 宽货币紧信用 | G31: 双紧 | H31: 被动补库存 | I31: 产能周期下行,主动补库存 | J31: {=INDEX(股债表现与四个维度!$A:$T,MATCH($A31,股债表现与四个维度!$A:$A,0),MATCH(J$3&J$4,股债表现与四个维度!$2:$2&股债表现与四个维度!$3:$3,0))} -> 0.090909091 | K31: {=INDEX(股债表现与四个维度!$A:$T,MATCH($A31,股债表现与四个维度!$A:$A,0),MATCH(K$3&K$4,股债表现与四个维度!$2:$2&股债表现与四个维度!$3:$3,0))} -> 0 | L31: {=INDEX(股债表现与四个维度!$A:$T,MATCH($A31,股债表现与四个维度!$A:$A,0),MATCH(L$3&L$4,股债表现与四个维度!$2:$2&股债表现与四个维度!$3:$3,0))} -> -0.088888889 | M31: {=INDEX(股债表现与四个维度!$A:$T,MATCH($A31,股债表现与四个维度!$A:$A,0),MATCH(M$3&M$4,股债表现与四个维度!$2:$2&股债表现与四个维度!$3:$3,0))} -> 0.31111111 | N31: {=INDEX(股债表现与四个维度!$A:$T,MATCH($A31,股债表现与四个维度!$A:$A,0),MATCH(N$3&N$4,股债表现与四个维度!$2:$2&股债表现与四个维度!$3:$3,0))} -> 0 | O31: {=INDEX(股债表现与四个维度!$A:$T,MATCH($A31,股债表现与四个维度!$A:$A,0),MATCH(O$3&O$4,股债表现与四个维度!$2:$2&股债表现与四个维度!$3:$3,0))} -> -0.61538462 | P31: {=INDEX(股债表现与四个维度!$A:$T,MATCH($A31,股债表现与四个维度!$A:$A,0),MATCH(P$3&P$4,股债表现与四个维度!$2:$2&股债表现与四个维度!$3:$3,0))} -> -0.08 | Q31: {=INDEX(股债表现与四个维度!$A:$T,MATCH($A31,股债表现与四个维度!$A:$A,0),MATCH(Q$3&Q$4,股债表现与四个维度!$2:$2&股债表现与四个维度!$3:$3,0))} -> 0.36 | ... S31: {=INDEX(股债表现与四个维度!$A:$T,MATCH($A31,股债表现与四个维度!$A:$A,0),MATCH(S$3&S$4,股债表现与四个维度!$2:$2&股债表现与四个维度!$3:$3,0))} -> 0.5 | T31: =SUMIFS($J31:$S31,$J31:$S31,"<>"&"#N/A",$J$4:$S$4,T$4) -> -0.3279798 | U31: =SUMIFS($J31:$S31,$J31:$S31,"<>"&"#N/A",$J$4:$S$4,U$4) -> 0.5557265 | V31: =T31-U31 -> -0.88370629 | W31: =B31+C31 -> 6.5300603 | X31: =C31+D31 -> 4.3985183 | Y31: =AVERAGE(V31:V36) -> -2.3084846 | Z31: =AVERAGE(W31:W36) -> 0.14161396 | AA31: =AVERAGE(X31:X36) -> -2.7406311
A32: 45565 | B32: 22.210135 | C32: -6.9838528 | D32: 0.32825829 | E32: =VLOOKUP(A32,美林时钟!A17:AB276,28,TRUE) -> 复苏 | F32: 宽货币紧信用 | G32: 紧货币宽财政 | H32: 被动补库存 | I32: 产能周期下行,主动补库存 | J32: {=INDEX(股债表现与四个维度!$A:$T,MATCH($A32,股债表现与四个维度!$A:$A,0),MATCH(J$3&J$4,股债表现与四个维度!$2:$2&股债表现与四个维度!$3:$3,0))} -> 0.090909091 | K32: {=INDEX(股债表现与四个维度!$A:$T,MATCH($A32,股债表现与四个维度!$A:$A,0),MATCH(K$3&K$4,股债表现与四个维度!$2:$2&股债表现与四个维度!$3:$3,0))} -> 0 | L32: {=INDEX(股债表现与四个维度!$A:$T,MATCH($A32,股债表现与四个维度!$A:$A,0),MATCH(L$3&L$4,股债表现与四个维度!$2:$2&股债表现与四个维度!$3:$3,0))} -> -0.068181818 | M32: {=INDEX(股债表现与四个维度!$A:$T,MATCH($A32,股债表现与四个维度!$A:$A,0),MATCH(M$3&M$4,股债表现与四个维度!$2:$2&股债表现与四个维度!$3:$3,0))} -> 0.29545455 | N32: {=INDEX(股债表现与四个维度!$A:$T,MATCH($A32,股债表现与四个维度!$A:$A,0),MATCH(N$3&N$4,股债表现与四个维度!$2:$2&股债表现与四个维度!$3:$3,0))} -> -0.5 | O32: {=INDEX(股债表现与四个维度!$A:$T,MATCH($A32,股债表现与四个维度!$A:$A,0),MATCH(O$3&O$4,股债表现与四个维度!$2:$2&股债表现与四个维度!$3:$3,0))} -> 0.5 | P32: {=INDEX(股债表现与四个维度!$A:$T,MATCH($A32,股债表现与四个维度!$A:$A,0),MATCH(P$3&P$4,股债表现与四个维度!$2:$2&股债表现与四个维度!$3:$3,0))} -> -0.041666667 | Q32: {=INDEX(股债表现与四个维度!$A:$T,MATCH($A32,股债表现与四个维度!$A:$A,0),MATCH(Q$3&Q$4,股债表现与四个维度!$2:$2&股债表现与四个维度!$3:$3,0))} -> 0.33333333 | ... S32: {=INDEX(股债表现与四个维度!$A:$T,MATCH($A32,股债表现与四个维度!$A:$A,0),MATCH(S$3&S$4,股债表现与四个维度!$2:$2&股债表现与四个维度!$3:$3,0))} -> 0.5 | T32: =SUMIFS($J32:$S32,$J32:$S32,"<>"&"#N/A",$J$4:$S$4,T$4) -> -0.76893939 | U32: =SUMIFS($J32:$S32,$J32:$S32,"<>"&"#N/A",$J$4:$S$4,U$4) -> 1.6287879 | V32: =T32-U32 -> -2.3977273 | W32: =B32+C32 -> 15.226282 | X32: =C32+D32 -> -6.6555945 | Y32: =AVERAGE(V32:V37) -> -2.5968375 | Z32: =AVERAGE(W32:W37) -> -1.1986391 | AA32: =AVERAGE(X32:X37) -> -3.3786863
A33: 45535 | B33: -3.9690314 | C33: -6.466996 | D33: -0.15323648 | E33: =VLOOKUP(A33,美林时钟!A18:AB277,28,TRUE) -> 衰退 | F33: 宽货币紧信用 | G33: 紧货币宽财政 | H33: 被动补库存 | I33: 产能周期下行,被动去库存 | J33: {=INDEX(股债表现与四个维度!$A:$T,MATCH($A33,股债表现与四个维度!$A:$A,0),MATCH(J$3&J$4,股债表现与四个维度!$2:$2&股债表现与四个维度!$3:$3,0))} -> 0.090909091 | K33: {=INDEX(股债表现与四个维度!$A:$T,MATCH($A33,股债表现与四个维度!$A:$A,0),MATCH(K$3&K$4,股债表现与四个维度!$2:$2&股债表现与四个维度!$3:$3,0))} -> 0.63636364 | L33: {=INDEX(股债表现与四个维度!$A:$T,MATCH($A33,股债表现与四个维度!$A:$A,0),MATCH(L$3&L$4,股债表现与四个维度!$2:$2&股债表现与四个维度!$3:$3,0))} -> -0.069767442 | M33: {=INDEX(股债表现与四个维度!$A:$T,MATCH($A33,股债表现与四个维度!$A:$A,0),MATCH(M$3&M$4,股债表现与四个维度!$2:$2&股债表现与四个维度!$3:$3,0))} -> 0.30232558 | N33: {=INDEX(股债表现与四个维度!$A:$T,MATCH($A33,股债表现与四个维度!$A:$A,0),MATCH(N$3&N$4,股债表现与四个维度!$2:$2&股债表现与四个维度!$3:$3,0))} -> -1 | O33: {=INDEX(股债表现与四个维度!$A:$T,MATCH($A33,股债表现与四个维度!$A:$A,0),MATCH(O$3&O$4,股债表现与四个维度!$2:$2&股债表现与四个维度!$3:$3,0))} -> 1 | P33: {=INDEX(股债表现与四个维度!$A:$T,MATCH($A33,股债表现与四个维度!$A:$A,0),MATCH(P$3&P$4,股债表现与四个维度!$2:$2&股债表现与四个维度!$3:$3,0))} -> -0.043478261 | Q33: {=INDEX(股债表现与四个维度!$A:$T,MATCH($A33,股债表现与四个维度!$A:$A,0),MATCH(Q$3&Q$4,股债表现与四个维度!$2:$2&股债表现与四个维度!$3:$3,0))} -> 0.34782609 | ... S33: {=INDEX(股债表现与四个维度!$A:$T,MATCH($A33,股债表现与四个维度!$A:$A,0),MATCH(S$3&S$4,股债表现与四个维度!$2:$2&股债表现与四个维度!$3:$3,0))} -> 0.42857143 | T33: =SUMIFS($J33:$S33,$J33:$S33,"<>"&"#N/A",$J$4:$S$4,T$4) -> -1.1651938 | U33: =SUMIFS($J33:$S33,$J33:$S33,"<>"&"#N/A",$J$4:$S$4,U$4) -> 2.7150867 | V33: =T33-U33 -> -3.8802805 | W33: =B33+C33 -> -10.436027 | X33: =C33+D33 -> -6.6202325 | Y33: =AVERAGE(V33:V38) -> -2.6485948 | Z33: =AVERAGE(W33:W38) -> -5.9851539 | AA33: =AVERAGE(X33:X38) -> -2.0758991
A34: 45504 | B34: 0.27106655 | C34: -1.745492 | D34: 0.29764466 | E34: =VLOOKUP(A34,美林时钟!A19:AB278,28,TRUE) -> 滞涨 | F34: 宽货币紧信用 | G34: 紧货币宽财政 | H34: 主动补库存 | I34: 产能周期下行,被动去库存 | J34: {=INDEX(股债表现与四个维度!$A:$T,MATCH($A34,股债表现与四个维度!$A:$A,0),MATCH(J$3&J$4,股债表现与四个维度!$2:$2&股债表现与四个维度!$3:$3,0))} -> 0.2 | K34: {=INDEX(股债表现与四个维度!$A:$T,MATCH($A34,股债表现与四个维度!$A:$A,0),MATCH(K$3&K$4,股债表现与四个维度!$2:$2&股债表现与四个维度!$3:$3,0))} -> 0.6 | L34: {=INDEX(股债表现与四个维度!$A:$T,MATCH($A34,股债表现与四个维度!$A:$A,0),MATCH(L$3&L$4,股债表现与四个维度!$2:$2&股债表现与四个维度!$3:$3,0))} -> -0.047619048 | M34: {=INDEX(股债表现与四个维度!$A:$T,MATCH($A34,股债表现与四个维度!$A:$A,0),MATCH(M$3&M$4,股债表现与四个维度!$2:$2&股债表现与四个维度!$3:$3,0))} -> 0.28571429 | N34: {=INDEX(股债表现与四个维度!$A:$T,MATCH($A34,股债表现与四个维度!$A:$A,0),MATCH(N$3&N$4,股债表现与四个维度!$2:$2&股债表现与四个维度!$3:$3,0))} -> 0.038461538 | O34: {=INDEX(股债表现与四个维度!$A:$T,MATCH($A34,股债表现与四个维度!$A:$A,0),MATCH(O$3&O$4,股债表现与四个维度!$2:$2&股债表现与四个维度!$3:$3,0))} -> 0.46153846 | P34: {=INDEX(股债表现与四个维度!$A:$T,MATCH($A34,股债表现与四个维度!$A:$A,0),MATCH(P$3&P$4,股债表现与四个维度!$2:$2&股债表现与四个维度!$3:$3,0))} -> 0 | Q34: {=INDEX(股债表现与四个维度!$A:$T,MATCH($A34,股债表现与四个维度!$A:$A,0),MATCH(Q$3&Q$4,股债表现与四个维度!$2:$2&股债表现与四个维度!$3:$3,0))} -> 0.31818182 | ... S34: {=INDEX(股债表现与四个维度!$A:$T,MATCH($A34,股债表现与四个维度!$A:$A,0),MATCH(S$3&S$4,股债表现与四个维度!$2:$2&股债表现与四个维度!$3:$3,0))} -> 0.42857143 | T34: =SUMIFS($J34:$S34,$J34:$S34,"<>"&"#N/A",$J$4:$S$4,T$4) -> 0.047985348 | U34: =SUMIFS($J34:$S34,$J34:$S34,"<>"&"#N/A",$J$4:$S$4,U$4) -> 2.094006 | V34: =T34-U34 -> -2.0460206 | W34: =B34+C34 -> -1.4744254 | X34: =C34+D34 -> -1.4478473 | Y34: =AVERAGE(V34:V39) -> -2.2078799 | Z34: =AVERAGE(W34:W39) -> -5.9292295 | AA34: =AVERAGE(X34:X39) -> -1.4462161
A35: 45473 | B35: -5.1273772 | C35: -4.7655639 | D35: 0.24279531 | E35: =VLOOKUP(A35,美林时钟!A20:AB279,28,TRUE) -> 滞涨 | F35: 宽货币紧信用 | G35: 紧货币宽财政 | H35: 被动补库存 | I35: 产能周期下行,主动补库存 | J35: {=INDEX(股债表现与四个维度!$A:$T,MATCH($A35,股债表现与四个维度!$A:$A,0),MATCH(J$3&J$4,股债表现与四个维度!$2:$2&股债表现与四个维度!$3:$3,0))} -> 0.33333333 | K35: {=INDEX(股债表现与四个维度!$A:$T,MATCH($A35,股债表现与四个维度!$A:$A,0),MATCH(K$3&K$4,股债表现与四个维度!$2:$2&股债表现与四个维度!$3:$3,0))} -> 0.77777778 | L35: {=INDEX(股债表现与四个维度!$A:$T,MATCH($A35,股债表现与四个维度!$A:$A,0),MATCH(L$3&L$4,股债表现与四个维度!$2:$2&股债表现与四个维度!$3:$3,0))} -> -0.024390244 | M35: {=INDEX(股债表现与四个维度!$A:$T,MATCH($A35,股债表现与四个维度!$A:$A,0),MATCH(M$3&M$4,股债表现与四个维度!$2:$2&股债表现与四个维度!$3:$3,0))} -> 0.31707317 | N35: {=INDEX(股债表现与四个维度!$A:$T,MATCH($A35,股债表现与四个维度!$A:$A,0),MATCH(N$3&N$4,股债表现与四个维度!$2:$2&股债表现与四个维度!$3:$3,0))} -> 0.038461538 | O35: {=INDEX(股债表现与四个维度!$A:$T,MATCH($A35,股债表现与四个维度!$A:$A,0),MATCH(O$3&O$4,股债表现与四个维度!$2:$2&股债表现与四个维度!$3:$3,0))} -> 0.46153846 | P35: {=INDEX(股债表现与四个维度!$A:$T,MATCH($A35,股债表现与四个维度!$A:$A,0),MATCH(P$3&P$4,股债表现与四个维度!$2:$2&股债表现与四个维度!$3:$3,0))} -> 0.047619048 | Q35: {=INDEX(股债表现与四个维度!$A:$T,MATCH($A35,股债表现与四个维度!$A:$A,0),MATCH(Q$3&Q$4,股债表现与四个维度!$2:$2&股债表现与四个维度!$3:$3,0))} -> 0.38095238 | ... S35: {=INDEX(股债表现与四个维度!$A:$T,MATCH($A35,股债表现与四个维度!$A:$A,0),MATCH(S$3&S$4,股债表现与四个维度!$2:$2&股债表现与四个维度!$3:$3,0))} -> 0.6 | T35: =SUMIFS($J35:$S35,$J35:$S35,"<>"&"#N/A",$J$4:$S$4,T$4) -> 0.29502368 | U35: =SUMIFS($J35:$S35,$J35:$S35,"<>"&"#N/A",$J$4:$S$4,U$4) -> 2.5373418 | V35: =T35-U35 -> -2.2423181 | W35: =B35+C35 -> -9.8929411 | X35: =C35+D35 -> -4.5227686 | Y35: =AVERAGE(V35:V40) -> -2.0208268 | Z35: =AVERAGE(W35:W40) -> -6.87476 | AA35: =AVERAGE(X35:X40) -> -1.6221612
A36: 45443 | B36: -1.2058617 | C36: 2.1025974 | D36: 0.39 | E36: 滞涨 | F36: 宽货币紧信用 | G36: 双宽 | H36: 被动补库存 | I36: 产能周期下行,主动补库存 | J36: {=INDEX(股债表现与四个维度!$A:$T,MATCH($A36,股债表现与四个维度!$A:$A,0),MATCH(J$3&J$4,股债表现与四个维度!$2:$2&股债表现与四个维度!$3:$3,0))} -> 0.25 | K36: {=INDEX(股债表现与四个维度!$A:$T,MATCH($A36,股债表现与四个维度!$A:$A,0),MATCH(K$3&K$4,股债表现与四个维度!$2:$2&股债表现与四个维度!$3:$3,0))} -> 0.75 | L36: {=INDEX(股债表现与四个维度!$A:$T,MATCH($A36,股债表现与四个维度!$A:$A,0),MATCH(L$3&L$4,股债表现与四个维度!$2:$2&股债表现与四个维度!$3:$3,0))} -> -0.05 | M36: {=INDEX(股债表现与四个维度!$A:$T,MATCH($A36,股债表现与四个维度!$A:$A,0),MATCH(M$3&M$4,股债表现与四个维度!$2:$2&股债表现与四个维度!$3:$3,0))} -> 0.3 | N36: {=INDEX(股债表现与四个维度!$A:$T,MATCH($A36,股债表现与四个维度!$A:$A,0),MATCH(N$3&N$4,股债表现与四个维度!$2:$2&股债表现与四个维度!$3:$3,0))} -> 0.038461538 | O36: {=INDEX(股债表现与四个维度!$A:$T,MATCH($A36,股债表现与四个维度!$A:$A,0),MATCH(O$3&O$4,股债表现与四个维度!$2:$2&股债表现与四个维度!$3:$3,0))} -> 0.46153846 | P36: {=INDEX(股债表现与四个维度!$A:$T,MATCH($A36,股债表现与四个维度!$A:$A,0),MATCH(P$3&P$4,股债表现与四个维度!$2:$2&股债表现与四个维度!$3:$3,0))} -> 0 | Q36: {=INDEX(股债表现与四个维度!$A:$T,MATCH($A36,股债表现与四个维度!$A:$A,0),MATCH(Q$3&Q$4,股债表现与四个维度!$2:$2&股债表现与四个维度!$3:$3,0))} -> 0.35 | ... S36: {=INDEX(股债表现与四个维度!$A:$T,MATCH($A36,股债表现与四个维度!$A:$A,0),MATCH(S$3&S$4,股债表现与四个维度!$2:$2&股债表现与四个维度!$3:$3,0))} -> 0.55555556 | T36: =SUMIFS($J36:$S36,$J36:$S36,"<>"&"#N/A",$J$4:$S$4,T$4) -> 0.016239316 | U36: =SUMIFS($J36:$S36,$J36:$S36,"<>"&"#N/A",$J$4:$S$4,U$4) -> 2.417094 | V36: =T36-U36 -> -2.4008547 | W36: =B36+C36 -> 0.89673569 | X36: =B36-D36 -> -1.5958617 | Y36: =AVERAGE(V36:V41) -> -1.849816 | Z36: =AVERAGE(W36:W41) -> -5.6043879 | AA36: =AVERAGE(X36:X41) -> -0.83161845
A37: 45412 | B37: 1.0201867 | C37: -2.531645 | D37: 0.45 | E37: 滞涨 | F37: 宽货币紧信用 | G37: 双宽 | H37: 被动补库存 | I37: 产能周期下行,主动补库存 | J37: {=INDEX(股债表现与四个维度!$A:$T,MATCH($A37,股债表现与四个维度!$A:$A,0),MATCH(J$3&J$4,股债表现与四个维度!$2:$2&股债表现与四个维度!$3:$3,0))} -> 0.14285714 | K37: {=INDEX(股债表现与四个维度!$A:$T,MATCH($A37,股债表现与四个维度!$A:$A,0),MATCH(K$3&K$4,股债表现与四个维度!$2:$2&股债表现与四个维度!$3:$3,0))} -> 0.71428571 | L37: {=INDEX(股债表现与四个维度!$A:$T,MATCH($A37,股债表现与四个维度!$A:$A,0),MATCH(L$3&L$4,股债表现与四个维度!$2:$2&股债表现与四个维度!$3:$3,0))} -> -0.076923077 | M37: {=INDEX(股债表现与四个维度!$A:$T,MATCH($A37,股债表现与四个维度!$A:$A,0),MATCH(M$3&M$4,股债表现与四个维度!$2:$2&股债表现与四个维度!$3:$3,0))} -> 0.28205128 | N37: {=INDEX(股债表现与四个维度!$A:$T,MATCH($A37,股债表现与四个维度!$A:$A,0),MATCH(N$3&N$4,股债表现与四个维度!$2:$2&股债表现与四个维度!$3:$3,0))} -> 0 | O37: {=INDEX(股债表现与四个维度!$A:$T,MATCH($A37,股债表现与四个维度!$A:$A,0),MATCH(O$3&O$4,股债表现与四个维度!$2:$2&股债表现与四个维度!$3:$3,0))} -> 0.44 | P37: {=INDEX(股债表现与四个维度!$A:$T,MATCH($A37,股债表现与四个维度!$A:$A,0),MATCH(P$3&P$4,股债表现与四个维度!$2:$2&股债表现与四个维度!$3:$3,0))} -> -0.052631579 | Q37: {=INDEX(股债表现与四个维度!$A:$T,MATCH($A37,股债表现与四个维度!$A:$A,0),MATCH(Q$3&Q$4,股债表现与四个维度!$2:$2&股债表现与四个维度!$3:$3,0))} -> 0.31578947 | ... S37: {=INDEX(股债表现与四个维度!$A:$T,MATCH($A37,股债表现与四个维度!$A:$A,0),MATCH(S$3&S$4,股债表现与四个维度!$2:$2&股债表现与四个维度!$3:$3,0))} -> 0.5 | T37: =SUMIFS($J37:$S37,$J37:$S37,"<>"&"#N/A",$J$4:$S$4,T$4) -> -0.36169751 | U37: =SUMIFS($J37:$S37,$J37:$S37,"<>"&"#N/A",$J$4:$S$4,U$4) -> 2.2521265 | V37: =T37-U37 -> -2.613824 | W37: =B37+C37 -> -1.5114583 | X37: =B37-D37 -> 0.57018669 | Y37: =AVERAGE(V37:V42) -> -1.6840842 | Z37: =AVERAGE(W37:W42) -> -5.2939375 | AA37: =AVERAGE(X37:X42) -> -0.91933607
A38: 45382 | B38: 1.3511291 | C38: -14.843936 | D38: 0.19 | E38: 滞涨 | F38: 宽货币紧信用 | G38: 双宽 | H38: 被动补库存 | I38: 产能周期下行,主动补库存 | J38: {=INDEX(股债表现与四个维度!$A:$T,MATCH($A38,股债表现与四个维度!$A:$A,0),MATCH(J$3&J$4,股债表现与四个维度!$2:$2&股债表现与四个维度!$3:$3,0))} -> 0.14285714 | K38: {=INDEX(股债表现与四个维度!$A:$T,MATCH($A38,股债表现与四个维度!$A:$A,0),MATCH(K$3&K$4,股债表现与四个维度!$2:$2&股债表现与四个维度!$3:$3,0))} -> 0.71428571 | L38: {=INDEX(股债表现与四个维度!$A:$T,MATCH($A38,股债表现与四个维度!$A:$A,0),MATCH(L$3&L$4,股债表现与四个维度!$2:$2&股债表现与四个维度!$3:$3,0))} -> -0.10526316 | M38: {=INDEX(股债表现与四个维度!$A:$T,MATCH($A38,股债表现与四个维度!$A:$A,0),MATCH(M$3&M$4,股债表现与四个维度!$2:$2&股债表现与四个维度!$3:$3,0))} -> 0.26315789 | N38: {=INDEX(股债表现与四个维度!$A:$T,MATCH($A38,股债表现与四个维度!$A:$A,0),MATCH(N$3&N$4,股债表现与四个维度!$2:$2&股债表现与四个维度!$3:$3,0))} -> 0 | O38: {=INDEX(股债表现与四个维度!$A:$T,MATCH($A38,股债表现与四个维度!$A:$A,0),MATCH(O$3&O$4,股债表现与四个维度!$2:$2&股债表现与四个维度!$3:$3,0))} -> 0.4 | P38: {=INDEX(股债表现与四个维度!$A:$T,MATCH($A38,股债表现与四个维度!$A:$A,0),MATCH(P$3&P$4,股债表现与四个维度!$2:$2&股债表现与四个维度!$3:$3,0))} -> -0.052631579 | Q38: {=INDEX(股债表现与四个维度!$A:$T,MATCH($A38,股债表现与四个维度!$A:$A,0),MATCH(Q$3&Q$4,股债表现与四个维度!$2:$2&股债表现与四个维度!$3:$3,0))} -> 0.31578947 | ... S38: {=INDEX(股债表现与四个维度!$A:$T,MATCH($A38,股债表现与四个维度!$A:$A,0),MATCH(S$3&S$4,股债表现与四个维度!$2:$2&股债表现与四个维度!$3:$3,0))} -> 0.42857143 | T38: =SUMIFS($J38:$S38,$J38:$S38,"<>"&"#N/A",$J$4:$S$4,T$4) -> -0.58646617 | U38: =SUMIFS($J38:$S38,$J38:$S38,"<>"&"#N/A",$J$4:$S$4,U$4) -> 2.1218045 | V38: =T38-U38 -> -2.7082707 | W38: =B38+C38 -> -13.492807 | X38: =B38-D38 -> 1.1611291 | Y38: =AVERAGE(V38:V43) -> -1.2461303 | Z38: =AVERAGE(W38:W43) -> -4.4443731 | AA38: =AVERAGE(X38:X43) -> -1.1727379
A39: 45351 | B39: -2.072135 | C39: -8.028346 | D39: 0.77 | E39: 过热 | F39: 宽货币紧信用 | G39: 双宽 | H39: 主动去库存 | I39: 产能周期下行,主动补库存 | J39: {=INDEX(股债表现与四个维度!$A:$T,MATCH($A39,股债表现与四个维度!$A:$A,0),MATCH(J$3&J$4,股债表现与四个维度!$2:$2&股债表现与四个维度!$3:$3,0))} -> 0.1 | K39: {=INDEX(股债表现与四个维度!$A:$T,MATCH($A39,股债表现与四个维度!$A:$A,0),MATCH(K$3&K$4,股债表现与四个维度!$2:$2&股债表现与四个维度!$3:$3,0))} -> -0.1 | L39: {=INDEX(股债表现与四个维度!$A:$T,MATCH($A39,股债表现与四个维度!$A:$A,0),MATCH(L$3&L$4,股债表现与四个维度!$2:$2&股债表现与四个维度!$3:$3,0))} -> -0.081081081 | M39: {=INDEX(股债表现与四个维度!$A:$T,MATCH($A39,股债表现与四个维度!$A:$A,0),MATCH(M$3&M$4,股债表现与四个维度!$2:$2&股债表现与四个维度!$3:$3,0))} -> 0.24324324 | N39: {=INDEX(股债表现与四个维度!$A:$T,MATCH($A39,股债表现与四个维度!$A:$A,0),MATCH(N$3&N$4,股债表现与四个维度!$2:$2&股债表现与四个维度!$3:$3,0))} -> 0.08 | O39: {=INDEX(股债表现与四个维度!$A:$T,MATCH($A39,股债表现与四个维度!$A:$A,0),MATCH(O$3&O$4,股债表现与四个维度!$2:$2&股债表现与四个维度!$3:$3,0))} -> 0.4 | P39: {=INDEX(股债表现与四个维度!$A:$T,MATCH($A39,股债表现与四个维度!$A:$A,0),MATCH(P$3&P$4,股债表现与四个维度!$2:$2&股债表现与四个维度!$3:$3,0))} -> 0.16666667 | Q39: {=INDEX(股债表现与四个维度!$A:$T,MATCH($A39,股债表现与四个维度!$A:$A,0),MATCH(Q$3&Q$4,股债表现与四个维度!$2:$2&股债表现与四个维度!$3:$3,0))} -> 0.125 | ... S39: {=INDEX(股债表现与四个维度!$A:$T,MATCH($A39,股债表现与四个维度!$A:$A,0),MATCH(S$3&S$4,股债表现与四个维度!$2:$2&股债表现与四个维度!$3:$3,0))} -> 0.33333333 | T39: =SUMIFS($J39:$S39,$J39:$S39,"<>"&"#N/A",$J$4:$S$4,T$4) -> -0.23441441 | U39: =SUMIFS($J39:$S39,$J39:$S39,"<>"&"#N/A",$J$4:$S$4,U$4) -> 1.0015766 | V39: =T39-U39 -> -1.235991 | W39: =B39+C39 -> -10.100481 | X39: =B39-D39 -> -2.842135 | Y39: =AVERAGE(V39:V44) -> -0.86496174 | Z39: =AVERAGE(W39:W44) -> -3.7673704 | AA39: =AVERAGE(X39:X44) -> -2.3335443
A40: 45291 | B40: -2.0535176 | C40: -5.0940909 | D40: 0.45 | E40: 过热 | F40: 宽货币紧信用 | G40: 双宽 | H40: 被动补库存 | I40: 产能周期下行,主动补库存 | J40: {=INDEX(股债表现与四个维度!$A:$T,MATCH($A40,股债表现与四个维度!$A:$A,0),MATCH(J$3&J$4,股债表现与四个维度!$2:$2&股债表现与四个维度!$3:$3,0))} -> 0.16666667 | K40: {=INDEX(股债表现与四个维度!$A:$T,MATCH($A40,股债表现与四个维度!$A:$A,0),MATCH(K$3&K$4,股债表现与四个维度!$2:$2&股债表现与四个维度!$3:$3,0))} -> -0.22222222 | L40: {=INDEX(股债表现与四个维度!$A:$T,MATCH($A40,股债表现与四个维度!$A:$A,0),MATCH(L$3&L$4,股债表现与四个维度!$2:$2&股债表现与四个维度!$3:$3,0))} -> -0.054054054 | M40: {=INDEX(股债表现与四个维度!$A:$T,MATCH($A40,股债表现与四个维度!$A:$A,0),MATCH(M$3&M$4,股债表现与四个维度!$2:$2&股债表现与四个维度!$3:$3,0))} -> 0.24324324 | N40: {=INDEX(股债表现与四个维度!$A:$T,MATCH($A40,股债表现与四个维度!$A:$A,0),MATCH(N$3&N$4,股债表现与四个维度!$2:$2&股债表现与四个维度!$3:$3,0))} -> 0.12 | O40: {=INDEX(股债表现与四个维度!$A:$T,MATCH($A40,股债表现与四个维度!$A:$A,0),MATCH(O$3&O$4,股债表现与四个维度!$2:$2&股债表现与四个维度!$3:$3,0))} -> 0.4 | P40: {=INDEX(股债表现与四个维度!$A:$T,MATCH($A40,股债表现与四个维度!$A:$A,0),MATCH(P$3&P$4,股债表现与四个维度!$2:$2&股债表现与四个维度!$3:$3,0))} -> 0 | Q40: {=INDEX(股债表现与四个维度!$A:$T,MATCH($A40,股债表现与四个维度!$A:$A,0),MATCH(Q$3&Q$4,股债表现与四个维度!$2:$2&股债表现与四个维度!$3:$3,0))} -> 0.23529412 | ... S40: {=INDEX(股债表现与四个维度!$A:$T,MATCH($A40,股债表现与四个维度!$A:$A,0),MATCH(S$3&S$4,股债表现与四个维度!$2:$2&股债表现与四个维度!$3:$3,0))} -> 0 | T40: =SUMIFS($J40:$S40,$J40:$S40,"<>"&"#N/A",$J$4:$S$4,T$4) -> -0.26738739 | U40: =SUMIFS($J40:$S40,$J40:$S40,"<>"&"#N/A",$J$4:$S$4,U$4) -> 0.65631514 | V40: =T40-U40 -> -0.92370253 | W40: =B40+C40 -> -7.1476085 | X40: =B40-D40 -> -2.5035176 | Y40: =AVERAGE(V40:V45) -> -0.77144221 | Z40: =AVERAGE(W40:W45) -> -2.1617524 | AA40: =AVERAGE(X40:X45) -> -1.5061427
A41: 45260 | B41: 0.35048789 | C41: -2.6211962 | D41: 0.13 | E41: 过热 | F41: 宽货币紧信用 | G41: 双宽 | H41: 被动补库存 | I41: 产能周期下行,主动补库存 | J41: {=INDEX(股债表现与四个维度!$A:$T,MATCH($A41,股债表现与四个维度!$A:$A,0),MATCH(J$3&J$4,股债表现与四个维度!$2:$2&股债表现与四个维度!$3:$3,0))} -> 0.23529412 | K41: {=INDEX(股债表现与四个维度!$A:$T,MATCH($A41,股债表现与四个维度!$A:$A,0),MATCH(K$3&K$4,股债表现与四个维度!$2:$2&股债表现与四个维度!$3:$3,0))} -> -0.17647059 | L41: {=INDEX(股债表现与四个维度!$A:$T,MATCH($A41,股债表现与四个维度!$A:$A,0),MATCH(L$3&L$4,股债表现与四个维度!$2:$2&股债表现与四个维度!$3:$3,0))} -> -0.054054054 | M41: {=INDEX(股债表现与四个维度!$A:$T,MATCH($A41,股债表现与四个维度!$A:$A,0),MATCH(M$3&M$4,股债表现与四个维度!$2:$2&股债表现与四个维度!$3:$3,0))} -> 0.2972973 | N41: {=INDEX(股债表现与四个维度!$A:$T,MATCH($A41,股债表现与四个维度!$A:$A,0),MATCH(N$3&N$4,股债表现与四个维度!$2:$2&股债表现与四个维度!$3:$3,0))} -> 0.12 | O41: {=INDEX(股债表现与四个维度!$A:$T,MATCH($A41,股债表现与四个维度!$A:$A,0),MATCH(O$3&O$4,股债表现与四个维度!$2:$2&股债表现与四个维度!$3:$3,0))} -> 0.48 | P41: {=INDEX(股债表现与四个维度!$A:$T,MATCH($A41,股债表现与四个维度!$A:$A,0),MATCH(P$3&P$4,股债表现与四个维度!$2:$2&股债表现与四个维度!$3:$3,0))} -> 0.0625 | Q41: {=INDEX(股债表现与四个维度!$A:$T,MATCH($A41,股债表现与四个维度!$A:$A,0),MATCH(Q$3&Q$4,股债表现与四个维度!$2:$2&股债表现与四个维度!$3:$3,0))} -> 0.3125 | ... S41: {=INDEX(股债表现与四个维度!$A:$T,MATCH($A41,股债表现与四个维度!$A:$A,0),MATCH(S$3&S$4,股债表现与四个维度!$2:$2&股债表现与四个维度!$3:$3,0))} -> 0.33333333 | T41: =SUMIFS($J41:$S41,$J41:$S41,"<>"&"#N/A",$J$4:$S$4,T$4) -> 0.03040673 | U41: =SUMIFS($J41:$S41,$J41:$S41,"<>"&"#N/A",$J$4:$S$4,U$4) -> 1.24666 | V41: =T41-U41 -> -1.2162533 | W41: =B41+C41 -> -2.2707083 | X41: =B41-D41 -> 0.22048789 | Y41: =AVERAGE(V41:V46) -> -0.79189289 | Z41: =AVERAGE(W41:W46) -> -1.5478393 | AA41: =AVERAGE(X41:X46) -> -0.87743526
A42: 45230 | B42: -2.1621674 | C42: 4.9216053 | D42: -0.04 | E42: 过热 | F42: 宽货币紧信用 | G42: 双宽 | H42: 被动补库存 | I42: 产能周期下行,主动补库存 | J42: {=INDEX(股债表现与四个维度!$A:$T,MATCH($A42,股债表现与四个维度!$A:$A,0),MATCH(J$3&J$4,股债表现与四个维度!$2:$2&股债表现与四个维度!$3:$3,0))} -> 0.3125 | K42: {=INDEX(股债表现与四个维度!$A:$T,MATCH($A42,股债表现与四个维度!$A:$A,0),MATCH(K$3&K$4,股债表现与四个维度!$2:$2&股债表现与四个维度!$3:$3,0))} -> -0.125 | L42: {=INDEX(股债表现与四个维度!$A:$T,MATCH($A42,股债表现与四个维度!$A:$A,0),MATCH(L$3&L$4,股债表现与四个维度!$2:$2&股债表现与四个维度!$3:$3,0))} -> 0 | M42: {=INDEX(股债表现与四个维度!$A:$T,MATCH($A42,股债表现与四个维度!$A:$A,0),MATCH(M$3&M$4,股债表现与四个维度!$2:$2&股债表现与四个维度!$3:$3,0))} -> 0.2972973 | N42: {=INDEX(股债表现与四个维度!$A:$T,MATCH($A42,股债表现与四个维度!$A:$A,0),MATCH(N$3&N$4,股债表现与四个维度!$2:$2&股债表现与四个维度!$3:$3,0))} -> 0.2 | O42: {=INDEX(股债表现与四个维度!$A:$T,MATCH($A42,股债表现与四个维度!$A:$A,0),MATCH(O$3&O$4,股债表现与四个维度!$2:$2&股债表现与四个维度!$3:$3,0))} -> 0.48 | P42: {=INDEX(股债表现与四个维度!$A:$T,MATCH($A42,股债表现与四个维度!$A:$A,0),MATCH(P$3&P$4,股债表现与四个维度!$2:$2&股债表现与四个维度!$3:$3,0))} -> 0.13333333 | Q42: {=INDEX(股债表现与四个维度!$A:$T,MATCH($A42,股债表现与四个维度!$A:$A,0),MATCH(Q$3&Q$4,股债表现与四个维度!$2:$2&股债表现与四个维度!$3:$3,0))} -> 0.4 | ... S42: {=INDEX(股债表现与四个维度!$A:$T,MATCH($A42,股债表现与四个维度!$A:$A,0),MATCH(S$3&S$4,股债表现与四个维度!$2:$2&股债表现与四个维度!$3:$3,0))} -> 1 | T42: =SUMIFS($J42:$S42,$J42:$S42,"<>"&"#N/A",$J$4:$S$4,T$4) -> 0.64583333 | U42: =SUMIFS($J42:$S42,$J42:$S42,"<>"&"#N/A",$J$4:$S$4,U$4) -> 2.0522973 | V42: =T42-U42 -> -1.406464 | W42: =B42+C42 -> 2.7594378 | X42: =B42-D42 -> -2.1221674 | Y42: =AVERAGE(V42:V47) -> -0.64542371 | Z42: =AVERAGE(W42:W47) -> -3.5755116 | AA42: =AVERAGE(X42:X47) -> -1.5095292
A43: 45199 | B43: -1.0902243 | C43: 4.6761522 | D43: -0.14 | E43: 过热 | F43: 宽货币紧信用 | G43: 双宽 | H43: 被动补库存 | I43: 产能周期下行,主动补库存 | J43: {=INDEX(股债表现与四个维度!$A:$T,MATCH($A43,股债表现与四个维度!$A:$A,0),MATCH(J$3&J$4,股债表现与四个维度!$2:$2&股债表现与四个维度!$3:$3,0))} -> 0.4 | K43: {=INDEX(股债表现与四个维度!$A:$T,MATCH($A43,股债表现与四个维度!$A:$A,0),MATCH(K$3&K$4,股债表现与四个维度!$2:$2&股债表现与四个维度!$3:$3,0))} -> -0.2 | L43: {=INDEX(股债表现与四个维度!$A:$T,MATCH($A43,股债表现与四个维度!$A:$A,0),MATCH(L$3&L$4,股债表现与四个维度!$2:$2&股债表现与四个维度!$3:$3,0))} -> 0 | M43: {=INDEX(股债表现与四个维度!$A:$T,MATCH($A43,股债表现与四个维度!$A:$A,0),MATCH(M$3&M$4,股债表现与四个维度!$2:$2&股债表现与四个维度!$3:$3,0))} -> 0.24324324 | N43: {=INDEX(股债表现与四个维度!$A:$T,MATCH($A43,股债表现与四个维度!$A:$A,0),MATCH(N$3&N$4,股债表现与四个维度!$2:$2&股债表现与四个维度!$3:$3,0))} -> 0.2 | O43: {=INDEX(股债表现与四个维度!$A:$T,MATCH($A43,股债表现与四个维度!$A:$A,0),MATCH(O$3&O$4,股债表现与四个维度!$2:$2&股债表现与四个维度!$3:$3,0))} -> 0.4 | P43: {=INDEX(股债表现与四个维度!$A:$T,MATCH($A43,股债表现与四个维度!$A:$A,0),MATCH(P$3&P$4,股债表现与四个维度!$2:$2&股债表现与四个维度!$3:$3,0))} -> 0.21428571 | Q43: {=INDEX(股债表现与四个维度!$A:$T,MATCH($A43,股债表现与四个维度!$A:$A,0),MATCH(Q$3&Q$4,股债表现与四个维度!$2:$2&股债表现与四个维度!$3:$3,0))} -> 0.35714286 | ... S43: {=INDEX(股债表现与四个维度!$A:$T,MATCH($A43,股债表现与四个维度!$A:$A,0),MATCH(S$3&S$4,股债表现与四个维度!$2:$2&股债表现与四个维度!$3:$3,0))} -> 1 | T43: =SUMIFS($J43:$S43,$J43:$S43,"<>"&"#N/A",$J$4:$S$4,T$4) -> 1.8142857 | U43: =SUMIFS($J43:$S43,$J43:$S43,"<>"&"#N/A",$J$4:$S$4,U$4) -> 1.8003861 | V43: =T43-U43 -> 0.013899614 | W43: =B43+C43 -> 3.5859279 | X43: =B43-D43 -> -0.95022431 | Y43: =AVERAGE(V43:V48) -> -0.3905104 | Z43: =AVERAGE(W43:W48) -> -4.9593523 | AA43: =AVERAGE(X43:X48) -> -1.4516096
A44: 45169 | B44: -5.6137095 | C44: -3.8170807 | D44: 0.19 | E44: 过热 | F44: 宽货币紧信用 | G44: 双宽 | H44: 被动补库存 | I44: 产能周期下行,主动补库存 | J44: {=INDEX(股债表现与四个维度!$A:$T,MATCH($A44,股债表现与四个维度!$A:$A,0),MATCH(J$3&J$4,股债表现与四个维度!$2:$2&股债表现与四个维度!$3:$3,0))} -> 0.35714286 | K44: {=INDEX(股债表现与四个维度!$A:$T,MATCH($A44,股债表现与四个维度!$A:$A,0),MATCH(K$3&K$4,股债表现与四个维度!$2:$2&股债表现与四个维度!$3:$3,0))} -> -0.28571429 | L44: {=INDEX(股债表现与四个维度!$A:$T,MATCH($A44,股债表现与四个维度!$A:$A,0),MATCH(L$3&L$4,股债表现与四个维度!$2:$2&股债表现与四个维度!$3:$3,0))} -> -0.027027027 | M44: {=INDEX(股债表现与四个维度!$A:$T,MATCH($A44,股债表现与四个维度!$A:$A,0),MATCH(M$3&M$4,股债表现与四个维度!$2:$2&股债表现与四个维度!$3:$3,0))} -> 0.24324324 | N44: {=INDEX(股债表现与四个维度!$A:$T,MATCH($A44,股债表现与四个维度!$A:$A,0),MATCH(N$3&N$4,股债表现与四个维度!$2:$2&股债表现与四个维度!$3:$3,0))} -> 0.16 | O44: {=INDEX(股债表现与四个维度!$A:$T,MATCH($A44,股债表现与四个维度!$A:$A,0),MATCH(O$3&O$4,股债表现与四个维度!$2:$2&股债表现与四个维度!$3:$3,0))} -> 0.4 | P44: {=INDEX(股债表现与四个维度!$A:$T,MATCH($A44,股债表现与四个维度!$A:$A,0),MATCH(P$3&P$4,股债表现与四个维度!$2:$2&股债表现与四个维度!$3:$3,0))} -> 0.15384615 | Q44: {=INDEX(股债表现与四个维度!$A:$T,MATCH($A44,股债表现与四个维度!$A:$A,0),MATCH(Q$3&Q$4,股债表现与四个维度!$2:$2&股债表现与四个维度!$3:$3,0))} -> 0.30769231 | ... S44: {=INDEX(股债表现与四个维度!$A:$T,MATCH($A44,股债表现与四个维度!$A:$A,0),MATCH(S$3&S$4,股债表现与四个维度!$2:$2&股债表现与四个维度!$3:$3,0))} -> 0.2 | T44: =SUMIFS($J44:$S44,$J44:$S44,"<>"&"#N/A",$J$4:$S$4,T$4) -> 0.44396198 | U44: =SUMIFS($J44:$S44,$J44:$S44,"<>"&"#N/A",$J$4:$S$4,U$4) -> 0.86522127 | V44: =T44-U44 -> -0.42125928 | W44: =B44+C44 -> -9.4307902 | X44: =B44-D44 -> -5.8037095 | Y44: =AVERAGE(V44:V49) -> -0.40977378 | Z44: =AVERAGE(W44:W49) -> -6.0941734 | AA44: =AVERAGE(X44:X49) -> -1.4959166
A45: 45138 | B45: 2.4722746 | C45: -2.9390476 | D45: 0.35 | E45: 过热 | F45: 宽货币紧信用 | G45: 双宽 | H45: 被动补库存 | I45: 产能周期下行,主动补库存 | J45: {=INDEX(股债表现与四个维度!$A:$T,MATCH($A45,股债表现与四个维度!$A:$A,0),MATCH(J$3&J$4,股债表现与四个维度!$2:$2&股债表现与四个维度!$3:$3,0))} -> 0.35714286 | K45: {=INDEX(股债表现与四个维度!$A:$T,MATCH($A45,股债表现与四个维度!$A:$A,0),MATCH(K$3&K$4,股债表现与四个维度!$2:$2&股债表现与四个维度!$3:$3,0))} -> -0.28571429 | L45: {=INDEX(股债表现与四个维度!$A:$T,MATCH($A45,股债表现与四个维度!$A:$A,0),MATCH(L$3&L$4,股债表现与四个维度!$2:$2&股债表现与四个维度!$3:$3,0))} -> -0.081081081 | M45: {=INDEX(股债表现与四个维度!$A:$T,MATCH($A45,股债表现与四个维度!$A:$A,0),MATCH(M$3&M$4,股债表现与四个维度!$2:$2&股债表现与四个维度!$3:$3,0))} -> 0.24324324 | N45: {=INDEX(股债表现与四个维度!$A:$T,MATCH($A45,股债表现与四个维度!$A:$A,0),MATCH(N$3&N$4,股债表现与四个维度!$2:$2&股债表现与四个维度!$3:$3,0))} -> 0.11538462 | O45: {=INDEX(股债表现与四个维度!$A:$T,MATCH($A45,股债表现与四个维度!$A:$A,0),MATCH(O$3&O$4,股债表现与四个维度!$2:$2&股债表现与四个维度!$3:$3,0))} -> 0.42307692 | P45: {=INDEX(股债表现与四个维度!$A:$T,MATCH($A45,股债表现与四个维度!$A:$A,0),MATCH(P$3&P$4,股债表现与四个维度!$2:$2&股债表现与四个维度!$3:$3,0))} -> 0.071428571 | Q45: {=INDEX(股债表现与四个维度!$A:$T,MATCH($A45,股债表现与四个维度!$A:$A,0),MATCH(Q$3&Q$4,股债表现与四个维度!$2:$2&股债表现与四个维度!$3:$3,0))} -> 0.35714286 | ... S45: {=INDEX(股债表现与四个维度!$A:$T,MATCH($A45,股债表现与四个维度!$A:$A,0),MATCH(S$3&S$4,股债表现与四个维度!$2:$2&股债表现与四个维度!$3:$3,0))} -> 0.2 | T45: =SUMIFS($J45:$S45,$J45:$S45,"<>"&"#N/A",$J$4:$S$4,T$4) -> 0.26287496 | U45: =SUMIFS($J45:$S45,$J45:$S45,"<>"&"#N/A",$J$4:$S$4,U$4) -> 0.93774874 | V45: =T45-U45 -> -0.67487377 | W45: =B45+C45 -> -0.46677305 | X45: =B45-D45 -> 2.1222746 | Y45: =AVERAGE(V45:V50) -> -0.44441918 | Z45: =AVERAGE(W45:W50) -> -3.6917902 | AA45: =AVERAGE(X45:X50) -> 0.047752316
A46: 45107 | B46: 1.5787272 | C46: -5.0428571 | D46: 0.31 | E46: 复苏 | F46: 宽货币紧信用 | G46: 宽货币紧财政 | H46: 主动去库存 | I46: 产能周期下行,被动去库存 | J46: {=INDEX(股债表现与四个维度!$A:$T,MATCH($A46,股债表现与四个维度!$A:$A,0),MATCH(J$3&J$4,股债表现与四个维度!$2:$2&股债表现与四个维度!$3:$3,0))} -> -0.0625 | K46: {=INDEX(股债表现与四个维度!$A:$T,MATCH($A46,股债表现与四个维度!$A:$A,0),MATCH(K$3&K$4,股债表现与四个维度!$2:$2&股债表现与四个维度!$3:$3,0))} -> 0.25 | L46: {=INDEX(股债表现与四个维度!$A:$T,MATCH($A46,股债表现与四个维度!$A:$A,0),MATCH(L$3&L$4,股债表现与四个维度!$2:$2&股债表现与四个维度!$3:$3,0))} -> -0.054054054 | M46: {=INDEX(股债表现与四个维度!$A:$T,MATCH($A46,股债表现与四个维度!$A:$A,0),MATCH(M$3&M$4,股债表现与四个维度!$2:$2&股债表现与四个维度!$3:$3,0))} -> 0.21621622 | N46: {=INDEX(股债表现与四个维度!$A:$T,MATCH($A46,股债表现与四个维度!$A:$A,0),MATCH(N$3&N$4,股债表现与四个维度!$2:$2&股债表现与四个维度!$3:$3,0))} -> 0.05 | O46: {=INDEX(股债表现与四个维度!$A:$T,MATCH($A46,股债表现与四个维度!$A:$A,0),MATCH(O$3&O$4,股债表现与四个维度!$2:$2&股债表现与四个维度!$3:$3,0))} -> 0.25 | P46: {=INDEX(股债表现与四个维度!$A:$T,MATCH($A46,股债表现与四个维度!$A:$A,0),MATCH(P$3&P$4,股债表现与四个维度!$2:$2&股债表现与四个维度!$3:$3,0))} -> 0.18181818 | Q46: {=INDEX(股债表现与四个维度!$A:$T,MATCH($A46,股债表现与四个维度!$A:$A,0),MATCH(Q$3&Q$4,股债表现与四个维度!$2:$2&股债表现与四个维度!$3:$3,0))} -> 0.045454545 | ... S46: {=INDEX(股债表现与四个维度!$A:$T,MATCH($A46,股债表现与四个维度!$A:$A,0),MATCH(S$3&S$4,股债表现与四个维度!$2:$2&股债表现与四个维度!$3:$3,0))} -> 0.2 | T46: =SUMIFS($J46:$S46,$J46:$S46,"<>"&"#N/A",$J$4:$S$4,T$4) -> -0.084735872 | U46: =SUMIFS($J46:$S46,$J46:$S46,"<>"&"#N/A",$J$4:$S$4,U$4) -> 0.96167076 | V46: =T46-U46 -> -1.0464066 | W46: =B46+C46 -> -3.46413 | X46: =B46-D46 -> 1.2687272 | Y46: =AVERAGE(V46:V51) -> -0.58278608 | Z46: =AVERAGE(W46:W51) -> -2.4406587 | AA46: =AVERAGE(X46:X51) -> -0.62850689
A47: 45077 | B47: -3.3120755 | C47: -11.124667 | D47: 0.26 | E47: 复苏 | F47: 宽货币紧信用 | G47: 宽货币紧财政 | H47: 主动去库存 | I47: 产能周期下行,被动去库存 | J47: {=INDEX(股债表现与四个维度!$A:$T,MATCH($A47,股债表现与四个维度!$A:$A,0),MATCH(J$3&J$4,股债表现与四个维度!$2:$2&股债表现与四个维度!$3:$3,0))} -> 0 | K47: {=INDEX(股债表现与四个维度!$A:$T,MATCH($A47,股债表现与四个维度!$A:$A,0),MATCH(K$3&K$4,股债表现与四个维度!$2:$2&股债表现与四个维度!$3:$3,0))} -> 0.2 | L47: {=INDEX(股债表现与四个维度!$A:$T,MATCH($A47,股债表现与四个维度!$A:$A,0),MATCH(L$3&L$4,股债表现与四个维度!$2:$2&股债表现与四个维度!$3:$3,0))} -> -0.054054054 | M47: {=INDEX(股债表现与四个维度!$A:$T,MATCH($A47,股债表现与四个维度!$A:$A,0),MATCH(M$3&M$4,股债表现与四个维度!$2:$2&股债表现与四个维度!$3:$3,0))} -> 0.21621622 | N47: {=INDEX(股债表现与四个维度!$A:$T,MATCH($A47,股债表现与四个维度!$A:$A,0),MATCH(N$3&N$4,股债表现与四个维度!$2:$2&股债表现与四个维度!$3:$3,0))} -> 0.10526316 | O47: {=INDEX(股债表现与四个维度!$A:$T,MATCH($A47,股债表现与四个维度!$A:$A,0),MATCH(O$3&O$4,股债表现与四个维度!$2:$2&股债表现与四个维度!$3:$3,0))} -> 0.21052632 | P47: {=INDEX(股债表现与四个维度!$A:$T,MATCH($A47,股债表现与四个维度!$A:$A,0),MATCH(P$3&P$4,股债表现与四个维度!$2:$2&股债表现与四个维度!$3:$3,0))} -> 0.23809524 | Q47: {=INDEX(股债表现与四个维度!$A:$T,MATCH($A47,股债表现与四个维度!$A:$A,0),MATCH(Q$3&Q$4,股债表现与四个维度!$2:$2&股债表现与四个维度!$3:$3,0))} -> 0 | ... S47: {=INDEX(股债表现与四个维度!$A:$T,MATCH($A47,股债表现与四个维度!$A:$A,0),MATCH(S$3&S$4,股债表现与四个维度!$2:$2&股债表现与四个维度!$3:$3,0))} -> 0 | T47: =SUMIFS($J47:$S47,$J47:$S47,"<>"&"#N/A",$J$4:$S$4,T$4) -> 0.28930434 | U47: =SUMIFS($J47:$S47,$J47:$S47,"<>"&"#N/A",$J$4:$S$4,U$4) -> 0.62674253 | V47: =T47-U47 -> -0.33743819 | W47: =B47+C47 -> -14.436742 | X47: =B47-D47 -> -3.5720755 | Y47: =AVERAGE(V47:V52) -> -0.66536142 | Z47: =AVERAGE(W47:W52) -> 0.46714585 | AA47: =AVERAGE(X47:X52) -> 0.53977266
... A71: 44286 | B71: -3.1374839 | C71: 4.0085332 | D71: 0.3 | E71: 滞涨 | F71: 宽货币紧信用 | G71: 宽货币紧财政 | H71: 主动去库存 | I71: 产能周期上行,被动补库存 | J71: {=INDEX(股债表现与四个维度!$A:$T,MATCH($A71,股债表现与四个维度!$A:$A,0),MATCH(J$3&J$4,股债表现与四个维度!$2:$2&股债表现与四个维度!$3:$3,0))} -> -0.75 | K71: {=INDEX(股债表现与四个维度!$A:$T,MATCH($A71,股债表现与四个维度!$A:$A,0),MATCH(K$3&K$4,股债表现与四个维度!$2:$2&股债表现与四个维度!$3:$3,0))} -> 0.25 | L71: {=INDEX(股债表现与四个维度!$A:$T,MATCH($A71,股债表现与四个维度!$A:$A,0),MATCH(L$3&L$4,股债表现与四个维度!$2:$2&股债表现与四个维度!$3:$3,0))} -> -0.25 | M71: {=INDEX(股债表现与四个维度!$A:$T,MATCH($A71,股债表现与四个维度!$A:$A,0),MATCH(M$3&M$4,股债表现与四个维度!$2:$2&股债表现与四个维度!$3:$3,0))} -> 0.33333333 | N71: {=INDEX(股债表现与四个维度!$A:$T,MATCH($A71,股债表现与四个维度!$A:$A,0),MATCH(N$3&N$4,股债表现与四个维度!$2:$2&股债表现与四个维度!$3:$3,0))} -> 0 | O71: {=INDEX(股债表现与四个维度!$A:$T,MATCH($A71,股债表现与四个维度!$A:$A,0),MATCH(O$3&O$4,股债表现与四个维度!$2:$2&股债表现与四个维度!$3:$3,0))} -> 0 | P71: {=INDEX(股债表现与四个维度!$A:$T,MATCH($A71,股债表现与四个维度!$A:$A,0),MATCH(P$3&P$4,股债表现与四个维度!$2:$2&股债表现与四个维度!$3:$3,0))} -> 0.23684211 | Q71: {=INDEX(股债表现与四个维度!$A:$T,MATCH($A71,股债表现与四个维度!$A:$A,0),MATCH(Q$3&Q$4,股债表现与四个维度!$2:$2&股债表现与四个维度!$3:$3,0))} -> -0.15789474 | ... S71: {=INDEX(股债表现与四个维度!$A:$T,MATCH($A71,股债表现与四个维度!$A:$A,0),MATCH(S$3&S$4,股债表现与四个维度!$2:$2&股债表现与四个维度!$3:$3,0))} -> 0.75 | T71: =SUMIFS($J71:$S71,$J71:$S71,"<>"&"#N/A",$J$4:$S$4,T$4) -> -0.76315789 | U71: =SUMIFS($J71:$S71,$J71:$S71,"<>"&"#N/A",$J$4:$S$4,U$4) -> 1.1754386 | V71: =T71-U71 -> -1.9385965 | W71: =B71+C71 -> 0.87104932 | X71: =B71-D71 -> -3.4374839 | Y71: =AVERAGE(V71:V76) -> 0.58548932 | Z71: =AVERAGE(W71:W76) -> 4.375038 | AA71: =AVERAGE(X71:X76) -> -0.42279526
A72: 44255 | B72: -0.055625054 | C72: -2.4138318 | D72: 0.18 | E72: 过热 | F72: 宽货币紧信用 | G72: 宽货币紧财政 | H72: 主动去库存 | I72: 产能周期上行,主动补库存 | J72: {=INDEX(股债表现与四个维度!$A:$T,MATCH($A72,股债表现与四个维度!$A:$A,0),MATCH(J$3&J$4,股债表现与四个维度!$2:$2&股债表现与四个维度!$3:$3,0))} -> 0.33333333 | K72: {=INDEX(股债表现与四个维度!$A:$T,MATCH($A72,股债表现与四个维度!$A:$A,0),MATCH(K$3&K$4,股债表现与四个维度!$2:$2&股债表现与四个维度!$3:$3,0))} -> -0.25 | L72: {=INDEX(股债表现与四个维度!$A:$T,MATCH($A72,股债表现与四个维度!$A:$A,0),MATCH(L$3&L$4,股债表现与四个维度!$2:$2&股债表现与四个维度!$3:$3,0))} -> -0.27272727 | M72: {=INDEX(股债表现与四个维度!$A:$T,MATCH($A72,股债表现与四个维度!$A:$A,0),MATCH(M$3&M$4,股债表现与四个维度!$2:$2&股债表现与四个维度!$3:$3,0))} -> 0.27272727 | P72: {=INDEX(股债表现与四个维度!$A:$T,MATCH($A72,股债表现与四个维度!$A:$A,0),MATCH(P$3&P$4,股债表现与四个维度!$2:$2&股债表现与四个维度!$3:$3,0))} -> 0.21052632 | Q72: {=INDEX(股债表现与四个维度!$A:$T,MATCH($A72,股债表现与四个维度!$A:$A,0),MATCH(Q$3&Q$4,股债表现与四个维度!$2:$2&股债表现与四个维度!$3:$3,0))} -> -0.15789474 | R72: {=INDEX(股债表现与四个维度!$A:$T,MATCH($A72,股债表现与四个维度!$A:$A,0),MATCH(R$3&R$4,股债表现与四个维度!$2:$2&股债表现与四个维度!$3:$3,0))} -> 0.33333333 | S72: {=INDEX(股债表现与四个维度!$A:$T,MATCH($A72,股债表现与四个维度!$A:$A,0),MATCH(S$3&S$4,股债表现与四个维度!$2:$2&股债表现与四个维度!$3:$3,0))} -> -0.33333333 | T72: =SUMIFS($J72:$S72,$J72:$S72,"<>"&"#N/A",$J$4:$S$4,T$4) -> 0.60446571 | U72: =SUMIFS($J72:$S72,$J72:$S72,"<>"&"#N/A",$J$4:$S$4,U$4) -> -0.4685008 | V72: =T72-U72 -> 1.0729665 | W72: =B72+C72 -> -2.4694569 | X72: =B72-D72 -> -0.23562505 | Y72: =AVERAGE(V72:V77) -> 0.99577893 | Z72: =AVERAGE(W72:W77) -> 5.1721961 | AA72: =AVERAGE(X72:X77) -> 0.46653043
A73: 44196 | B73: 3.1099019 | C73: -1.2153209 | D73: 0.74 | E73: 过热 | F73: 宽货币紧信用 | G73: 宽货币紧财政 | H73: 主动去库存 | I73: 产能周期上行,主动补库存 | J73: {=INDEX(股债表现与四个维度!$A:$T,MATCH($A73,股债表现与四个维度!$A:$A,0),MATCH(J$3&J$4,股债表现与四个维度!$2:$2&股债表现与四个维度!$3:$3,0))} -> 0.27272727 | K73: {=INDEX(股债表现与四个维度!$A:$T,MATCH($A73,股债表现与四个维度!$A:$A,0),MATCH(K$3&K$4,股债表现与四个维度!$2:$2&股债表现与四个维度!$3:$3,0))} -> -0.22727273 | L73: {=INDEX(股债表现与四个维度!$A:$T,MATCH($A73,股债表现与四个维度!$A:$A,0),MATCH(L$3&L$4,股债表现与四个维度!$2:$2&股债表现与四个维度!$3:$3,0))} -> -0.4 | M73: {=INDEX(股债表现与四个维度!$A:$T,MATCH($A73,股债表现与四个维度!$A:$A,0),MATCH(M$3&M$4,股债表现与四个维度!$2:$2&股债表现与四个维度!$3:$3,0))} -> 0.3 | P73: {=INDEX(股债表现与四个维度!$A:$T,MATCH($A73,股债表现与四个维度!$A:$A,0),MATCH(P$3&P$4,股债表现与四个维度!$2:$2&股债表现与四个维度!$3:$3,0))} -> 0.21052632 | Q73: {=INDEX(股债表现与四个维度!$A:$T,MATCH($A73,股债表现与四个维度!$A:$A,0),MATCH(Q$3&Q$4,股债表现与四个维度!$2:$2&股债表现与四个维度!$3:$3,0))} -> -0.13157895 | R73: {=INDEX(股债表现与四个维度!$A:$T,MATCH($A73,股债表现与四个维度!$A:$A,0),MATCH(R$3&R$4,股债表现与四个维度!$2:$2&股债表现与四个维度!$3:$3,0))} -> 0.26315789 | S73: {=INDEX(股债表现与四个维度!$A:$T,MATCH($A73,股债表现与四个维度!$A:$A,0),MATCH(S$3&S$4,股债表现与四个维度!$2:$2&股债表现与四个维度!$3:$3,0))} -> -0.31578947 | T73: =SUMIFS($J73:$S73,$J73:$S73,"<>"&"#N/A",$J$4:$S$4,T$4) -> 0.34641148 | U73: =SUMIFS($J73:$S73,$J73:$S73,"<>"&"#N/A",$J$4:$S$4,U$4) -> -0.37464115 | V73: =T73-U73 -> 0.72105263 | W73: =B73+C73 -> 1.894581 | X73: =B73-D73 -> 2.3699019 | Y73: =AVERAGE(V73:V78) -> 0.8490013 | Z73: =AVERAGE(W73:W78) -> 9.7990633 | AA73: =AVERAGE(X73:X78) -> 2.6647913
A74: 44165 | B74: 3.9826317 | C74: 6.2397199 | D74: -0.05 | E74: 过热 | F74: 宽货币宽信用 | G74: 宽货币紧财政 | H74: 主动去库存 | I74: 产能周期上行,主动补库存 | J74: {=INDEX(股债表现与四个维度!$A:$T,MATCH($A74,股债表现与四个维度!$A:$A,0),MATCH(J$3&J$4,股债表现与四个维度!$2:$2&股债表现与四个维度!$3:$3,0))} -> 0.23809524 | K74: {=INDEX(股债表现与四个维度!$A:$T,MATCH($A74,股债表现与四个维度!$A:$A,0),MATCH(K$3&K$4,股债表现与四个维度!$2:$2&股债表现与四个维度!$3:$3,0))} -> -0.19047619 | L74: {=INDEX(股债表现与四个维度!$A:$T,MATCH($A74,股债表现与四个维度!$A:$A,0),MATCH(L$3&L$4,股债表现与四个维度!$2:$2&股债表现与四个维度!$3:$3,0))} -> 0.22857143 | M74: {=INDEX(股债表现与四个维度!$A:$T,MATCH($A74,股债表现与四个维度!$A:$A,0),MATCH(M$3&M$4,股债表现与四个维度!$2:$2&股债表现与四个维度!$3:$3,0))} -> 0.057142857 | P74: {=INDEX(股债表现与四个维度!$A:$T,MATCH($A74,股债表现与四个维度!$A:$A,0),MATCH(P$3&P$4,股债表现与四个维度!$2:$2&股债表现与四个维度!$3:$3,0))} -> 0.21052632 | Q74: {=INDEX(股债表现与四个维度!$A:$T,MATCH($A74,股债表现与四个维度!$A:$A,0),MATCH(Q$3&Q$4,股债表现与四个维度!$2:$2&股债表现与四个维度!$3:$3,0))} -> -0.078947368 | R74: {=INDEX(股债表现与四个维度!$A:$T,MATCH($A74,股债表现与四个维度!$A:$A,0),MATCH(R$3&R$4,股债表现与四个维度!$2:$2&股债表现与四个维度!$3:$3,0))} -> 0.22222222 | S74: {=INDEX(股债表现与四个维度!$A:$T,MATCH($A74,股债表现与四个维度!$A:$A,0),MATCH(S$3&S$4,股债表现与四个维度!$2:$2&股债表现与四个维度!$3:$3,0))} -> -0.27777778 | T74: =SUMIFS($J74:$S74,$J74:$S74,"<>"&"#N/A",$J$4:$S$4,T$4) -> 0.8994152 | U74: =SUMIFS($J74:$S74,$J74:$S74,"<>"&"#N/A",$J$4:$S$4,U$4) -> -0.49005848 | V74: =T74-U74 -> 1.3894737 | W74: =B74+C74 -> 10.222352 | X74: =B74-D74 -> 4.0326317 | Y74: =AVERAGE(V74:V79) -> 0.74506042 | Z74: =AVERAGE(W74:W79) -> 13.317511 | AA74: =AVERAGE(X74:X79) -> 3.7511279
A75: 44135 | B75: 1.0531091 | C75: 7.995601 | D75: 0.34 | E75: 过热 | F75: 宽货币宽信用 | G75: 双紧 | H75: 主动去库存 | I75: 产能周期上行,主动补库存 | J75: {=INDEX(股债表现与四个维度!$A:$T,MATCH($A75,股债表现与四个维度!$A:$A,0),MATCH(J$3&J$4,股债表现与四个维度!$2:$2&股债表现与四个维度!$3:$3,0))} -> 0.3 | K75: {=INDEX(股债表现与四个维度!$A:$T,MATCH($A75,股债表现与四个维度!$A:$A,0),MATCH(K$3&K$4,股债表现与四个维度!$2:$2&股债表现与四个维度!$3:$3,0))} -> -0.15 | L75: {=INDEX(股债表现与四个维度!$A:$T,MATCH($A75,股债表现与四个维度!$A:$A,0),MATCH(L$3&L$4,股债表现与四个维度!$2:$2&股债表现与四个维度!$3:$3,0))} -> 0.22857143 | M75: {=INDEX(股债表现与四个维度!$A:$T,MATCH($A75,股债表现与四个维度!$A:$A,0),MATCH(M$3&M$4,股债表现与四个维度!$2:$2&股债表现与四个维度!$3:$3,0))} -> 0.11428571 | P75: {=INDEX(股债表现与四个维度!$A:$T,MATCH($A75,股债表现与四个维度!$A:$A,0),MATCH(P$3&P$4,股债表现与四个维度!$2:$2&股债表现与四个维度!$3:$3,0))} -> 0.21052632 | Q75: {=INDEX(股债表现与四个维度!$A:$T,MATCH($A75,股债表现与四个维度!$A:$A,0),MATCH(Q$3&Q$4,股债表现与四个维度!$2:$2&股债表现与四个维度!$3:$3,0))} -> -0.026315789 | R75: {=INDEX(股债表现与四个维度!$A:$T,MATCH($A75,股债表现与四个维度!$A:$A,0),MATCH(R$3&R$4,股债表现与四个维度!$2:$2&股债表现与四个维度!$3:$3,0))} -> 0.29411765 | S75: {=INDEX(股债表现与四个维度!$A:$T,MATCH($A75,股债表现与四个维度!$A:$A,0),MATCH(S$3&S$4,股债表现与四个维度!$2:$2&股债表现与四个维度!$3:$3,0))} -> -0.23529412 | T75: =SUMIFS($J75:$S75,$J75:$S75,"<>"&"#N/A",$J$4:$S$4,T$4) -> 1.0332154 | U75: =SUMIFS($J75:$S75,$J75:$S75,"<>"&"#N/A",$J$4:$S$4,U$4) -> -0.29732419 | V75: =T75-U75 -> 1.3305396 | W75: =B75+C75 -> 9.0487101 | X75: =B75-D75 -> 0.71310912 | Y75: =AVERAGE(V75:V80) -> 0.54955651 | Z75: =AVERAGE(W75:W80) -> 14.022071 | AA75: =AVERAGE(X75:X80) -> 3.2890225
A76: 44104 | B76: -5.9693053 | C76: 12.652298 | D76: 0.01 | E76: 过热 | F76: 宽货币宽信用 | G76: 双紧 | H76: 主动去库存 | I76: 产能周期上行,主动补库存 | J76: {=INDEX(股债表现与四个维度!$A:$T,MATCH($A76,股债表现与四个维度!$A:$A,0),MATCH(J$3&J$4,股债表现与四个维度!$2:$2&股债表现与四个维度!$3:$3,0))} -> 0.26315789 | K76: {=INDEX(股债表现与四个维度!$A:$T,MATCH($A76,股债表现与四个维度!$A:$A,0),MATCH(K$3&K$4,股债表现与四个维度!$2:$2&股债表现与四个维度!$3:$3,0))} -> -0.10526316 | L76: {=INDEX(股债表现与四个维度!$A:$T,MATCH($A76,股债表现与四个维度!$A:$A,0),MATCH(L$3&L$4,股债表现与四个维度!$2:$2&股债表现与四个维度!$3:$3,0))} -> 0.17142857 | M76: {=INDEX(股债表现与四个维度!$A:$T,MATCH($A76,股债表现与四个维度!$A:$A,0),MATCH(M$3&M$4,股债表现与四个维度!$2:$2&股债表现与四个维度!$3:$3,0))} -> 0.17142857 | P76: {=INDEX(股债表现与四个维度!$A:$T,MATCH($A76,股债表现与四个维度!$A:$A,0),MATCH(P$3&P$4,股债表现与四个维度!$2:$2&股债表现与四个维度!$3:$3,0))} -> 0.15789474 | Q76: {=INDEX(股债表现与四个维度!$A:$T,MATCH($A76,股债表现与四个维度!$A:$A,0),MATCH(Q$3&Q$4,股债表现与四个维度!$2:$2&股债表现与四个维度!$3:$3,0))} -> 0.026315789 | R76: {=INDEX(股债表现与四个维度!$A:$T,MATCH($A76,股债表现与四个维度!$A:$A,0),MATCH(R$3&R$4,股债表现与四个维度!$2:$2&股债表现与四个维度!$3:$3,0))} -> 0.25 | S76: {=INDEX(股债表现与四个维度!$A:$T,MATCH($A76,股债表现与四个维度!$A:$A,0),MATCH(S$3&S$4,股债表现与四个维度!$2:$2&股债表现与四个维度!$3:$3,0))} -> -0.1875 | T76: =SUMIFS($J76:$S76,$J76:$S76,"<>"&"#N/A",$J$4:$S$4,T$4) -> 0.8424812 | U76: =SUMIFS($J76:$S76,$J76:$S76,"<>"&"#N/A",$J$4:$S$4,U$4) -> -0.095018797 | V76: =T76-U76 -> 0.9375 | W76: =B76+C76 -> 6.6829928 | X76: =B76-D76 -> -5.9793053 | Y76: =AVERAGE(V76:V81) -> 0.48898768 | Z76: =AVERAGE(W76:W81) -> 11.560079 | AA76: =AVERAGE(X76:X81) -> 3.8072069
A77: 44074 | B77: 1.9684702 | C77: 3.685528 | D77: 0.07 | E77: 过热 | F77: 宽货币宽信用 | G77: 双紧 | H77: 主动去库存 | I77: 产能周期上行,主动补库存 | J77: {=INDEX(股债表现与四个维度!$A:$T,MATCH($A77,股债表现与四个维度!$A:$A,0),MATCH(J$3&J$4,股债表现与四个维度!$2:$2&股债表现与四个维度!$3:$3,0))} -> 0.22222222 | K77: {=INDEX(股债表现与四个维度!$A:$T,MATCH($A77,股债表现与四个维度!$A:$A,0),MATCH(K$3&K$4,股债表现与四个维度!$2:$2&股债表现与四个维度!$3:$3,0))} -> -0.055555556 | L77: {=INDEX(股债表现与四个维度!$A:$T,MATCH($A77,股债表现与四个维度!$A:$A,0),MATCH(L$3&L$4,股债表现与四个维度!$2:$2&股债表现与四个维度!$3:$3,0))} -> 0.11428571 | M77: {=INDEX(股债表现与四个维度!$A:$T,MATCH($A77,股债表现与四个维度!$A:$A,0),MATCH(M$3&M$4,股债表现与四个维度!$2:$2&股债表现与四个维度!$3:$3,0))} -> 0.22857143 | P77: {=INDEX(股债表现与四个维度!$A:$T,MATCH($A77,股债表现与四个维度!$A:$A,0),MATCH(P$3&P$4,股债表现与四个维度!$2:$2&股债表现与四个维度!$3:$3,0))} -> 0.10526316 | Q77: {=INDEX(股债表现与四个维度!$A:$T,MATCH($A77,股债表现与四个维度!$A:$A,0),MATCH(Q$3&Q$4,股债表现与四个维度!$2:$2&股债表现与四个维度!$3:$3,0))} -> 0.078947368 | R77: {=INDEX(股债表现与四个维度!$A:$T,MATCH($A77,股债表现与四个维度!$A:$A,0),MATCH(R$3&R$4,股债表现与四个维度!$2:$2&股债表现与四个维度!$3:$3,0))} -> 0.2 | S77: {=INDEX(股债表现与四个维度!$A:$T,MATCH($A77,股债表现与四个维度!$A:$A,0),MATCH(S$3&S$4,股债表现与四个维度!$2:$2&股债表现与四个维度!$3:$3,0))} -> -0.13333333 | T77: =SUMIFS($J77:$S77,$J77:$S77,"<>"&"#N/A",$J$4:$S$4,T$4) -> 0.64177109 | U77: =SUMIFS($J77:$S77,$J77:$S77,"<>"&"#N/A",$J$4:$S$4,U$4) -> 0.11862991 | V77: =T77-U77 -> 0.52314119 | W77: =B77+C77 -> 5.6539982 | X77: =B77-D77 -> 1.8984702 | Y77: =AVERAGE(V77:V82) -> 0.49608079 | Z77: =AVERAGE(W77:W82) -> 4.2042653 | AA77: =AVERAGE(X77:X82) -> 3.6487117
A78: 44043 | B78: 13.06394 | C78: 12.227805 | D78: 0.11 | E78: 过热 | F78: 宽货币宽信用 | G78: 双紧 | H78: 主动去库存 | I78: 产能周期上行,主动补库存 | J78: {=INDEX(股债表现与四个维度!$A:$T,MATCH($A78,股债表现与四个维度!$A:$A,0),MATCH(J$3&J$4,股债表现与四个维度!$2:$2&股债表现与四个维度!$3:$3,0))} -> 0.17647059 | K78: {=INDEX(股债表现与四个维度!$A:$T,MATCH($A78,股债表现与四个维度!$A:$A,0),MATCH(K$3&K$4,股债表现与四个维度!$2:$2&股债表现与四个维度!$3:$3,0))} -> 0 | L78: {=INDEX(股债表现与四个维度!$A:$T,MATCH($A78,股债表现与四个维度!$A:$A,0),MATCH(L$3&L$4,股债表现与四个维度!$2:$2&股债表现与四个维度!$3:$3,0))} -> 0.057142857 | M78: {=INDEX(股债表现与四个维度!$A:$T,MATCH($A78,股债表现与四个维度!$A:$A,0),MATCH(M$3&M$4,股债表现与四个维度!$2:$2&股债表现与四个维度!$3:$3,0))} -> 0.22857143 | P78: {=INDEX(股债表现与四个维度!$A:$T,MATCH($A78,股债表现与四个维度!$A:$A,0),MATCH(P$3&P$4,股债表现与四个维度!$2:$2&股债表现与四个维度!$3:$3,0))} -> 0.081081081 | Q78: {=INDEX(股债表现与四个维度!$A:$T,MATCH($A78,股债表现与四个维度!$A:$A,0),MATCH(Q$3&Q$4,股债表现与四个维度!$2:$2&股债表现与四个维度!$3:$3,0))} -> 0.10810811 | R78: {=INDEX(股债表现与四个维度!$A:$T,MATCH($A78,股债表现与四个维度!$A:$A,0),MATCH(R$3&R$4,股债表现与四个维度!$2:$2&股债表现与四个维度!$3:$3,0))} -> 0.14285714 | S78: {=INDEX(股债表现与四个维度!$A:$T,MATCH($A78,股债表现与四个维度!$A:$A,0),MATCH(S$3&S$4,股债表现与四个维度!$2:$2&股债表现与四个维度!$3:$3,0))} -> -0.071428571 | T78: =SUMIFS($J78:$S78,$J78:$S78,"<>"&"#N/A",$J$4:$S$4,T$4) -> 0.45755167 | U78: =SUMIFS($J78:$S78,$J78:$S78,"<>"&"#N/A",$J$4:$S$4,U$4) -> 0.26525097 | V78: =T78-U78 -> 0.1923007 | W78: =B78+C78 -> 25.291746 | X78: =B78-D78 -> 12.95394 | Y78: =AVERAGE(V78:V83) -> 0.36920805 | Z78: =AVERAGE(W78:W83) -> 1.4823971 | AA78: =AVERAGE(X78:X83) -> 3.1456228
A79: 44012 | B79: 8.4079215 | C79: 14.597343 | D79: -0.48 | E79: 过热 | F79: 宽货币宽信用 | G79: 双紧 | H79: 主动去库存 | I79: 产能周期上行,主动补库存 | J79: {=INDEX(股债表现与四个维度!$A:$T,MATCH($A79,股债表现与四个维度!$A:$A,0),MATCH(J$3&J$4,股债表现与四个维度!$2:$2&股债表现与四个维度!$3:$3,0))} -> 0.17647059 | K79: {=INDEX(股债表现与四个维度!$A:$T,MATCH($A79,股债表现与四个维度!$A:$A,0),MATCH(K$3&K$4,股债表现与四个维度!$2:$2&股债表现与四个维度!$3:$3,0))} -> 0 | L79: {=INDEX(股债表现与四个维度!$A:$T,MATCH($A79,股债表现与四个维度!$A:$A,0),MATCH(L$3&L$4,股债表现与四个维度!$2:$2&股债表现与四个维度!$3:$3,0))} -> 0.058823529 | M79: {=INDEX(股债表现与四个维度!$A:$T,MATCH($A79,股债表现与四个维度!$A:$A,0),MATCH(M$3&M$4,股债表现与四个维度!$2:$2&股债表现与四个维度!$3:$3,0))} -> 0.26470588 | P79: {=INDEX(股债表现与四个维度!$A:$T,MATCH($A79,股债表现与四个维度!$A:$A,0),MATCH(P$3&P$4,股债表现与四个维度!$2:$2&股债表现与四个维度!$3:$3,0))} -> 0.081081081 | Q79: {=INDEX(股债表现与四个维度!$A:$T,MATCH($A79,股债表现与四个维度!$A:$A,0),MATCH(Q$3&Q$4,股债表现与四个维度!$2:$2&股债表现与四个维度!$3:$3,0))} -> 0.10810811 | R79: {=INDEX(股债表现与四个维度!$A:$T,MATCH($A79,股债表现与四个维度!$A:$A,0),MATCH(R$3&R$4,股债表现与四个维度!$2:$2&股债表现与四个维度!$3:$3,0))} -> 0.15384615 | S79: {=INDEX(股债表现与四个维度!$A:$T,MATCH($A79,股债表现与四个维度!$A:$A,0),MATCH(S$3&S$4,股债表现与四个维度!$2:$2&股债表现与四个维度!$3:$3,0))} -> 0 | T79: =SUMIFS($J79:$S79,$J79:$S79,"<>"&"#N/A",$J$4:$S$4,T$4) -> 0.47022135 | U79: =SUMIFS($J79:$S79,$J79:$S79,"<>"&"#N/A",$J$4:$S$4,U$4) -> 0.37281399 | V79: =T79-U79 -> 0.097407362 | W79: =B79+C79 -> 23.005265 | X79: =B79-D79 -> 8.8879215 | Y79: =AVERAGE(V79:V84) -> 0.35672171 | Z79: =AVERAGE(W79:W84) -> -2.2660858 | AA79: =AVERAGE(X79:X84) -> 2.1660563
A80: 43982 | B80: 0.57999903 | C80: 13.869713 | D80: -0.68 | E80: 复苏 | F80: 宽货币宽信用 | G80: 双紧 | H80: 主动补库存 | I80: 产能周期上行,主动补库存 | J80: {=INDEX(股债表现与四个维度!$A:$T,MATCH($A80,股债表现与四个维度!$A:$A,0),MATCH(J$3&J$4,股债表现与四个维度!$2:$2&股债表现与四个维度!$3:$3,0))} -> 0.083333333 | K80: {=INDEX(股债表现与四个维度!$A:$T,MATCH($A80,股债表现与四个维度!$A:$A,0),MATCH(K$3&K$4,股债表现与四个维度!$2:$2&股债表现与四个维度!$3:$3,0))} -> -0.25 | L80: {=INDEX(股债表现与四个维度!$A:$T,MATCH($A80,股债表现与四个维度!$A:$A,0),MATCH(L$3&L$4,股债表现与四个维度!$2:$2&股债表现与四个维度!$3:$3,0))} -> 0.03030303 | M80: {=INDEX(股债表现与四个维度!$A:$T,MATCH($A80,股债表现与四个维度!$A:$A,0),MATCH(M$3&M$4,股债表现与四个维度!$2:$2&股债表现与四个维度!$3:$3,0))} -> 0.24242424 | P80: {=INDEX(股债表现与四个维度!$A:$T,MATCH($A80,股债表现与四个维度!$A:$A,0),MATCH(P$3&P$4,股债表现与四个维度!$2:$2&股债表现与四个维度!$3:$3,0))} -> 0.071428571 | Q80: {=INDEX(股债表现与四个维度!$A:$T,MATCH($A80,股债表现与四个维度!$A:$A,0),MATCH(Q$3&Q$4,股债表现与四个维度!$2:$2&股债表现与四个维度!$3:$3,0))} -> 0.14285714 | R80: {=INDEX(股债表现与四个维度!$A:$T,MATCH($A80,股债表现与四个维度!$A:$A,0),MATCH(R$3&R$4,股债表现与四个维度!$2:$2&股债表现与四个维度!$3:$3,0))} -> 0.083333333 | S80: {=INDEX(股债表现与四个维度!$A:$T,MATCH($A80,股债表现与四个维度!$A:$A,0),MATCH(S$3&S$4,股债表现与四个维度!$2:$2&股债表现与四个维度!$3:$3,0))} -> -0.083333333 | T80: =SUMIFS($J80:$S80,$J80:$S80,"<>"&"#N/A",$J$4:$S$4,T$4) -> 0.26839827 | U80: =SUMIFS($J80:$S80,$J80:$S80,"<>"&"#N/A",$J$4:$S$4,U$4) -> 0.051948052 | V80: =T80-U80 -> 0.21645022 | W80: =B80+C80 -> 14.449712 | X80: =B80-D80 -> 1.259999 | Y80: =AVERAGE(V80:V85) -> 0.34854448 | Z80: =AVERAGE(W80:W85) -> -6.0482977 | AA80: =AVERAGE(X80:X85) -> 0.35358117
A81: 43951 | B81: 5.2322153 | C81: -10.955455 | D81: 1.41 | E81: 复苏 | F81: 宽货币宽信用 | G81: 双宽 | H81: 主动补库存 | I81: 产能周期上行,主动补库存 | J81: {=INDEX(股债表现与四个维度!$A:$T,MATCH($A81,股债表现与四个维度!$A:$A,0),MATCH(J$3&J$4,股债表现与四个维度!$2:$2&股债表现与四个维度!$3:$3,0))} -> 0.18181818 | K81: {=INDEX(股债表现与四个维度!$A:$T,MATCH($A81,股债表现与四个维度!$A:$A,0),MATCH(K$3&K$4,股债表现与四个维度!$2:$2&股债表现与四个维度!$3:$3,0))} -> -0.36363636 | L81: {=INDEX(股债表现与四个维度!$A:$T,MATCH($A81,股债表现与四个维度!$A:$A,0),MATCH(L$3&L$4,股债表现与四个维度!$2:$2&股债表现与四个维度!$3:$3,0))} -> 0.0625 | M81: {=INDEX(股债表现与四个维度!$A:$T,MATCH($A81,股债表现与四个维度!$A:$A,0),MATCH(M$3&M$4,股债表现与四个维度!$2:$2&股债表现与四个维度!$3:$3,0))} -> 0.21875 | P81: {=INDEX(股债表现与四个维度!$A:$T,MATCH($A81,股债表现与四个维度!$A:$A,0),MATCH(P$3&P$4,股债表现与四个维度!$2:$2&股债表现与四个维度!$3:$3,0))} -> 0.21428571 | Q81: {=INDEX(股债表现与四个维度!$A:$T,MATCH($A81,股债表现与四个维度!$A:$A,0),MATCH(Q$3&Q$4,股债表现与四个维度!$2:$2&股债表现与四个维度!$3:$3,0))} -> 0 | R81: {=INDEX(股债表现与四个维度!$A:$T,MATCH($A81,股债表现与四个维度!$A:$A,0),MATCH(R$3&R$4,股债表现与四个维度!$2:$2&股债表现与四个维度!$3:$3,0))} -> 0.18181818 | S81: {=INDEX(股债表现与四个维度!$A:$T,MATCH($A81,股债表现与四个维度!$A:$A,0),MATCH(S$3&S$4,股债表现与四个维度!$2:$2&股债表现与四个维度!$3:$3,0))} -> -0.18181818 | T81: =SUMIFS($J81:$S81,$J81:$S81,"<>"&"#N/A",$J$4:$S$4,T$4) -> 0.64042208 | U81: =SUMIFS($J81:$S81,$J81:$S81,"<>"&"#N/A",$J$4:$S$4,U$4) -> -0.32670455 | V81: =T81-U81 -> 0.96712662 | W81: =B81+C81 -> -5.7232392 | X81: =B81-D81 -> 3.8222153 | Y81: =AVERAGE(V81:V86) -> 0.30534694 | Z81: =AVERAGE(W81:W86) -> -6.4480708 | AA81: =AVERAGE(X81:X86) -> 0.28794569
A82: 43921 | B82: -6.5302763 | C82: -30.921614 | D82: 0.4 | E82: 复苏 | F82: 宽货币宽信用 | G82: 双宽 | H82: 主动补库存 | I82: 产能周期上行,主动补库存 | J82: {=INDEX(股债表现与四个维度!$A:$T,MATCH($A82,股债表现与四个维度!$A:$A,0),MATCH(J$3&J$4,股债表现与四个维度!$2:$2&股债表现与四个维度!$3:$3,0))} -> 0.18181818 | K82: {=INDEX(股债表现与四个维度!$A:$T,MATCH($A82,股债表现与四个维度!$A:$A,0),MATCH(K$3&K$4,股债表现与四个维度!$2:$2&股债表现与四个维度!$3:$3,0))} -> -0.36363636 | L82: {=INDEX(股债表现与四个维度!$A:$T,MATCH($A82,股债表现与四个维度!$A:$A,0),MATCH(L$3&L$4,股债表现与四个维度!$2:$2&股债表现与四个维度!$3:$3,0))} -> 0.064516129 | M82: {=INDEX(股债表现与四个维度!$A:$T,MATCH($A82,股债表现与四个维度!$A:$A,0),MATCH(M$3&M$4,股债表现与四个维度!$2:$2&股债表现与四个维度!$3:$3,0))} -> 0.19354839 | P82: {=INDEX(股债表现与四个维度!$A:$T,MATCH($A82,股债表现与四个维度!$A:$A,0),MATCH(P$3&P$4,股债表现与四个维度!$2:$2&股债表现与四个维度!$3:$3,0))} -> 0.26666667 | Q82: {=INDEX(股债表现与四个维度!$A:$T,MATCH($A82,股债表现与四个维度!$A:$A,0),MATCH(Q$3&Q$4,股债表现与四个维度!$2:$2&股债表现与四个维度!$3:$3,0))} -> 0.066666667 | R82: {=INDEX(股债表现与四个维度!$A:$T,MATCH($A82,股债表现与四个维度!$A:$A,0),MATCH(R$3&R$4,股债表现与四个维度!$2:$2&股债表现与四个维度!$3:$3,0))} -> 0.18181818 | S82: {=INDEX(股债表现与四个维度!$A:$T,MATCH($A82,股债表现与四个维度!$A:$A,0),MATCH(S$3&S$4,股债表现与四个维度!$2:$2&股债表现与四个维度!$3:$3,0))} -> -0.18181818 | T82: =SUMIFS($J82:$S82,$J82:$S82,"<>"&"#N/A",$J$4:$S$4,T$4) -> 0.69481916 | U82: =SUMIFS($J82:$S82,$J82:$S82,"<>"&"#N/A",$J$4:$S$4,U$4) -> -0.28523949 | V82: =T82-U82 -> 0.98005865 | W82: =B82+C82 -> -37.45189 | X82: =B82-D82 -> -6.9302763 | Y82: =AVERAGE(V82:V87) -> 0.15306416 | Z82: =AVERAGE(W82:W87) -> -4.6700223 | AA82: =AVERAGE(X82:X87) -> -0.25416818
A83: 43890 | B83: -0.14006288 | C83: -10.537148 | D83: 0.98 | E83: 过热 | F83: 宽货币宽信用 | G83: 双宽 | H83: 主动去库存 | I83: 产能周期上行,被动补库存 | J83: {=INDEX(股债表现与四个维度!$A:$T,MATCH($A83,股债表现与四个维度!$A:$A,0),MATCH(J$3&J$4,股债表现与四个维度!$2:$2&股债表现与四个维度!$3:$3,0))} -> 0.2 | K83: {=INDEX(股债表现与四个维度!$A:$T,MATCH($A83,股债表现与四个维度!$A:$A,0),MATCH(K$3&K$4,股债表现与四个维度!$2:$2&股债表现与四个维度!$3:$3,0))} -> -0.13333333 | L83: {=INDEX(股债表现与四个维度!$A:$T,MATCH($A83,股债表现与四个维度!$A:$A,0),MATCH(L$3&L$4,股债表现与四个维度!$2:$2&股债表现与四个维度!$3:$3,0))} -> 0.066666667 | M83: {=INDEX(股债表现与四个维度!$A:$T,MATCH($A83,股债表现与四个维度!$A:$A,0),MATCH(M$3&M$4,股债表现与四个维度!$2:$2&股债表现与四个维度!$3:$3,0))} -> 0.16666667 | P83: {=INDEX(股债表现与四个维度!$A:$T,MATCH($A83,股债表现与四个维度!$A:$A,0),MATCH(P$3&P$4,股债表现与四个维度!$2:$2&股债表现与四个维度!$3:$3,0))} -> 0.085714286 | Q83: {=INDEX(股债表现与四个维度!$A:$T,MATCH($A83,股债表现与四个维度!$A:$A,0),MATCH(Q$3&Q$4,股债表现与四个维度!$2:$2&股债表现与四个维度!$3:$3,0))} -> 0.057142857 | R83: {=INDEX(股债表现与四个维度!$A:$T,MATCH($A83,股债表现与四个维度!$A:$A,0),MATCH(R$3&R$4,股债表现与四个维度!$2:$2&股债表现与四个维度!$3:$3,0))} -> 0 | S83: {=INDEX(股债表现与四个维度!$A:$T,MATCH($A83,股债表现与四个维度!$A:$A,0),MATCH(S$3&S$4,股债表现与四个维度!$2:$2&股债表现与四个维度!$3:$3,0))} -> 0.5 | T83: =SUMIFS($J83:$S83,$J83:$S83,"<>"&"#N/A",$J$4:$S$4,T$4) -> 0.35238095 | U83: =SUMIFS($J83:$S83,$J83:$S83,"<>"&"#N/A",$J$4:$S$4,U$4) -> 0.59047619 | V83: =T83-U83 -> -0.23809524 | W83: =B83+C83 -> -10.677211 | X83: =B83-D83 -> -1.1200629 | Y83: =AVERAGE(V83:V88) -> -0.05217575 | Z83: =AVERAGE(W83:W88) -> -0.57035719 | AA83: =AVERAGE(X83:X88) -> 0.70562
... A127: 42429 | B127: -14.751567 | C127: -5.1175187 | D127: 0.45 | E127: 滞涨 | F127: 宽货币宽信用 | G127: 紧货币宽财政 | H127: 主动去库存 | I127: 产能周期下行,被动去库存 | J127: {=INDEX(股债表现与四个维度!$A:$T,MATCH($A127,股债表现与四个维度!$A:$A,0),MATCH(J$3&J$4,股债表现与四个维度!$2:$2&股债表现与四个维度!$3:$3,0))} -> 0.42857143 | K127: {=INDEX(股债表现与四个维度!$A:$T,MATCH($A127,股债表现与四个维度!$A:$A,0),MATCH(K$3&K$4,股债表现与四个维度!$2:$2&股债表现与四个维度!$3:$3,0))} -> -0.14285714 | L127: {=INDEX(股债表现与四个维度!$A:$T,MATCH($A127,股债表现与四个维度!$A:$A,0),MATCH(L$3&L$4,股债表现与四个维度!$2:$2&股债表现与四个维度!$3:$3,0))} -> -0.25 | M127: {=INDEX(股债表现与四个维度!$A:$T,MATCH($A127,股债表现与四个维度!$A:$A,0),MATCH(M$3&M$4,股债表现与四个维度!$2:$2&股债表现与四个维度!$3:$3,0))} -> 0.5 | P127: {=INDEX(股债表现与四个维度!$A:$T,MATCH($A127,股债表现与四个维度!$A:$A,0),MATCH(P$3&P$4,股债表现与四个维度!$2:$2&股债表现与四个维度!$3:$3,0))} -> 0.04 | Q127: {=INDEX(股债表现与四个维度!$A:$T,MATCH($A127,股债表现与四个维度!$A:$A,0),MATCH(Q$3&Q$4,股债表现与四个维度!$2:$2&股债表现与四个维度!$3:$3,0))} -> -0.2 | R127: {=INDEX(股债表现与四个维度!$A:$T,MATCH($A127,股债表现与四个维度!$A:$A,0),MATCH(R$3&R$4,股债表现与四个维度!$2:$2&股债表现与四个维度!$3:$3,0))} -> 0.18181818 | S127: {=INDEX(股债表现与四个维度!$A:$T,MATCH($A127,股债表现与四个维度!$A:$A,0),MATCH(S$3&S$4,股债表现与四个维度!$2:$2&股债表现与四个维度!$3:$3,0))} -> -0.36363636 | T127: =SUMIFS($J127:$S127,$J127:$S127,"<>"&"#N/A",$J$4:$S$4,T$4) -> 0.40038961 | U127: =SUMIFS($J127:$S127,$J127:$S127,"<>"&"#N/A",$J$4:$S$4,U$4) -> -0.20649351 | V127: =T127-U127 -> 0.60688312 | W127: =B127+C127 -> -19.869086 | X127: =B127-D127 -> -15.201567 | Y127: =AVERAGE(V127:V132) -> -0.14708293 | Z127: =AVERAGE(W127:W132) -> -11.383146 | AA127: =AVERAGE(X127:X132) -> -1.8255885
A128: 42369 | B128: 5.3346949 | C128: -17.751863 | D128: 1.01 | E128: 滞涨 | F128: 宽货币宽信用 | H128: 主动去库存 | I128: 产能周期下行,主动去库存 | J128: {=INDEX(股债表现与四个维度!$A:$T,MATCH($A128,股债表现与四个维度!$A:$A,0),MATCH(J$3&J$4,股债表现与四个维度!$2:$2&股债表现与四个维度!$3:$3,0))} -> 0.2 | K128: {=INDEX(股债表现与四个维度!$A:$T,MATCH($A128,股债表现与四个维度!$A:$A,0),MATCH(K$3&K$4,股债表现与四个维度!$2:$2&股债表现与四个维度!$3:$3,0))} -> -0.2 | L128: {=INDEX(股债表现与四个维度!$A:$T,MATCH($A128,股债表现与四个维度!$A:$A,0),MATCH(L$3&L$4,股债表现与四个维度!$2:$2&股债表现与四个维度!$3:$3,0))} -> -0.66666667 | M128: {=INDEX(股债表现与四个维度!$A:$T,MATCH($A128,股债表现与四个维度!$A:$A,0),MATCH(M$3&M$4,股债表现与四个维度!$2:$2&股债表现与四个维度!$3:$3,0))} -> 0.66666667 | P128: {=INDEX(股债表现与四个维度!$A:$T,MATCH($A128,股债表现与四个维度!$A:$A,0),MATCH(P$3&P$4,股债表现与四个维度!$2:$2&股债表现与四个维度!$3:$3,0))} -> -0.043478261 | Q128: {=INDEX(股债表现与四个维度!$A:$T,MATCH($A128,股债表现与四个维度!$A:$A,0),MATCH(Q$3&Q$4,股债表现与四个维度!$2:$2&股债表现与四个维度!$3:$3,0))} -> -0.2173913 | R128: {=INDEX(股债表现与四个维度!$A:$T,MATCH($A128,股债表现与四个维度!$A:$A,0),MATCH(R$3&R$4,股债表现与四个维度!$2:$2&股债表现与四个维度!$3:$3,0))} -> 0.14814815 | S128: {=INDEX(股债表现与四个维度!$A:$T,MATCH($A128,股债表现与四个维度!$A:$A,0),MATCH(S$3&S$4,股债表现与四个维度!$2:$2&股债表现与四个维度!$3:$3,0))} -> 0.33333333 | T128: =SUMIFS($J128:$S128,$J128:$S128,"<>"&"#N/A",$J$4:$S$4,T$4) -> -0.36199678 | U128: =SUMIFS($J128:$S128,$J128:$S128,"<>"&"#N/A",$J$4:$S$4,U$4) -> 0.5826087 | V128: =T128-U128 -> -0.94460548 | W128: =B128+C128 -> -12.417168 | X128: =B128-D128 -> 4.3246949 | Y128: =AVERAGE(V128:V133) -> -0.24823012 | Z128: =AVERAGE(W128:W133) -> -12.441981 | AA128: =AVERAGE(X128:X133) -> -1.7989716
A129: 42338 | B129: 6.2075222 | C129: 3.3803175 | D129: 0.16 | E129: 滞涨 | F129: 宽货币宽信用 | H129: 主动去库存 | I129: 产能周期下行,主动去库存 | J129: {=INDEX(股债表现与四个维度!$A:$T,MATCH($A129,股债表现与四个维度!$A:$A,0),MATCH(J$3&J$4,股债表现与四个维度!$2:$2&股债表现与四个维度!$3:$3,0))} -> 0.2 | K129: {=INDEX(股债表现与四个维度!$A:$T,MATCH($A129,股债表现与四个维度!$A:$A,0),MATCH(K$3&K$4,股债表现与四个维度!$2:$2&股债表现与四个维度!$3:$3,0))} -> -0.6 | L129: {=INDEX(股债表现与四个维度!$A:$T,MATCH($A129,股债表现与四个维度!$A:$A,0),MATCH(L$3&L$4,股债表现与四个维度!$2:$2&股债表现与四个维度!$3:$3,0))} -> -1 | M129: {=INDEX(股债表现与四个维度!$A:$T,MATCH($A129,股债表现与四个维度!$A:$A,0),MATCH(M$3&M$4,股债表现与四个维度!$2:$2&股债表现与四个维度!$3:$3,0))} -> 0.6 | P129: {=INDEX(股债表现与四个维度!$A:$T,MATCH($A129,股债表现与四个维度!$A:$A,0),MATCH(P$3&P$4,股债表现与四个维度!$2:$2&股债表现与四个维度!$3:$3,0))} -> -0.090909091 | Q129: {=INDEX(股债表现与四个维度!$A:$T,MATCH($A129,股债表现与四个维度!$A:$A,0),MATCH(Q$3&Q$4,股债表现与四个维度!$2:$2&股债表现与四个维度!$3:$3,0))} -> -0.27272727 | R129: {=INDEX(股债表现与四个维度!$A:$T,MATCH($A129,股债表现与四个维度!$A:$A,0),MATCH(R$3&R$4,股债表现与四个维度!$2:$2&股债表现与四个维度!$3:$3,0))} -> 0.11538462 | S129: {=INDEX(股债表现与四个维度!$A:$T,MATCH($A129,股债表现与四个维度!$A:$A,0),MATCH(S$3&S$4,股债表现与四个维度!$2:$2&股债表现与四个维度!$3:$3,0))} -> 0.30769231 | T129: =SUMIFS($J129:$S129,$J129:$S129,"<>"&"#N/A",$J$4:$S$4,T$4) -> -0.77552448 | U129: =SUMIFS($J129:$S129,$J129:$S129,"<>"&"#N/A",$J$4:$S$4,U$4) -> 0.034965035 | V129: =T129-U129 -> -0.81048951 | W129: =B129+C129 -> 9.5878396 | X129: =B129-D129 -> 6.0475222 | Y129: =AVERAGE(V129:V134) -> -0.090795871 | Z129: =AVERAGE(W129:W134) -> -9.375002 | AA129: =AVERAGE(X129:X134) -> -3.8882401
A130: 42308 | B130: 17.101641 | C130: -23.252222 | D130: 1.77 | E130: 滞涨 | F130: 宽货币宽信用 | H130: 主动去库存 | I130: 产能周期下行,主动去库存 | J130: {=INDEX(股债表现与四个维度!$A:$T,MATCH($A130,股债表现与四个维度!$A:$A,0),MATCH(J$3&J$4,股债表现与四个维度!$2:$2&股债表现与四个维度!$3:$3,0))} -> 0.6 | K130: {=INDEX(股债表现与四个维度!$A:$T,MATCH($A130,股债表现与四个维度!$A:$A,0),MATCH(K$3&K$4,股债表现与四个维度!$2:$2&股债表现与四个维度!$3:$3,0))} -> -1 | L130: {=INDEX(股债表现与四个维度!$A:$T,MATCH($A130,股债表现与四个维度!$A:$A,0),MATCH(L$3&L$4,股债表现与四个维度!$2:$2&股债表现与四个维度!$3:$3,0))} -> -1 | M130: {=INDEX(股债表现与四个维度!$A:$T,MATCH($A130,股债表现与四个维度!$A:$A,0),MATCH(M$3&M$4,股债表现与四个维度!$2:$2&股债表现与四个维度!$3:$3,0))} -> 0.5 | P130: {=INDEX(股债表现与四个维度!$A:$T,MATCH($A130,股债表现与四个维度!$A:$A,0),MATCH(P$3&P$4,股债表现与四个维度!$2:$2&股债表现与四个维度!$3:$3,0))} -> -0.047619048 | Q130: {=INDEX(股债表现与四个维度!$A:$T,MATCH($A130,股债表现与四个维度!$A:$A,0),MATCH(Q$3&Q$4,股债表现与四个维度!$2:$2&股债表现与四个维度!$3:$3,0))} -> -0.33333333 | R130: {=INDEX(股债表现与四个维度!$A:$T,MATCH($A130,股债表现与四个维度!$A:$A,0),MATCH(R$3&R$4,股债表现与四个维度!$2:$2&股债表现与四个维度!$3:$3,0))} -> 0.16 | S130: {=INDEX(股债表现与四个维度!$A:$T,MATCH($A130,股债表现与四个维度!$A:$A,0),MATCH(S$3&S$4,股债表现与四个维度!$2:$2&股债表现与四个维度!$3:$3,0))} -> 0.28 | T130: =SUMIFS($J130:$S130,$J130:$S130,"<>"&"#N/A",$J$4:$S$4,T$4) -> -0.28761905 | U130: =SUMIFS($J130:$S130,$J130:$S130,"<>"&"#N/A",$J$4:$S$4,U$4) -> -0.55333333 | V130: =T130-U130 -> 0.26571429 | W130: =B130+C130 -> -6.1505817 | X130: =B130-D130 -> 15.331641 | Y130: =AVERAGE(V130:V135) -> 0.044285714 | Z130: =AVERAGE(W130:W135) -> -9.9784062 | AA130: =AVERAGE(X130:X135) -> -2.9636708
A131: 42277 | B131: -5.9193732 | C131: -15.602857 | D131: 0.44 | E131: 滞涨 | F131: 宽货币宽信用 | H131: 主动去库存 | I131: 产能周期下行,主动去库存 | J131: {=INDEX(股债表现与四个维度!$A:$T,MATCH($A131,股债表现与四个维度!$A:$A,0),MATCH(J$3&J$4,股债表现与四个维度!$2:$2&股债表现与四个维度!$3:$3,0))} -> 0 | K131: {=INDEX(股债表现与四个维度!$A:$T,MATCH($A131,股债表现与四个维度!$A:$A,0),MATCH(K$3&K$4,股债表现与四个维度!$2:$2&股债表现与四个维度!$3:$3,0))} -> 0 | L131: {=INDEX(股债表现与四个维度!$A:$T,MATCH($A131,股债表现与四个维度!$A:$A,0),MATCH(L$3&L$4,股债表现与四个维度!$2:$2&股债表现与四个维度!$3:$3,0))} -> 0 | M131: {=INDEX(股债表现与四个维度!$A:$T,MATCH($A131,股债表现与四个维度!$A:$A,0),MATCH(M$3&M$4,股债表现与四个维度!$2:$2&股债表现与四个维度!$3:$3,0))} -> 0 | P131: {=INDEX(股债表现与四个维度!$A:$T,MATCH($A131,股债表现与四个维度!$A:$A,0),MATCH(P$3&P$4,股债表现与四个维度!$2:$2&股债表现与四个维度!$3:$3,0))} -> 0 | Q131: {=INDEX(股债表现与四个维度!$A:$T,MATCH($A131,股债表现与四个维度!$A:$A,0),MATCH(Q$3&Q$4,股债表现与四个维度!$2:$2&股债表现与四个维度!$3:$3,0))} -> 0 | R131: {=INDEX(股债表现与四个维度!$A:$T,MATCH($A131,股债表现与四个维度!$A:$A,0),MATCH(R$3&R$4,股债表现与四个维度!$2:$2&股债表现与四个维度!$3:$3,0))} -> 0 | S131: {=INDEX(股债表现与四个维度!$A:$T,MATCH($A131,股债表现与四个维度!$A:$A,0),MATCH(S$3&S$4,股债表现与四个维度!$2:$2&股债表现与四个维度!$3:$3,0))} -> 0 | T131: =SUMIFS($J131:$S131,$J131:$S131,"<>"&"#N/A",$J$4:$S$4,T$4) -> 0 | U131: =SUMIFS($J131:$S131,$J131:$S131,"<>"&"#N/A",$J$4:$S$4,U$4) -> 0 | V131: =T131-U131 -> 0 | W131: =B131+C131 -> -21.52223 | X131: =B131-D131 -> -6.3593732 | Y131: =AVERAGE(V131:V136) -> 0 | Z131: =AVERAGE(W131:W136) -> -5.3138248 | AA131: =AVERAGE(X131:X136) -> -2.8783197
A132: 42247 | B132: -15.346449 | C132: -2.5812008 | D132: -0.25 | E132: 衰退 | F132: 宽货币宽信用 | H132: 主动去库存 | I132: 产能周期下行,主动去库存 | J132: {=INDEX(股债表现与四个维度!$A:$T,MATCH($A132,股债表现与四个维度!$A:$A,0),MATCH(J$3&J$4,股债表现与四个维度!$2:$2&股债表现与四个维度!$3:$3,0))} -> 0 | K132: {=INDEX(股债表现与四个维度!$A:$T,MATCH($A132,股债表现与四个维度!$A:$A,0),MATCH(K$3&K$4,股债表现与四个维度!$2:$2&股债表现与四个维度!$3:$3,0))} -> 0 | L132: {=INDEX(股债表现与四个维度!$A:$T,MATCH($A132,股债表现与四个维度!$A:$A,0),MATCH(L$3&L$4,股债表现与四个维度!$2:$2&股债表现与四个维度!$3:$3,0))} -> 0 | M132: {=INDEX(股债表现与四个维度!$A:$T,MATCH($A132,股债表现与四个维度!$A:$A,0),MATCH(M$3&M$4,股债表现与四个维度!$2:$2&股债表现与四个维度!$3:$3,0))} -> 0 | P132: {=INDEX(股债表现与四个维度!$A:$T,MATCH($A132,股债表现与四个维度!$A:$A,0),MATCH(P$3&P$4,股债表现与四个维度!$2:$2&股债表现与四个维度!$3:$3,0))} -> 0 | Q132: {=INDEX(股债表现与四个维度!$A:$T,MATCH($A132,股债表现与四个维度!$A:$A,0),MATCH(Q$3&Q$4,股债表现与四个维度!$2:$2&股债表现与四个维度!$3:$3,0))} -> 0 | R132: {=INDEX(股债表现与四个维度!$A:$T,MATCH($A132,股债表现与四个维度!$A:$A,0),MATCH(R$3&R$4,股债表现与四个维度!$2:$2&股债表现与四个维度!$3:$3,0))} -> 0 | S132: {=INDEX(股债表现与四个维度!$A:$T,MATCH($A132,股债表现与四个维度!$A:$A,0),MATCH(S$3&S$4,股债表现与四个维度!$2:$2&股债表现与四个维度!$3:$3,0))} -> 0 | T132: =SUMIFS($J132:$S132,$J132:$S132,"<>"&"#N/A",$J$4:$S$4,T$4) -> 0 | U132: =SUMIFS($J132:$S132,$J132:$S132,"<>"&"#N/A",$J$4:$S$4,U$4) -> 0 | V132: =T132-U132 -> 0 | W132: =B132+C132 -> -17.927649 | X132: =B132-D132 -> -15.096449 | Y132: =AVERAGE(V132:V137) -> 0 | Z132: =AVERAGE(W132:W137) -> 1.9546366 | AA132: =AVERAGE(X132:X137) -> 1.1118238
A133: 42216 | B133: -15.771865 | C133: -10.450228 | D133: -0.73 | E133: 衰退 | F133: 宽货币宽信用 | H133: 主动去库存 | I133: 产能周期下行,主动去库存 | J133: {=INDEX(股债表现与四个维度!$A:$T,MATCH($A133,股债表现与四个维度!$A:$A,0),MATCH(J$3&J$4,股债表现与四个维度!$2:$2&股债表现与四个维度!$3:$3,0))} -> 0 | K133: {=INDEX(股债表现与四个维度!$A:$T,MATCH($A133,股债表现与四个维度!$A:$A,0),MATCH(K$3&K$4,股债表现与四个维度!$2:$2&股债表现与四个维度!$3:$3,0))} -> 0 | L133: {=INDEX(股债表现与四个维度!$A:$T,MATCH($A133,股债表现与四个维度!$A:$A,0),MATCH(L$3&L$4,股债表现与四个维度!$2:$2&股债表现与四个维度!$3:$3,0))} -> 0 | M133: {=INDEX(股债表现与四个维度!$A:$T,MATCH($A133,股债表现与四个维度!$A:$A,0),MATCH(M$3&M$4,股债表现与四个维度!$2:$2&股债表现与四个维度!$3:$3,0))} -> 0 | P133: {=INDEX(股债表现与四个维度!$A:$T,MATCH($A133,股债表现与四个维度!$A:$A,0),MATCH(P$3&P$4,股债表现与四个维度!$2:$2&股债表现与四个维度!$3:$3,0))} -> 0 | Q133: {=INDEX(股债表现与四个维度!$A:$T,MATCH($A133,股债表现与四个维度!$A:$A,0),MATCH(Q$3&Q$4,股债表现与四个维度!$2:$2&股债表现与四个维度!$3:$3,0))} -> 0 | R133: {=INDEX(股债表现与四个维度!$A:$T,MATCH($A133,股债表现与四个维度!$A:$A,0),MATCH(R$3&R$4,股债表现与四个维度!$2:$2&股债表现与四个维度!$3:$3,0))} -> 0 | S133: {=INDEX(股债表现与四个维度!$A:$T,MATCH($A133,股债表现与四个维度!$A:$A,0),MATCH(S$3&S$4,股债表现与四个维度!$2:$2&股债表现与四个维度!$3:$3,0))} -> 0 | T133: =SUMIFS($J133:$S133,$J133:$S133,"<>"&"#N/A",$J$4:$S$4,T$4) -> 0 | U133: =SUMIFS($J133:$S133,$J133:$S133,"<>"&"#N/A",$J$4:$S$4,U$4) -> 0 | V133: =T133-U133 -> 0 | W133: =B133+C133 -> -26.222093 | X133: =B133-D133 -> -15.041865 | Y133: =AVERAGE(V133:V138) -> 0 | Z133: =AVERAGE(W133:W138) -> 3.825399 | AA133: =AVERAGE(X133:X138) -> 4.1614288
A134: 42185 | B134: -10.520916 | C134: 16.505619 | D134: -2.31 | E134: 复苏 | F134: 宽货币宽信用 | H134: 主动补库存 | I134: 产能周期下行,主动去库存 | J134: {=INDEX(股债表现与四个维度!$A:$T,MATCH($A134,股债表现与四个维度!$A:$A,0),MATCH(J$3&J$4,股债表现与四个维度!$2:$2&股债表现与四个维度!$3:$3,0))} -> 0 | K134: {=INDEX(股债表现与四个维度!$A:$T,MATCH($A134,股债表现与四个维度!$A:$A,0),MATCH(K$3&K$4,股债表现与四个维度!$2:$2&股债表现与四个维度!$3:$3,0))} -> 0 | L134: {=INDEX(股债表现与四个维度!$A:$T,MATCH($A134,股债表现与四个维度!$A:$A,0),MATCH(L$3&L$4,股债表现与四个维度!$2:$2&股债表现与四个维度!$3:$3,0))} -> 0 | M134: {=INDEX(股债表现与四个维度!$A:$T,MATCH($A134,股债表现与四个维度!$A:$A,0),MATCH(M$3&M$4,股债表现与四个维度!$2:$2&股债表现与四个维度!$3:$3,0))} -> 0 | P134: {=INDEX(股债表现与四个维度!$A:$T,MATCH($A134,股债表现与四个维度!$A:$A,0),MATCH(P$3&P$4,股债表现与四个维度!$2:$2&股债表现与四个维度!$3:$3,0))} -> 0 | Q134: {=INDEX(股债表现与四个维度!$A:$T,MATCH($A134,股债表现与四个维度!$A:$A,0),MATCH(Q$3&Q$4,股债表现与四个维度!$2:$2&股债表现与四个维度!$3:$3,0))} -> 0 | R134: {=INDEX(股债表现与四个维度!$A:$T,MATCH($A134,股债表现与四个维度!$A:$A,0),MATCH(R$3&R$4,股债表现与四个维度!$2:$2&股债表现与四个维度!$3:$3,0))} -> 0 | S134: {=INDEX(股债表现与四个维度!$A:$T,MATCH($A134,股债表现与四个维度!$A:$A,0),MATCH(S$3&S$4,股债表现与四个维度!$2:$2&股债表现与四个维度!$3:$3,0))} -> 0 | T134: =SUMIFS($J134:$S134,$J134:$S134,"<>"&"#N/A",$J$4:$S$4,T$4) -> 0 | U134: =SUMIFS($J134:$S134,$J134:$S134,"<>"&"#N/A",$J$4:$S$4,U$4) -> 0 | V134: =T134-U134 -> 0 | W134: =B134+C134 -> 5.984703 | X134: =B134-D134 -> -8.2109161 | Z134: =AVERAGE(W134:W139) -> 11.694677 | AA134: =AVERAGE(X134:X139) -> 8.0413646
A135: 42155 | B135: 15.044938 | C135: -9.0775238 | D135: 3.45 | E135: 复苏 | F135: 宽货币紧信用 | H135: 主动补库存 | I135: 产能周期下行,主动去库存 | J135: {=INDEX(股债表现与四个维度!$A:$T,MATCH($A135,股债表现与四个维度!$A:$A,0),MATCH(J$3&J$4,股债表现与四个维度!$2:$2&股债表现与四个维度!$3:$3,0))} -> 0 | K135: {=INDEX(股债表现与四个维度!$A:$T,MATCH($A135,股债表现与四个维度!$A:$A,0),MATCH(K$3&K$4,股债表现与四个维度!$2:$2&股债表现与四个维度!$3:$3,0))} -> 0 | L135: {=INDEX(股债表现与四个维度!$A:$T,MATCH($A135,股债表现与四个维度!$A:$A,0),MATCH(L$3&L$4,股债表现与四个维度!$2:$2&股债表现与四个维度!$3:$3,0))} -> 0 | M135: {=INDEX(股债表现与四个维度!$A:$T,MATCH($A135,股债表现与四个维度!$A:$A,0),MATCH(M$3&M$4,股债表现与四个维度!$2:$2&股债表现与四个维度!$3:$3,0))} -> 0 | P135: {=INDEX(股债表现与四个维度!$A:$T,MATCH($A135,股债表现与四个维度!$A:$A,0),MATCH(P$3&P$4,股债表现与四个维度!$2:$2&股债表现与四个维度!$3:$3,0))} -> 0 | Q135: {=INDEX(股债表现与四个维度!$A:$T,MATCH($A135,股债表现与四个维度!$A:$A,0),MATCH(Q$3&Q$4,股债表现与四个维度!$2:$2&股债表现与四个维度!$3:$3,0))} -> 0 | R135: {=INDEX(股债表现与四个维度!$A:$T,MATCH($A135,股债表现与四个维度!$A:$A,0),MATCH(R$3&R$4,股债表现与四个维度!$2:$2&股债表现与四个维度!$3:$3,0))} -> 0 | S135: {=INDEX(股债表现与四个维度!$A:$T,MATCH($A135,股债表现与四个维度!$A:$A,0),MATCH(S$3&S$4,股债表现与四个维度!$2:$2&股债表现与四个维度!$3:$3,0))} -> 0 | T135: =SUMIFS($J135:$S135,$J135:$S135,"<>"&"#N/A",$J$4:$S$4,T$4) -> 0 | U135: =SUMIFS($J135:$S135,$J135:$S135,"<>"&"#N/A",$J$4:$S$4,U$4) -> 0 | V135: =T135-U135 -> 0 | W135: =B135+C135 -> 5.9674142 | X135: =B135-D135 -> 11.594938 | Z135: =AVERAGE(W135:W140) -> 7.9285122 | AA135: =AVERAGE(X135:X140) -> 10.435803
A136: 42124 | B136: 18.963747 | C136: 2.8731602 | D136: 3.12 | E136: 复苏 | F136: 宽货币紧信用 | H136: 主动补库存 | I136: 产能周期下行,主动去库存 | J136: {=INDEX(股债表现与四个维度!$A:$T,MATCH($A136,股债表现与四个维度!$A:$A,0),MATCH(J$3&J$4,股债表现与四个维度!$2:$2&股债表现与四个维度!$3:$3,0))} -> 0 | K136: {=INDEX(股债表现与四个维度!$A:$T,MATCH($A136,股债表现与四个维度!$A:$A,0),MATCH(K$3&K$4,股债表现与四个维度!$2:$2&股债表现与四个维度!$3:$3,0))} -> 0 | L136: {=INDEX(股债表现与四个维度!$A:$T,MATCH($A136,股债表现与四个维度!$A:$A,0),MATCH(L$3&L$4,股债表现与四个维度!$2:$2&股债表现与四个维度!$3:$3,0))} -> 0 | M136: {=INDEX(股债表现与四个维度!$A:$T,MATCH($A136,股债表现与四个维度!$A:$A,0),MATCH(M$3&M$4,股债表现与四个维度!$2:$2&股债表现与四个维度!$3:$3,0))} -> 0 | P136: {=INDEX(股债表现与四个维度!$A:$T,MATCH($A136,股债表现与四个维度!$A:$A,0),MATCH(P$3&P$4,股债表现与四个维度!$2:$2&股债表现与四个维度!$3:$3,0))} -> 0 | Q136: {=INDEX(股债表现与四个维度!$A:$T,MATCH($A136,股债表现与四个维度!$A:$A,0),MATCH(Q$3&Q$4,股债表现与四个维度!$2:$2&股债表现与四个维度!$3:$3,0))} -> 0 | R136: {=INDEX(股债表现与四个维度!$A:$T,MATCH($A136,股债表现与四个维度!$A:$A,0),MATCH(R$3&R$4,股债表现与四个维度!$2:$2&股债表现与四个维度!$3:$3,0))} -> 0 | S136: {=INDEX(股债表现与四个维度!$A:$T,MATCH($A136,股债表现与四个维度!$A:$A,0),MATCH(S$3&S$4,股债表现与四个维度!$2:$2&股债表现与四个维度!$3:$3,0))} -> 0 | T136: =SUMIFS($J136:$S136,$J136:$S136,"<>"&"#N/A",$J$4:$S$4,T$4) -> 0 | U136: =SUMIFS($J136:$S136,$J136:$S136,"<>"&"#N/A",$J$4:$S$4,U$4) -> 0 | V136: =T136-U136 -> 0 | W136: =B136+C136 -> 21.836907 | X136: =B136-D136 -> 15.843747 | Z136: =AVERAGE(W136:W141) -> 2.0351385 | AA136: =AVERAGE(X136:X141) -> 8.4173115
A137: 42094 | B137: 18.781488 | C137: 3.3070499 | D137: 1.2 | E137: 衰退 | F137: 宽货币紧信用 | H137: 主动补库存 | I137: 产能周期下行,主动去库存 | J137: {=INDEX(股债表现与四个维度!$A:$T,MATCH($A137,股债表现与四个维度!$A:$A,0),MATCH(J$3&J$4,股债表现与四个维度!$2:$2&股债表现与四个维度!$3:$3,0))} -> 0 | K137: {=INDEX(股债表现与四个维度!$A:$T,MATCH($A137,股债表现与四个维度!$A:$A,0),MATCH(K$3&K$4,股债表现与四个维度!$2:$2&股债表现与四个维度!$3:$3,0))} -> 0 | L137: {=INDEX(股债表现与四个维度!$A:$T,MATCH($A137,股债表现与四个维度!$A:$A,0),MATCH(L$3&L$4,股债表现与四个维度!$2:$2&股债表现与四个维度!$3:$3,0))} -> 0 | M137: {=INDEX(股债表现与四个维度!$A:$T,MATCH($A137,股债表现与四个维度!$A:$A,0),MATCH(M$3&M$4,股债表现与四个维度!$2:$2&股债表现与四个维度!$3:$3,0))} -> 0 | P137: {=INDEX(股债表现与四个维度!$A:$T,MATCH($A137,股债表现与四个维度!$A:$A,0),MATCH(P$3&P$4,股债表现与四个维度!$2:$2&股债表现与四个维度!$3:$3,0))} -> 0 | Q137: {=INDEX(股债表现与四个维度!$A:$T,MATCH($A137,股债表现与四个维度!$A:$A,0),MATCH(Q$3&Q$4,股债表现与四个维度!$2:$2&股债表现与四个维度!$3:$3,0))} -> 0 | R137: {=INDEX(股债表现与四个维度!$A:$T,MATCH($A137,股债表现与四个维度!$A:$A,0),MATCH(R$3&R$4,股债表现与四个维度!$2:$2&股债表现与四个维度!$3:$3,0))} -> 0 | S137: {=INDEX(股债表现与四个维度!$A:$T,MATCH($A137,股债表现与四个维度!$A:$A,0),MATCH(S$3&S$4,股债表现与四个维度!$2:$2&股债表现与四个维度!$3:$3,0))} -> 0 | T137: =SUMIFS($J137:$S137,$J137:$S137,"<>"&"#N/A",$J$4:$S$4,T$4) -> 0 | U137: =SUMIFS($J137:$S137,$J137:$S137,"<>"&"#N/A",$J$4:$S$4,U$4) -> 0 | V137: =T137-U137 -> 0 | W137: =B137+C137 -> 22.088538 | X137: =B137-D137 -> 17.581488 | Z137: =AVERAGE(W137:W142) -> -1.4993378 | AA137: =AVERAGE(X137:X142) -> 7.0914319
A138: 42063 | B138: 4.1711811 | C138: -10.874256 | D138: 0.97 | E138: 衰退 | F138: 宽货币紧信用 | H138: 主动补库存 | I138: 产能周期下行,主动去库存 | J138: {=INDEX(股债表现与四个维度!$A:$T,MATCH($A138,股债表现与四个维度!$A:$A,0),MATCH(J$3&J$4,股债表现与四个维度!$2:$2&股债表现与四个维度!$3:$3,0))} -> 0 | K138: {=INDEX(股债表现与四个维度!$A:$T,MATCH($A138,股债表现与四个维度!$A:$A,0),MATCH(K$3&K$4,股债表现与四个维度!$2:$2&股债表现与四个维度!$3:$3,0))} -> 0 | L138: {=INDEX(股债表现与四个维度!$A:$T,MATCH($A138,股债表现与四个维度!$A:$A,0),MATCH(L$3&L$4,股债表现与四个维度!$2:$2&股债表现与四个维度!$3:$3,0))} -> 0 | M138: {=INDEX(股债表现与四个维度!$A:$T,MATCH($A138,股债表现与四个维度!$A:$A,0),MATCH(M$3&M$4,股债表现与四个维度!$2:$2&股债表现与四个维度!$3:$3,0))} -> 0 | P138: {=INDEX(股债表现与四个维度!$A:$T,MATCH($A138,股债表现与四个维度!$A:$A,0),MATCH(P$3&P$4,股债表现与四个维度!$2:$2&股债表现与四个维度!$3:$3,0))} -> 0 | Q138: {=INDEX(股债表现与四个维度!$A:$T,MATCH($A138,股债表现与四个维度!$A:$A,0),MATCH(Q$3&Q$4,股债表现与四个维度!$2:$2&股债表现与四个维度!$3:$3,0))} -> 0 | R138: {=INDEX(股债表现与四个维度!$A:$T,MATCH($A138,股债表现与四个维度!$A:$A,0),MATCH(R$3&R$4,股债表现与四个维度!$2:$2&股债表现与四个维度!$3:$3,0))} -> 0 | S138: {=INDEX(股债表现与四个维度!$A:$T,MATCH($A138,股债表现与四个维度!$A:$A,0),MATCH(S$3&S$4,股债表现与四个维度!$2:$2&股债表现与四个维度!$3:$3,0))} -> 0 | T138: =SUMIFS($J138:$S138,$J138:$S138,"<>"&"#N/A",$J$4:$S$4,T$4) -> 0 | U138: =SUMIFS($J138:$S138,$J138:$S138,"<>"&"#N/A",$J$4:$S$4,U$4) -> 0 | V138: =T138-U138 -> 0 | W138: =B138+C138 -> -6.7030751 | X138: =B138-D138 -> 3.2011811 | Z138: =AVERAGE(W138:W143) -> -4.0495486 | AA138: =AVERAGE(X138:X143) -> 4.4328999
A139: 42004 | B139: 11.23775 | C139: 9.7558261 | D139: 3 | E139: 衰退 | F139: 宽货币紧信用 | H139: 主动补库存 | I139: 产能周期下行,主动去库存 | W139: =B139+C139 -> 20.993576 | X139: =B139-D139 -> 8.2377498 | Z139: =AVERAGE(W139:W144) -> 1.0728443 | AA139: =AVERAGE(X139:X144) -> 5.1896233
A140: 41973 | B140: 9.0157128 | C140: -25.628 | D140: 2.86 | E140: 衰退 | F140: 宽货币紧信用 | H140: 主动补库存 | I140: 产能周期下行,主动去库存 | W140: =B140+C140 -> -16.612287 | X140: =B140-D140 -> 6.1557128 | Z140: =AVERAGE(W140:W145) -> -4.0901924 | AA140: =AVERAGE(X140:X145) -> 4.1032837
A141: 41943 | B141: 2.0739902 | C141: -31.466818 | D141: 2.59 | E141: 衰退 | F141: 宽货币紧信用 | H141: 被动补库存 | I141: 产能周期下行,主动去库存 | W141: =B141+C141 -> -29.392828 | X141: =B141-D141 -> -0.5160098 | Z141: =AVERAGE(W141:W146) -> -4.4593625 | AA141: =AVERAGE(X141:X146) -> 3.099447
A142: 41912 | B142: 9.6784694 | C142: -9.0484199 | D142: 1.79 | E142: 衰退 | F142: 宽货币紧信用 | H142: 被动补库存 | I142: 产能周期下行,主动去库存 | W142: =B142+C142 -> 0.63004948 | X142: =B142-D142 -> 7.8884694 | Z142: =AVERAGE(W142:W147) -> -1.6642926 | AA142: =AVERAGE(X142:X147) -> 2.8875075
A143: 41882 | B143: 2.8302961 | C143: 3.9569772 | D143: 1.2 | E143: 衰退 | F143: 宽货币紧信用 | H143: 被动补库存 | I143: 产能周期下行,主动去库存 | W143: =B143+C143 -> 6.7872733 | X143: =B143-D143 -> 1.6302961 | Z143: =AVERAGE(W143:W148) -> -2.5270043 | AA143: =AVERAGE(X143:X148) -> 1.1658058
A144: 41851 | B144: 8.5715214 | C144: 15.459761 | D144: 0.83 | E144: 滞涨 | F144: 宽货币紧信用 | H144: 被动补库存 | I144: 产能周期下行,被动补库存 | W144: =B144+C144 -> 24.031282 | X144: =B144-D144 -> 7.7415214 | Z144: =AVERAGE(W144:W149) -> -3.9102885 | AA144: =AVERAGE(X144:X149) -> 0.60903993
A145: 41820 | B145: 3.0797126 | C145: -13.064357 | D145: 1.36 | E145: 过热 | F145: 宽货币紧信用 | H145: 被动补库存 | I145: 产能周期下行,主动补库存 | W145: =B145+C145 -> -9.9846446 | X145: =B145-D145 -> 1.7197126 | Z145: =AVERAGE(W145:W150) -> -7.1414753 | AA145: =AVERAGE(X145:X150) -> -1.1422156
A146: 41790 | B146: 1.4926926 | C146: -20.32 | D146: 1.36 | E146: 过热 | F146: 宽货币紧信用 | H146: 被动补库存 | I146: 产能周期下行,主动补库存 | W146: =B146+C146 -> -18.827307 | X146: =B146-D146 -> 0.13269256 | Z146: =AVERAGE(W146:W151) -> 1.2295027 | AA146: =AVERAGE(X146:X151) -> -0.3779955
A147: 41759 | B147: -0.76764702 | C147: -11.854762 | D147: 1.02 | E147: 过热 | F147: 宽货币紧信用 | H147: 被动补库存 | I147: 产能周期下行,主动补库存 | W147: =B147+C147 -> -12.622409 | X147: =B147-D147 -> -1.787647 | Z147: =AVERAGE(W147:W152) -> 4.9800154 | AA147: =AVERAGE(X147:X152) -> -0.76248289
A148: 41729 | B148: -2.7917407 | C148: -1.7544799 | D148: -0.35 | E148: 复苏 | F148: 紧货币紧信用 | H148: 主动去库存 | I148: 产能周期下行,主动补库存 | W148: =B148+C148 -> -4.5462205 | X148: =B148-D148 -> -2.4417407 | Z148: =AVERAGE(W148:W153) -> 10.242738 | AA148: =AVERAGE(X148:X153) -> 0.3129311
A149: 41698 | B149: -0.17029925 | C149: -1.3421324 | D149: 1.54 | E149: 衰退 | F149: 紧货币紧信用 | H149: 主动去库存 | I149: 产能周期下行,主动补库存 | W149: =B149+C149 -> -1.5124316 | X149: =B149-D149 -> -1.7102993 | Z149: =AVERAGE(W149:W154) -> 16.74391 | AA149: =AVERAGE(X149:X154) -> 1.8002343
A150: 41639 | B150: -3.946012 | C150: 8.5901732 | D150: -1.18 | E150: 衰退 | F150: 紧货币紧信用 | H150: 主动去库存 | I150: 产能周期下行,主动补库存 | W150: =B150+C150 -> 4.6441611 | X150: =B150-D150 -> -2.766012 | Z150: =AVERAGE(W150:W155) -> 19.62093 | AA150: =AVERAGE(X150:X155) -> 2.7624128
... A188: 40390 | B188: 11.866384 | C188: -8.2090476 | D188: 1.54 | E188: 衰退 | F188: 紧货币紧信用 | H188: 被动补库存 | I188: 产能周期上行,被动补库存 | W188: =B188+C188 -> 3.6573367 | X188: =B188-D188 -> 10.326384 | Z188: =AVERAGE(W188:W193) -> -7.9847587 | AA188: =AVERAGE(X188:X193) -> -2.5706242
A189: 40359 | B189: -7.6506119 | C189: 5.8210476 | D189: -0.54 | E189: 衰退 | F189: 紧货币紧信用 | H189: 被动补库存 | I189: 产能周期上行,被动补库存 | W189: =B189+C189 -> -1.8295643 | X189: =B189-D189 -> -7.1106119 | Z189: =AVERAGE(W184:W193) -> 2.8981634 | AA189: =AVERAGE(X184:X193) -> -0.71744677
A190: 40329 | B190: -8.3030861 | C190: -19.166286 | D190: -0.19 | E190: 滞涨 | F190: 紧货币紧信用 | H190: 主动去库存 | I190: 产能周期上行,被动补库存 | W190: =B190+C190 -> -27.469372 | X190: =B190-D190 -> -8.1130861 | Z190: =AVERAGE(W184:W193) -> 2.8981634 | AA190: =AVERAGE(X184:X193) -> -0.71744677
A191: 40298 | B191: -7.6926723 | C191: 4.5855901 | D191: 0.37 | E191: 滞涨 | F191: 紧货币紧信用 | H191: 主动去库存 | I191: 产能周期上行,被动补库存 | W191: =B191+C191 -> -3.1070822 | X191: =B191-D191 -> -8.0626723 | Z191: =AVERAGE(W184:W193) -> 2.8981634 | AA191: =AVERAGE(X184:X193) -> -0.71744677
A192: 40268 | B192: 2.5550185 | C192: -15.325701 | D192: 1.36 | E192: 滞涨 | F192: 紧货币紧信用 | H192: 主动去库存 | I192: 产能周期上行,被动补库存 | W192: =B192+C192 -> -12.770683 | X192: =B192-D192 -> 1.1950185 | Z192: =AVERAGE(W184:W193) -> 2.8981634 | AA192: =AVERAGE(X184:X193) -> -0.71744677
A193: 40237 | B193: -2.8687777 | C193: -3.5204102 | D193: 0.79 | E193: 过热 | F193: 紧货币紧信用 | H193: 主动去库存 | I193: 产能周期上行,被动补库存 | W193: =B193+C193 -> -6.3891878 | X193: =B193-D193 -> -3.6587777 | Z193: =AVERAGE(W184:W193) -> 2.8981634 | AA193: =AVERAGE(X184:X193) -> -0.71744677

Sheet 主要指标对比
M1: 月度测算 | N1: 根据GDP季度同比公布值修正后的月度GDP同比 | Q1: =[1]!edb() -> Wind | U1: =[1]!edb() -> Wind
L2: =IFERROR(EOMONTH(M2,0),EOMONTH(L3,-1)) -> 43890 | M2: 2020年1-2月 | N2: -10.665053 | Q2: 指标名称 | R2: 中国:GDP:平减指数:初步核算:当季同比 | U2: 指标名称 | V2: 中国:CPI:当月同比:*0.6+中国:PPI:全部工业品:当月同比:*0.4 | W2: 中国综合PMI:产出指数
B3: 综合景气指标(向前滚动5年、右轴) | C3: 月度GDP同比 | D3: 综合通胀（逆序） | E3: 综合PMI | F3: GDP平减指数（逆序） | G3: 综合PMI（近半年平均） | L3: =IFERROR(EOMONTH(M3,0),EOMONTH(L4,-1)) -> 43921 | M3: 43891 | N3: -4.1064704 | Q3: 单位 | R3: % | U3: 单位 | W3: %
L4: =IFERROR(EOMONTH(M4,0),EOMONTH(L5,-1)) -> 43951 | M4: 43922 | N4: 2.0680994 | Q4: 更新时间 | R4: 2026-01-19 | U4: 更新时间 | V4: 2026-01-09 | W4: 2025-12-31
A5: 45688 | B5: =VLOOKUP($A5,'框架指示的股债胜率（综合）'!$A:$Y,COLUMN(Y$1),0) -> -1.4195336 | C5: =IFERROR(VLOOKUP(A5,L:N,3,0),#REF!) -> 0 | D5: =VLOOKUP(A5,U:W,2,0) -> -0.62 | E5: =VLOOKUP(A5,U:W,3,0) -> 50.1 | F5: =VLOOKUP(A5,Q:R,2,0) -> #N/A | G5: =AVERAGE(E5:E10) -> 50.733333 | L5: =IFERROR(EOMONTH(M5,0),EOMONTH(L6,-1)) -> 43982 | M5: 43952 | N5: 4.2828557 | Q5: 46022 | R5: -0.6742 | U5: 46022 | V5: -0.28 | W5: 50.7
A6: 45657 | B6: =VLOOKUP($A6,'框架指示的股债胜率（综合）'!$A:$Y,COLUMN(Y$1),0) -> -1.7174815 | C6: =IFERROR(VLOOKUP(A6,L:N,3,0),C5) -> 0 | D6: =VLOOKUP(A6,U:W,2,0) -> -0.86 | E6: =VLOOKUP(A6,U:W,3,0) -> 52.2 | F6: =VLOOKUP(A6,Q:R,2,0) -> 1.9227 | G6: =AVERAGE(E6:E11) -> 50.75 | L6: =IFERROR(EOMONTH(M6,0),EOMONTH(L7,-1)) -> 44012 | M6: 43983 | N6: 4.7057633 | Q6: 45930 | R6: 1.608 | U6: 45991 | V6: -0.46 | W6: 49.7
A7: 45626 | B7: =VLOOKUP($A7,'框架指示的股债胜率（综合）'!$A:$Y,COLUMN(Y$1),0) -> -2.0424001 | C7: =IFERROR(VLOOKUP(A7,L:N,3,0),C6) -> 0 | D7: =VLOOKUP(A7,U:W,2,0) -> -0.88 | E7: =VLOOKUP(A7,U:W,3,0) -> 50.8 | F7: =VLOOKUP(A7,Q:R,2,0) -> #N/A | G7: =AVERAGE(E7:E12) -> 50.466667 | L7: =IFERROR(EOMONTH(M7,0),EOMONTH(L8,-1)) -> 44043 | M7: 44013 | N7: 4.4697385 | Q7: 45838 | R7: 1.3562 | U7: 45961 | V7: -0.72 | W7: 50
A8: 45596 | B8: =VLOOKUP($A8,'框架指示的股债胜率（综合）'!$A:$Y,COLUMN(Y$1),0) -> -2.3084846 | C8: =IFERROR(VLOOKUP(A8,L:N,3,0),C7) -> 0 | D8: =VLOOKUP(A8,U:W,2,0) -> -0.98 | E8: =VLOOKUP(A8,U:W,3,0) -> 50.8 | F8: =VLOOKUP(A8,Q:R,2,0) -> #N/A | G8: =AVERAGE(E8:E13) -> 50.5 | L8: =IFERROR(EOMONTH(M8,0),EOMONTH(L9,-1)) -> 44074 | M8: 44044 | N8: 4.8779771 | Q8: 45747 | R8: 2.0682 | U8: 45930 | V8: -1.1 | W8: 50.6
A9: 45565 | B9: =VLOOKUP($A9,'框架指示的股债胜率（综合）'!$A:$Y,COLUMN(Y$1),0) -> -2.5968375 | C9: =IFERROR(VLOOKUP(A9,L:N,3,0),#REF!) -> 0 | D9: =VLOOKUP(A9,U:W,2,0) -> -0.88 | E9: =VLOOKUP(A9,U:W,3,0) -> 50.4 | F9: =VLOOKUP(A9,Q:R,2,0) -> -0.5334 | G9: =AVERAGE(E9:E14) -> 50.65 | L9: =IFERROR(EOMONTH(M9,0),EOMONTH(L10,-1)) -> 44104 | M9: 44075 | N9: 5.6485673 | Q9: 45657 | R9: 1.9227 | U9: 45900 | V9: -1.4 | W9: 50.5
A10: 45535 | B10: =VLOOKUP($A10,'框架指示的股债胜率（综合）'!$A:$Y,COLUMN(Y$1),0) -> -2.6485948 | C10: =IFERROR(VLOOKUP(A10,L:N,3,0),C9) -> 0 | D10: =VLOOKUP(A10,U:W,2,0) -> -0.36 | E10: =VLOOKUP(A10,U:W,3,0) -> 50.1 | F10: =VLOOKUP(A10,Q:R,2,0) -> #N/A | G10: =AVERAGE(E10:E15) -> 51.033333 | L10: =IFERROR(EOMONTH(M10,0),EOMONTH(L11,-1)) -> 44135 | M10: 44105 | N10: 6.5669251 | Q10: 45565 | R10: -0.5334 | U10: 45869 | V10: -1.44 | W10: 50.2
A11: 45504 | B11: =VLOOKUP($A11,'框架指示的股债胜率（综合）'!$A:$Y,COLUMN(Y$1),0) -> -2.2078799 | C11: =IFERROR(VLOOKUP(A11,L:N,3,0),C10) -> 0 | D11: =VLOOKUP(A11,U:W,2,0) -> -0.02 | E11: =VLOOKUP(A11,U:W,3,0) -> 50.2 | F11: =VLOOKUP(A11,Q:R,2,0) -> #N/A | G11: =AVERAGE(E11:E16) -> 51.166667 | L11: =IFERROR(EOMONTH(M11,0),EOMONTH(L12,-1)) -> 44165 | M11: 44136 | N11: 6.678227 | Q11: 45473 | R11: -0.6135 | U11: 45838 | V11: -1.38 | W11: 50.7
A12: 45473 | B12: =VLOOKUP($A12,'框架指示的股债胜率（综合）'!$A:$Y,COLUMN(Y$1),0) -> -2.0208268 | C12: =IFERROR(VLOOKUP(A12,L:N,3,0),C11) -> 0 | D12: =VLOOKUP(A12,U:W,2,0) -> -0.2 | E12: =VLOOKUP(A12,U:W,3,0) -> 50.5 | F12: =VLOOKUP(A12,Q:R,2,0) -> -0.6135 | G12: =AVERAGE(E12:E17) -> 51.183333 | L12: =IFERROR(EOMONTH(M12,0),EOMONTH(L13,-1)) -> 44196 | M12: 44166 | N12: 6.4859039 | Q12: 45382 | R12: -1.2672 | U12: 45808 | V12: -1.38 | W12: 50.4
A13: 45443 | B13: =VLOOKUP($A13,'框架指示的股债胜率（综合）'!$A:$Y,COLUMN(Y$1),0) -> -1.849816 | C13: =IFERROR(VLOOKUP(A13,L:N,3,0),C4) -> 4.8086568 | D13: =VLOOKUP(A13,U:W,2,0) -> -0.38 | E13: =VLOOKUP(A13,U:W,3,0) -> 51 | F13: =VLOOKUP(A13,Q:R,2,0) -> #N/A | G13: =AVERAGE(E13:E18) -> 51.166667 | L13: =IFERROR(EOMONTH(M13,0),EOMONTH(L14,-1)) -> 44255 | M13: 2021年1-2月 | N13: 24.321076 | Q13: 45291 | R13: -1.4349 | U13: 45777 | V13: -1.14 | W13: 50.2
A14: 45412 | B14: =VLOOKUP($A14,'框架指示的股债胜率（综合）'!$A:$Y,COLUMN(Y$1),0) -> -1.6840842 | C14: =IFERROR(VLOOKUP(A14,L:N,3,0),C13) -> 4.9271528 | D14: =VLOOKUP(A14,U:W,2,0) -> -0.82 | E14: =VLOOKUP(A14,U:W,3,0) -> 51.7 | F14: =VLOOKUP(A14,Q:R,2,0) -> #N/A | G14: =AVERAGE(E14:E19) -> 51.116667 | L14: =IFERROR(EOMONTH(M14,0),EOMONTH(L15,-1)) -> 44286 | M14: 44256 | N14: 14.315768 | Q14: 45199 | R14: -0.8394 | U14: 45747 | V14: -1.06 | W14: 51.4
A15: 45382 | B15: =VLOOKUP($A15,'框架指示的股债胜率（综合）'!$A:$Y,COLUMN(Y$1),0) -> -1.2461303 | C15: =IFERROR(VLOOKUP(A15,L:N,3,0),C14) -> 4.7760786 | D15: =VLOOKUP(A15,U:W,2,0) -> -1.06 | E15: =VLOOKUP(A15,U:W,3,0) -> 52.7 | F15: =VLOOKUP(A15,Q:R,2,0) -> -1.2672 | G15: =AVERAGE(E15:E20) -> 51.166667 | L15: =IFERROR(EOMONTH(M15,0),EOMONTH(L16,-1)) -> 44316 | M15: 44287 | N15: 9.5153255 | Q15: 45107 | R15: -0.9171 | U15: 45716 | V15: -1.3 | W15: 51.1
A16: 45351 | B16: =VLOOKUP($A16,'框架指示的股债胜率（综合）'!$A:$Y,COLUMN(Y$1),0) -> -0.86496174 | C16: =IFERROR(VLOOKUP(A16,L:N,3,0),C15) -> 5.7826379 | D16: =VLOOKUP(A16,U:W,2,0) -> -0.66 | E16: =VLOOKUP(A16,U:W,3,0) -> 50.9 | F16: =VLOOKUP(A16,Q:R,2,0) -> #N/A | G16: =AVERAGE(E16:E21) -> 50.933333 | L16: =IFERROR(EOMONTH(M16,0),EOMONTH(L17,-1)) -> 44347 | M16: 44317 | N16: 6.951965 | Q16: 45016 | R16: 0.9425 | U16: 45688 | V16: -0.62 | W16: 50.1
A17: 45291 | B17: =VLOOKUP($A17,'框架指示的股债胜率（综合）'!$A:$Y,COLUMN(Y$1),0) -> -0.77144221 | C17: =IFERROR(VLOOKUP(A17,L:N,3,0),C16) -> 5.7064248 | D17: =VLOOKUP(A17,U:W,2,0) -> -1.26 | E17: =VLOOKUP(A17,U:W,3,0) -> 50.3 | F17: =VLOOKUP(A17,Q:R,2,0) -> -1.4349 | G17: =AVERAGE(E17:E22) -> 50.966667 | L17: =IFERROR(EOMONTH(M17,0),EOMONTH(L18,-1)) -> 44377 | M17: 44348 | N17: 6.3028357 | Q17: 44926 | R17: 0.5599 | U17: 45657 | V17: -0.86 | W17: 52.2
A18: 45260 | B18: =VLOOKUP($A18,'框架指示的股债胜率（综合）'!$A:$Y,COLUMN(Y$1),0) -> -0.79189289 | C18: =IFERROR(VLOOKUP(A18,L:N,3,0),C17) -> 5.539915 | D18: =VLOOKUP(A18,U:W,2,0) -> -1.5 | E18: =VLOOKUP(A18,U:W,3,0) -> 50.4 | F18: =VLOOKUP(A18,Q:R,2,0) -> #N/A | G18: =AVERAGE(E18:E23) -> 51.3 | L18: =IFERROR(EOMONTH(M18,0),EOMONTH(L19,-1)) -> 44408 | M18: 44378 | N18: 5.8597592 | Q18: 44834 | R18: 1.7583 | U18: 45626 | V18: -0.88 | W18: 50.8
A19: 45230 | B19: =VLOOKUP($A19,'框架指示的股债胜率（综合）'!$A:$Y,COLUMN(Y$1),0) -> -0.64542371 | C19: =IFERROR(VLOOKUP(A19,L:N,3,0),C18) -> 4.3643494 | D19: =VLOOKUP(A19,U:W,2,0) -> -1.16 | E19: =VLOOKUP(A19,U:W,3,0) -> 50.7 | F19: =VLOOKUP(A19,Q:R,2,0) -> #N/A | G19: =AVERAGE(E19:E24) -> 51.716667 | L19: =IFERROR(EOMONTH(M19,0),EOMONTH(L20,-1)) -> 44439 | M19: 44409 | N19: 4.6953913 | Q19: 44742 | R19: 2.9845 | U19: 45596 | V19: -0.98 | W19: 50.8
A20: 45199 | B20: =VLOOKUP($A20,'框架指示的股债胜率（综合）'!$A:$Y,COLUMN(Y$1),0) -> -0.3905104 | C20: =IFERROR(VLOOKUP(A20,L:N,3,0),C19) -> 5.1888546 | D20: =VLOOKUP(A20,U:W,2,0) -> -1 | E20: =VLOOKUP(A20,U:W,3,0) -> 52 | F20: =VLOOKUP(A20,Q:R,2,0) -> -0.8394 | G20: =AVERAGE(E20:E25) -> 52.333333 | L20: =IFERROR(EOMONTH(M20,0),EOMONTH(L21,-1)) -> 44469 | M20: 44440 | N20: 3.9746123 | Q20: 44651 | R20: 3.4068 | U20: 45565 | V20: -0.88 | W20: 50.4
A21: 45169 | B21: =VLOOKUP($A21,'框架指示的股债胜率（综合）'!$A:$Y,COLUMN(Y$1),0) -> -0.40977378 | C21: =IFERROR(VLOOKUP(A21,L:N,3,0),C20) -> 5.1282424 | D21: =VLOOKUP(A21,U:W,2,0) -> -1.14 | E21: =VLOOKUP(A21,U:W,3,0) -> 51.3 | F21: =VLOOKUP(A21,Q:R,2,0) -> #N/A | G21: =AVERAGE(E21:E26) -> 53.166667 | L21: =IFERROR(EOMONTH(M21,0),EOMONTH(L22,-1)) -> 44500 | M21: 44470 | N21: 4.1648011 | Q21: 44561 | R21: 5.2205 | U21: 45535 | V21: -0.36 | W21: 50.1
A22: 45138 | B22: =VLOOKUP($A22,'框架指示的股债胜率（综合）'!$A:$Y,COLUMN(Y$1),0) -> -0.44441918 | C22: =IFERROR(VLOOKUP(A22,L:N,3,0),C21) -> 4.393244 | D22: =VLOOKUP(A22,U:W,2,0) -> -1.94 | E22: =VLOOKUP(A22,U:W,3,0) -> 51.1 | F22: =VLOOKUP(A22,Q:R,2,0) -> #N/A | G22: =AVERAGE(E22:E27) -> 54.016667 | L22: =IFERROR(EOMONTH(M22,0),EOMONTH(L23,-1)) -> 44530 | M22: 44501 | N22: 3.9285937 | Q22: 44469 | R22: 4.2081 | U22: 45504 | V22: -0.02 | W22: 50.2
A23: 45107 | B23: =VLOOKUP($A23,'框架指示的股债胜率（综合）'!$A:$Y,COLUMN(Y$1),0) -> -0.58278608 | C23: =IFERROR(VLOOKUP(A23,L:N,3,0),C22) -> 5.2278401 | D23: =VLOOKUP(A23,U:W,2,0) -> -2.16 | E23: =VLOOKUP(A23,U:W,3,0) -> 52.3 | F23: =VLOOKUP(A23,Q:R,2,0) -> -0.9171 | G23: =AVERAGE(E23:E28) -> 52.6 | L23: =IFERROR(EOMONTH(M23,0),EOMONTH(L24,-1)) -> 44561 | M23: 44531 | N23: 4.3979261 | Q23: 44377 | R23: 4.8128 | U23: 45473 | V23: -0.2 | W23: 50.5
A24: 45077 | B24: =VLOOKUP($A24,'框架指示的股债胜率（综合）'!$A:$Y,COLUMN(Y$1),0) -> -0.66536142 | C24: =IFERROR(VLOOKUP(A24,L:N,3,0),C23) -> 6.22163 | D24: =VLOOKUP(A24,U:W,2,0) -> -1.72 | E24: =VLOOKUP(A24,U:W,3,0) -> 52.9 | F24: =VLOOKUP(A24,Q:R,2,0) -> #N/A | G24: =AVERAGE(E24:E29) -> 51.733333 | L24: =IFERROR(EOMONTH(M24,0),EOMONTH(L25,-1)) -> 44620 | M24: 2022年1-2月 | N24: 5.9578912 | Q24: 44286 | R24: 2.0532 | U24: 45443 | V24: -0.38 | W24: 51
A25: 45046 | B25: =VLOOKUP($A25,'框架指示的股债胜率（综合）'!$A:$Y,COLUMN(Y$1),0) -> -0.80832807 | C25: =IFERROR(VLOOKUP(A25,L:N,3,0),C24) -> 7.5436626 | D25: =VLOOKUP(A25,U:W,2,0) -> -1.38 | E25: =VLOOKUP(A25,U:W,3,0) -> 54.4 | F25: =VLOOKUP(A25,Q:R,2,0) -> #N/A | G25: =AVERAGE(E25:E30) -> 51.083333 | L25: =IFERROR(EOMONTH(M25,0),EOMONTH(L26,-1)) -> 44651 | M25: 44621 | N25: 3.7003507 | Q25: 44196 | R25: 0.0698 | U25: 45412 | V25: -0.82 | W25: 51.7
A26: 45016 | B26: =VLOOKUP($A26,'框架指示的股债胜率（综合）'!$A:$Y,COLUMN(Y$1),0) -> -0.70828594 | C26: =IFERROR(VLOOKUP(A26,L:N,3,0),C25) -> 5.3201715 | D26: =VLOOKUP(A26,U:W,2,0) -> -0.58 | E26: =VLOOKUP(A26,U:W,3,0) -> 57 | F26: =VLOOKUP(A26,Q:R,2,0) -> 0.9425 | G26: =AVERAGE(E26:E31) -> 50.5 | L26: =IFERROR(EOMONTH(M26,0),EOMONTH(L27,-1)) -> 44681 | M26: 44652 | N26: -1.7769661 | Q26: 44104 | R26: 2.7844 | U26: 45382 | V26: -1.06 | W26: 52.7
A27: 44985 | B27: =VLOOKUP($A27,'框架指示的股债胜率（综合）'!$A:$Y,COLUMN(Y$1),0) -> -0.30840266 | C27: =IFERROR(VLOOKUP(A27,L:N,3,0),C26) -> 3.699512 | D27: =VLOOKUP(A27,U:W,2,0) -> 0.04 | E27: =VLOOKUP(A27,U:W,3,0) -> 56.4 | F27: =VLOOKUP(A27,Q:R,2,0) -> #N/A | G27: =AVERAGE(E27:E32) -> 49.616667 | L27: =IFERROR(EOMONTH(M27,0),EOMONTH(L28,-1)) -> 44712 | M27: 44682 | N27: -0.068426302 | Q27: 44012 | R27: 2.0441 | U27: 45351 | V27: -0.66 | W27: 50.9
A28: 44926 | B28: =VLOOKUP($A28,'框架指示的股债胜率（综合）'!$A:$Y,COLUMN(Y$1),0) -> -0.10910294 | C28: =IFERROR(VLOOKUP(A28,L:N,3,0),C27) -> 2.5729369 | D28: =VLOOKUP(A28,U:W,2,0) -> 0.8 | E28: =VLOOKUP(A28,U:W,3,0) -> 42.6 | F28: =VLOOKUP(A28,Q:R,2,0) -> 0.5599 | G28: =AVERAGE(E28:E33) -> 48.966667 | L28: =IFERROR(EOMONTH(M28,0),EOMONTH(L29,-1)) -> 44742 | M28: 44713 | N28: 3.142974 | Q28: 43921 | R28: 3.8128 | U28: 45322 | V28: -1.48 | W28: 50.9
A29: 44895 | B29: =VLOOKUP($A29,'框架指示的股债胜率（综合）'!$A:$Y,COLUMN(Y$1),0) -> -0.18593988 | C29: =IFERROR(VLOOKUP(A29,L:N,3,0),C28) -> 2.2579905 | D29: =VLOOKUP(A29,U:W,2,0) -> 0.44 | E29: =VLOOKUP(A29,U:W,3,0) -> 47.1 | F29: =VLOOKUP(A29,Q:R,2,0) -> #N/A | G29: =AVERAGE(E29:E34) -> 50.883333 | L29: =IFERROR(EOMONTH(M29,0),EOMONTH(L30,-1)) -> 44773 | M29: 44743 | N29: 3.2213079 | Q29: 43830 | R29: 3.4243 | U29: 45291 | V29: -1.26 | W29: 50.3
A30: 44865 | B30: =VLOOKUP($A30,'框架指示的股债胜率（综合）'!$A:$Y,COLUMN(Y$1),0) -> -0.22302937 | C30: =IFERROR(VLOOKUP(A30,L:N,3,0),C29) -> 3.9399728 | D30: =VLOOKUP(A30,U:W,2,0) -> 0.74 | E30: =VLOOKUP(A30,U:W,3,0) -> 49 | F30: =VLOOKUP(A30,Q:R,2,0) -> #N/A | G30: =AVERAGE(E30:E35) -> 51.1 | L30: =IFERROR(EOMONTH(M30,0),EOMONTH(L31,-1)) -> 44804 | M30: 44774 | N30: 3.8448335 | Q30: 43738 | R30: 0.4111 | U30: 45260 | V30: -1.5 | W30: 50.4
A31: 44834 | B31: =VLOOKUP($A31,'框架指示的股债胜率（综合）'!$A:$Y,COLUMN(Y$1),0) -> -0.32728794 | C31: =IFERROR(VLOOKUP(A31,L:N,3,0),C30) -> 4.5266995 | D31: =VLOOKUP(A31,U:W,2,0) -> 2.04 | E31: =VLOOKUP(A31,U:W,3,0) -> 50.9 | F31: =VLOOKUP(A31,Q:R,2,0) -> 1.7583 | G31: =AVERAGE(E31:E36) -> 50.05 | L31: =IFERROR(EOMONTH(M31,0),EOMONTH(L32,-1)) -> 44834 | M31: 44805 | N31: 4.5266995 | Q31: 43646 | R31: 1.5699 | U31: 45230 | V31: -1.16 | W31: 50.7
A32: 44804 | B32: =VLOOKUP($A32,'框架指示的股债胜率（综合）'!$A:$Y,COLUMN(Y$1),0) -> -0.80717248 | C32: =IFERROR(VLOOKUP(A32,L:N,3,0),C31) -> 3.8448335 | D32: =VLOOKUP(A32,U:W,2,0) -> 2.42 | E32: =VLOOKUP(A32,U:W,3,0) -> 51.7 | F32: =VLOOKUP(A32,Q:R,2,0) -> #N/A | G32: =AVERAGE(E32:E37) -> 49.7 | L32: =IFERROR(EOMONTH(M32,0),EOMONTH(L33,-1)) -> 44865 | M32: 44835 | N32: 3.9399728 | Q32: 43555 | R32: 0.9115 | U32: 45199 | V32: -1 | W32: 52
A33: 44773 | B33: =VLOOKUP($A33,'框架指示的股债胜率（综合）'!$A:$Y,COLUMN(Y$1),0) -> -1.4132284 | C33: =IFERROR(VLOOKUP(A33,L:N,3,0),C32) -> 3.2213079 | D33: =VLOOKUP(A33,U:W,2,0) -> 3.3 | E33: =VLOOKUP(A33,U:W,3,0) -> 52.5 | F33: =VLOOKUP(A33,Q:R,2,0) -> #N/A | G33: =AVERAGE(E33:E38) -> 49.616667 | L33: =IFERROR(EOMONTH(M33,0),EOMONTH(L34,-1)) -> 44895 | M33: 44866 | N33: 2.2579905 | Q33: 43465 | R33: 1.6041 | U33: 45169 | V33: -1.14 | W33: 51.3
A34: 44742 | B34: =VLOOKUP($A34,'框架指示的股债胜率（综合）'!$A:$Y,COLUMN(Y$1),0) -> -1.7622183 | C34: =IFERROR(VLOOKUP(A34,L:N,3,0),C33) -> 3.142974 | D34: =VLOOKUP(A34,U:W,2,0) -> 3.94 | E34: =VLOOKUP(A34,U:W,3,0) -> 54.1 | F34: =VLOOKUP(A34,Q:R,2,0) -> 2.9845 | G34: =AVERAGE(E34:E39) -> 49.566667 | L34: =IFERROR(EOMONTH(M34,0),EOMONTH(L35,-1)) -> 44926 | M34: 44896 | N34: 2.5729369 | Q34: 43373 | R34: 2.8254 | U34: 45138 | V34: -1.94 | W34: 51.1
A35: 44712 | B35: =VLOOKUP($A35,'框架指示的股债胜率（综合）'!$A:$Y,COLUMN(Y$1),0) -> -1.7890809 | C35: =IFERROR(VLOOKUP(A35,L:N,3,0),C34) -> -0.068426302 | D35: =VLOOKUP(A35,U:W,2,0) -> 3.82 | E35: =VLOOKUP(A35,U:W,3,0) -> 48.4 | F35: =VLOOKUP(A35,Q:R,2,0) -> #N/A | G35: =AVERAGE(E35:E40) -> 49.25 | L35: =IFERROR(EOMONTH(M35,0),EOMONTH(L36,-1)) -> 44985 | M35: 2023年1-2月 | N35: 3.699512 | Q35: 43281 | R35: 2.7614 | U35: 45107 | V35: -2.16 | W35: 52.3
A36: 44681 | B36: =VLOOKUP($A36,'框架指示的股债胜率（综合）'!$A:$Y,COLUMN(Y$1),0) -> -1.6619965 | C36: =IFERROR(VLOOKUP(A36,L:N,3,0),C35) -> -1.7769661 | D36: =VLOOKUP(A36,U:W,2,0) -> 4.46 | E36: =VLOOKUP(A36,U:W,3,0) -> 42.7 | F36: =VLOOKUP(A36,Q:R,2,0) -> #N/A | G36: =AVERAGE(E36:E41) -> 49.65 | L36: =IFERROR(EOMONTH(M36,0),EOMONTH(L37,-1)) -> 45016 | M36: 44986 | N36: 5.3201715 | Q36: 43190 | R36: 3.0129 | U36: 45077 | V36: -1.72 | W36: 52.9
A37: 44651 | B37: =VLOOKUP($A37,'框架指示的股债胜率（综合）'!$A:$Y,COLUMN(Y$1),0) -> -1.8376983 | C37: =IFERROR(VLOOKUP(A37,L:N,3,0),C36) -> 3.7003507 | D37: =VLOOKUP(A37,U:W,2,0) -> 4.22 | E37: =VLOOKUP(A37,U:W,3,0) -> 48.8 | F37: =VLOOKUP(A37,Q:R,2,0) -> 3.4068 | G37: =AVERAGE(E37:E42) -> 51.15 | L37: =IFERROR(EOMONTH(M37,0),EOMONTH(L38,-1)) -> 45046 | M37: 45017 | N37: 7.5436626 | Q37: 43100 | R37: 3.9591 | U37: 45046 | V37: -1.38 | W37: 54.4
A38: 44620 | B38: =VLOOKUP($A38,'框架指示的股债胜率（综合）'!$A:$Y,COLUMN(Y$1),0) -> -1.7266396 | C38: =IFERROR(VLOOKUP(A38,L:N,3,0),C37) -> 5.9578912 | D38: =VLOOKUP(A38,U:W,2,0) -> 4.06 | E38: =VLOOKUP(A38,U:W,3,0) -> 51.2 | F38: =VLOOKUP(A38,Q:R,2,0) -> #N/A | G38: =AVERAGE(E38:E43) -> 51.166667 | L38: =IFERROR(EOMONTH(M38,0),EOMONTH(L39,-1)) -> 45077 | M38: 45047 | N38: 6.22163 | Q38: 43008 | R38: 4.0851 | U38: 45016 | V38: -0.58 | W38: 57
A39: 44561 | B39: =VLOOKUP($A39,'框架指示的股债胜率（综合）'!$A:$Y,COLUMN(Y$1),0) -> -1.9153258 | C39: =IFERROR(VLOOKUP(A39,L:N,3,0),C38) -> 4.3979261 | D39: =VLOOKUP(A39,U:W,2,0) -> 5.02 | E39: =VLOOKUP(A39,U:W,3,0) -> 52.2 | F39: =VLOOKUP(A39,Q:R,2,0) -> 5.2205 | G39: =AVERAGE(E39:E44) -> 51.366667 | L39: =IFERROR(EOMONTH(M39,0),EOMONTH(L40,-1)) -> 45107 | M39: 45078 | N39: 5.2278401 | Q39: 42916 | R39: 3.9293 | U39: 44985 | V39: 0.04 | W39: 56.4
A40: 44530 | B40: =VLOOKUP($A40,'框架指示的股债胜率（综合）'!$A:$Y,COLUMN(Y$1),0) -> -2.1126322 | C40: =IFERROR(VLOOKUP(A40,L:N,3,0),C39) -> 3.9285937 | D40: =VLOOKUP(A40,U:W,2,0) -> 6.54 | E40: =VLOOKUP(A40,U:W,3,0) -> 52.2 | F40: =VLOOKUP(A40,Q:R,2,0) -> #N/A | G40: =AVERAGE(E40:E45) -> 51.483333 | L40: =IFERROR(EOMONTH(M40,0),EOMONTH(L41,-1)) -> 45138 | M40: 45108 | N40: 4.393244 | Q40: 42825 | R40: 4.6096 | U40: 44957 | V40: 0.94 | W40: 52.9
A41: 44500 | B41: =VLOOKUP($A41,'框架指示的股债胜率（综合）'!$A:$Y,COLUMN(Y$1),0) -> -2.2571608 | C41: =IFERROR(VLOOKUP(A41,L:N,3,0),C40) -> 4.1648011 | D41: =VLOOKUP(A41,U:W,2,0) -> 6.3 | E41: =VLOOKUP(A41,U:W,3,0) -> 50.8 | F41: =VLOOKUP(A41,Q:R,2,0) -> #N/A | G41: =AVERAGE(E41:E46) -> 51.816667 | L41: =IFERROR(EOMONTH(M41,0),EOMONTH(L42,-1)) -> 45169 | M41: 45139 | N41: 5.1282424 | Q41: 42735 | R41: 2.5808 | U41: 44926 | V41: 0.8 | W41: 42.6
A42: 44469 | B42: =VLOOKUP($A42,'框架指示的股债胜率（综合）'!$A:$Y,COLUMN(Y$1),0) -> -2.4441491 | C42: =IFERROR(VLOOKUP(A42,L:N,3,0),C41) -> 3.9746123 | D42: =VLOOKUP(A42,U:W,2,0) -> 4.7 | E42: =VLOOKUP(A42,U:W,3,0) -> 51.7 | F42: =VLOOKUP(A42,Q:R,2,0) -> 4.2081 | G42: =AVERAGE(E42:E47) -> 52.316667 | L42: =IFERROR(EOMONTH(M42,0),EOMONTH(L43,-1)) -> 45199 | M42: 45170 | N42: 5.1888546 | Q42: 42643 | R42: 1.0499 | U42: 44895 | V42: 0.44 | W42: 47.1
A43: 44439 | B43: =VLOOKUP($A43,'框架指示的股债胜率（综合）'!$A:$Y,COLUMN(Y$1),0) -> -2.2880819 | C43: =IFERROR(VLOOKUP(A43,L:N,3,0),C42) -> 4.6953913 | D43: =VLOOKUP(A43,U:W,2,0) -> 4.28 | E43: =VLOOKUP(A43,U:W,3,0) -> 48.9 | F43: =VLOOKUP(A43,Q:R,2,0) -> #N/A | G43: =AVERAGE(E43:E48) -> 52.916667 | L43: =IFERROR(EOMONTH(M43,0),EOMONTH(L44,-1)) -> 45230 | M43: 45200 | N43: 4.3643494 | Q43: 42551 | R43: 0.5832 | U43: 44865 | V43: 0.74 | W43: 49
A44: 44408 | B44: =VLOOKUP($A44,'框架指示的股债胜率（综合）'!$A:$Y,COLUMN(Y$1),0) -> -1.860973 | C44: =IFERROR(VLOOKUP(A44,L:N,3,0),C43) -> 5.8597592 | D44: =VLOOKUP(A44,U:W,2,0) -> 4.2 | E44: =VLOOKUP(A44,U:W,3,0) -> 52.4 | F44: =VLOOKUP(A44,Q:R,2,0) -> #N/A | G44: =AVERAGE(E44:E49) -> 53.366667 | L44: =IFERROR(EOMONTH(M44,0),EOMONTH(L45,-1)) -> 45260 | M44: 45231 | N44: 5.539915 | Q44: 42460 | R44: 0.2917 | U44: 44834 | V44: 2.04 | W44: 50.9
A45: 44377 | B45: =VLOOKUP($A45,'框架指示的股债胜率（综合）'!$A:$Y,COLUMN(Y$1),0) -> -1.328992 | C45: =IFERROR(VLOOKUP(A45,L:N,3,0),C44) -> 6.3028357 | D45: =VLOOKUP(A45,U:W,2,0) -> 4.18 | E45: =VLOOKUP(A45,U:W,3,0) -> 52.9 | F45: =VLOOKUP(A45,Q:R,2,0) -> 4.8128 | G45: =AVERAGE(E45:E50) -> 53.816667 | L45: =IFERROR(EOMONTH(M45,0),EOMONTH(L46,-1)) -> 45291 | M45: 45261 | N45: 5.7064248 | Q45: 42369 | R45: -0.3364 | U45: 44804 | V45: 2.42 | W45: 51.7
A46: 44347 | B46: =VLOOKUP($A46,'框架指示的股债胜率（综合）'!$A:$Y,COLUMN(Y$1),0) -> -0.64556121 | C46: =IFERROR(VLOOKUP(A46,L:N,3,0),C45) -> 6.951965 | D46: =VLOOKUP(A46,U:W,2,0) -> 4.38 | E46: =VLOOKUP(A46,U:W,3,0) -> 54.2 | F46: =VLOOKUP(A46,Q:R,2,0) -> #N/A | G46: =AVERAGE(E46:E51) -> 54.283333 | L46: =IFERROR(EOMONTH(M46,0),EOMONTH(L47,-1)) -> 45351 | M46: 45323 | N46: 5.7826379 | Q46: 42277 | R46: -0.8637 | U46: 44773 | V46: 3.3 | W46: 52.5
A47: 44316 | B47: =VLOOKUP($A47,'框架指示的股债胜率（综合）'!$A:$Y,COLUMN(Y$1),0) -> 0.075269459 | C47: =IFERROR(VLOOKUP(A47,L:N,3,0),C46) -> 9.5153255 | D47: =VLOOKUP(A47,U:W,2,0) -> 3.26 | E47: =VLOOKUP(A47,U:W,3,0) -> 53.8 | F47: =VLOOKUP(A47,Q:R,2,0) -> #N/A | G47: =AVERAGE(E47:E52) -> 54.466667 | L47: =IFERROR(EOMONTH(M47,0),EOMONTH(L48,-1)) -> 45382 | M47: 45352 | N47: 4.7760786 | Q47: 42185 | R47: 0.1419 | U47: 44742 | V47: 3.94 | W47: 54.1
... A49: 44255 | B49: =VLOOKUP($A49,'框架指示的股债胜率（综合）'!$A:$Y,COLUMN(Y$1),0) -> 0.99577893 | C49: =IFERROR(VLOOKUP(A49,L:N,3,0),C48) -> 24.321076 | D49: =VLOOKUP(A49,U:W,2,0) -> 0.56 | E49: =VLOOKUP(A49,U:W,3,0) -> 51.6 | F49: =VLOOKUP(A49,Q:R,2,0) -> #N/A | G49: =AVERAGE(E49:E54) -> 54.55 | L49: =IFERROR(EOMONTH(M49,0),EOMONTH(L50,-1)) -> 45443 | M49: 45413 | N49: 4.8086568 | Q49: 42004 | R49: 0.2303 | U49: 44681 | V49: 4.46 | W49: 42.7
A50: 44196 | B50: =VLOOKUP($A50,'框架指示的股债胜率（综合）'!$A:$Y,COLUMN(Y$1),0) -> 0.8490013 | C50: =IFERROR(VLOOKUP(A50,L:N,3,0),C49) -> 6.4859039 | D50: =VLOOKUP(A50,U:W,2,0) -> -0.04 | E50: =VLOOKUP(A50,U:W,3,0) -> 55.1 | F50: =VLOOKUP(A50,Q:R,2,0) -> 0.0698 | G50: =AVERAGE(E50:E55) -> 54.966667 | L50: =IFERROR(EOMONTH(M50,0),EOMONTH(L51,-1)) -> 45473 | M50: 45444 | Q50: 41912 | R50: 1.191 | U50: 44651 | V50: 4.22 | W50: 48.8
A51: 44165 | B51: =VLOOKUP($A51,'框架指示的股债胜率（综合）'!$A:$Y,COLUMN(Y$1),0) -> 0.74506042 | C51: =IFERROR(VLOOKUP(A51,L:N,3,0),C50) -> 6.678227 | D51: =VLOOKUP(A51,U:W,2,0) -> -0.9 | E51: =VLOOKUP(A51,U:W,3,0) -> 55.7 | F51: =VLOOKUP(A51,Q:R,2,0) -> #N/A | G51: =AVERAGE(E51:E56) -> 54.816667 | L51: =IFERROR(EOMONTH(M51,0),EOMONTH(L52,-1)) -> 45504 | M51: 45474 | Q51: 41820 | R51: 1.0964 | U51: 44620 | V51: 4.06 | W51: 51.2
A52: 44135 | B52: =VLOOKUP($A52,'框架指示的股债胜率（综合）'!$A:$Y,COLUMN(Y$1),0) -> 0.54955651 | C52: =IFERROR(VLOOKUP(A52,L:N,3,0),C51) -> 6.5669251 | D52: =VLOOKUP(A52,U:W,2,0) -> -0.54 | E52: =VLOOKUP(A52,U:W,3,0) -> 55.3 | F52: =VLOOKUP(A52,Q:R,2,0) -> #N/A | G52: =AVERAGE(E52:E57) -> 54.433333 | L52: =IFERROR(EOMONTH(M52,0),EOMONTH(L53,-1)) -> 45535 | M52: 45505 | Q52: 41729 | R52: 0.9114 | U52: 44592 | V52: 4.18 | W52: 51
A53: 44104 | B53: =VLOOKUP($A53,'框架指示的股债胜率（综合）'!$A:$Y,COLUMN(Y$1),0) -> 0.48898768 | C53: =IFERROR(VLOOKUP(A53,L:N,3,0),C52) -> 5.6485673 | D53: =VLOOKUP(A53,U:W,2,0) -> 0.18 | E53: =VLOOKUP(A53,U:W,3,0) -> 55.1 | F53: =VLOOKUP(A53,Q:R,2,0) -> 2.7844 | G53: =AVERAGE(E53:E58) -> 54.116667 | L53: =IFERROR(EOMONTH(M53,0),EOMONTH(L54,-1)) -> 45565 | M53: 45536 | Q53: 41639 | R53: 2.6893 | U53: 44561 | V53: 5.02 | W53: 52.2
A54: 44074 | B54: =VLOOKUP($A54,'框架指示的股债胜率（综合）'!$A:$Y,COLUMN(Y$1),0) -> 0.49608079 | C54: =IFERROR(VLOOKUP(A54,L:N,3,0),C53) -> 4.8779771 | D54: =VLOOKUP(A54,U:W,2,0) -> 0.64 | E54: =VLOOKUP(A54,U:W,3,0) -> 54.5 | F54: =VLOOKUP(A54,Q:R,2,0) -> #N/A | G54: =AVERAGE(E54:E59) -> 53.766667 | L54: =IFERROR(EOMONTH(M54,0),EOMONTH(L55,-1)) -> 45596 | M54: 45566 | Q54: 41547 | R54: 2.2276 | U54: 44530 | V54: 6.54 | W54: 52.2
A55: 44043 | B55: =VLOOKUP($A55,'框架指示的股债胜率（综合）'!$A:$Y,COLUMN(Y$1),0) -> 0.36920805 | C55: =IFERROR(VLOOKUP(A55,L:N,3,0),C54) -> 4.4697385 | D55: =VLOOKUP(A55,U:W,2,0) -> 0.66 | E55: =VLOOKUP(A55,U:W,3,0) -> 54.1 | F55: =VLOOKUP(A55,Q:R,2,0) -> #N/A | G55: =AVERAGE(E55:E60) -> 49.5 | L55: =IFERROR(EOMONTH(M55,0),EOMONTH(L56,-1)) -> 45626 | M55: 45597 | Q55: 41455 | R55: 1.6068 | U55: 44500 | V55: 6.3 | W55: 50.8
A56: 44012 | B56: =VLOOKUP($A56,'框架指示的股债胜率（综合）'!$A:$Y,COLUMN(Y$1),0) -> 0.35672171 | C56: =IFERROR(VLOOKUP(A56,L:N,3,0),C55) -> 4.7057633 | D56: =VLOOKUP(A56,U:W,2,0) -> 0.3 | E56: =VLOOKUP(A56,U:W,3,0) -> 54.2 | F56: =VLOOKUP(A56,Q:R,2,0) -> 2.0441 | G56: =AVERAGE(E56:E61) -> 49.383333 | L56: =IFERROR(EOMONTH(M56,0),EOMONTH(L57,-1)) -> 45657 | M56: 45627 | Q56: 41364 | R56: 2.2565 | U56: 44469 | V56: 4.7 | W56: 51.7
A57: 43982 | B57: =VLOOKUP($A57,'框架指示的股债胜率（综合）'!$A:$Y,COLUMN(Y$1),0) -> 0.34854448 | C57: =IFERROR(VLOOKUP(A57,L:N,3,0),C56) -> 4.2828557 | D57: =VLOOKUP(A57,U:W,2,0) -> -0.04 | E57: =VLOOKUP(A57,U:W,3,0) -> 53.4 | F57: =VLOOKUP(A57,Q:R,2,0) -> #N/A | G57: =AVERAGE(E57:E62) -> 49.3 | L57: =IFERROR(EOMONTH(M57,0),EOMONTH(L58,-1)) -> 45688 | M57: 45658 | Q57: 41274 | R57: 1.8346 | U57: 44439 | V57: 4.28 | W57: 48.9
A58: 43951 | B58: =VLOOKUP($A58,'框架指示的股债胜率（综合）'!$A:$Y,COLUMN(Y$1),0) -> 0.30534694 | C58: =IFERROR(VLOOKUP(A58,L:N,3,0),C57) -> 2.0680994 | D58: =VLOOKUP(A58,U:W,2,0) -> 0.74 | E58: =VLOOKUP(A58,U:W,3,0) -> 53.4 | F58: =VLOOKUP(A58,Q:R,2,0) -> #N/A | G58: =AVERAGE(E58:E63) -> 49.066667 | Q58: 41182 | R58: 1.5508 | U58: 44408 | V58: 4.2 | W58: 52.4
A59: 43921 | B59: =VLOOKUP($A59,'框架指示的股债胜率（综合）'!$A:$Y,COLUMN(Y$1),0) -> 0.15306416 | C59: =IFERROR(VLOOKUP(A59,L:N,3,0),C58) -> -4.1064704 | D59: =VLOOKUP(A59,U:W,2,0) -> 1.98 | E59: =VLOOKUP(A59,U:W,3,0) -> 53 | F59: =VLOOKUP(A59,Q:R,2,0) -> 3.8128 | G59: =AVERAGE(E59:E64) -> 49.016667 | Q59: 41090 | R59: 2.6912 | U59: 44377 | V59: 4.18 | W59: 52.9
A60: 43890 | B60: =VLOOKUP($A60,'框架指示的股债胜率（综合）'!$A:$Y,COLUMN(Y$1),0) -> -0.05217575 | D60: =VLOOKUP(A60,U:W,2,0) -> 2.96 | E60: =VLOOKUP(A60,U:W,3,0) -> 28.9 | F60: =VLOOKUP(A60,Q:R,2,0) -> #N/A | G60: =AVERAGE(E60:E65) -> 49.016667 | Q60: 40999 | R60: 3.9575 | U60: 44347 | V60: 4.38 | W60: 54.2
A61: 43830 | B61: =VLOOKUP($A61,'框架指示的股债胜率（综合）'!$A:$Y,COLUMN(Y$1),0) -> -0.05652741 | D61: =VLOOKUP(A61,U:W,2,0) -> 2.5 | E61: =VLOOKUP(A61,U:W,3,0) -> 53.4 | F61: =VLOOKUP(A61,Q:R,2,0) -> 3.4243 | G61: =AVERAGE(E61:E66) -> 53.05 | Q61: 40908 | R61: 6.401 | U61: 44316 | V61: 3.26 | W61: 53.8
A62: 43799 | B62: =VLOOKUP($A62,'框架指示的股债胜率（综合）'!$A:$Y,COLUMN(Y$1),0) -> -0.065502385 | D62: =VLOOKUP(A62,U:W,2,0) -> 2.14 | E62: =VLOOKUP(A62,U:W,3,0) -> 53.7 | F62: =VLOOKUP(A62,Q:R,2,0) -> #N/A | G62: =AVERAGE(E62:E67) -> 52.983333 | Q62: 40816 | R62: 9.2549 | U62: 44286 | V62: 2 | W62: 55.3
A63: 43769 | B63: =VLOOKUP($A63,'框架指示的股债胜率（综合）'!$A:$Y,COLUMN(Y$1),0) -> -0.063956083 | D63: =VLOOKUP(A63,U:W,2,0) -> 1.64 | E63: =VLOOKUP(A63,U:W,3,0) -> 52 | F63: =VLOOKUP(A63,Q:R,2,0) -> #N/A | G63: =AVERAGE(E63:E68) -> 52.916667 | Q63: 40724 | R63: 8.8493 | U63: 44255 | V63: 0.56 | W63: 51.6
A64: 43738 | B64: =VLOOKUP($A64,'框架指示的股债胜率（综合）'!$A:$Y,COLUMN(Y$1),0) -> -0.05590765 | D64: =VLOOKUP(A64,U:W,2,0) -> 1.32 | E64: =VLOOKUP(A64,U:W,3,0) -> 53.1 | F64: =VLOOKUP(A64,Q:R,2,0) -> 0.4111 | G64: =AVERAGE(E64:E69) -> 53.15 | Q64: 40633 | R64: 8.3764 | U64: 44227 | V64: -0.06 | W64: 52.8
A65: 43708 | B65: =VLOOKUP($A65,'框架指示的股债胜率（综合）'!$A:$Y,COLUMN(Y$1),0) -> -0.1078467 | D65: =VLOOKUP(A65,U:W,2,0) -> 1.36 | E65: =VLOOKUP(A65,U:W,3,0) -> 53 | F65: =VLOOKUP(A65,Q:R,2,0) -> #N/A | G65: =AVERAGE(E65:E70) -> 53.3 | Q65: 40543 | R65: 7.752 | U65: 44196 | V65: -0.04 | W65: 55.1
A66: 43677 | B66: =VLOOKUP($A66,'框架指示的股债胜率（综合）'!$A:$Y,COLUMN(Y$1),0) -> -0.11819857 | D66: =VLOOKUP(A66,U:W,2,0) -> 1.56 | E66: =VLOOKUP(A66,U:W,3,0) -> 53.1 | F66: =VLOOKUP(A66,Q:R,2,0) -> #N/A | G66: =AVERAGE(E66:E71) -> 53.2 | Q66: 40451 | R66: 7.3926 | U66: 44165 | V66: -0.9 | W66: 55.7
A67: 43646 | B67: =VLOOKUP($A67,'框架指示的股债胜率（综合）'!$A:$Y,COLUMN(Y$1),0) -> -0.0012026139 | D67: =VLOOKUP(A67,U:W,2,0) -> 1.62 | E67: =VLOOKUP(A67,U:W,3,0) -> 53 | F67: =VLOOKUP(A67,Q:R,2,0) -> 1.5699 | G67: =AVERAGE(E67:E72) -> 53.116667 | Q67: 40359 | R67: 6.9651 | U67: 44135 | V67: -0.54 | W67: 55.3
A68: 43616 | B68: =VLOOKUP($A68,'框架指示的股债胜率（综合）'!$A:$Y,COLUMN(Y$1),0) -> 0.15096944 | D68: =VLOOKUP(A68,U:W,2,0) -> 1.86 | E68: =VLOOKUP(A68,U:W,3,0) -> 53.3 | F68: =VLOOKUP(A68,Q:R,2,0) -> #N/A | G68: =AVERAGE(E68:E73) -> 53.083333 | Q68: 40268 | R68: 5.451 | U68: 44104 | V68: 0.18 | W68: 55.1
A69: 43585 | B69: =VLOOKUP($A69,'框架指示的股债胜率（综合）'!$A:$Y,COLUMN(Y$1),0) -> 0.22421605 | D69: =VLOOKUP(A69,U:W,2,0) -> 1.86 | E69: =VLOOKUP(A69,U:W,3,0) -> 53.4 | F69: =VLOOKUP(A69,Q:R,2,0) -> #N/A | G69: =AVERAGE(E69:E74) -> 53.05 | Q69: 40178 | R69: 1.6827 | U69: 44074 | V69: 0.64 | W69: 54.5
A70: 43555 | B70: =VLOOKUP($A70,'框架指示的股债胜率（综合）'!$A:$Y,COLUMN(Y$1),0) -> 0.31309164 | D70: =VLOOKUP(A70,U:W,2,0) -> 1.54 | E70: =VLOOKUP(A70,U:W,3,0) -> 54 | F70: =VLOOKUP(A70,Q:R,2,0) -> 0.9115 | G70: =AVERAGE(E70:E75) -> 53.166667 | Q70: 40086 | R70: -1.3991 | U70: 44043 | V70: 0.66 | W70: 54.1
A71: 43524 | B71: =VLOOKUP($A71,'框架指示的股债胜率（综合）'!$A:$Y,COLUMN(Y$1),0) -> 0.50916803 | D71: =VLOOKUP(A71,U:W,2,0) -> 0.94 | E71: =VLOOKUP(A71,U:W,3,0) -> 52.4 | F71: =VLOOKUP(A71,Q:R,2,0) -> #N/A | G71: =AVERAGE(E71:E76) -> 53.133333 | Q71: 39994 | R71: -1.4628 | U71: 44012 | V71: 0.3 | W71: 54.2
... A88: 42947 | B88: =VLOOKUP($A88,'框架指示的股债胜率（综合）'!$A:$Y,COLUMN(Y$1),0) -> 1.4900534 | D88: =VLOOKUP(A88,U:W,2,0) -> 3.04 | E88: =VLOOKUP(A88,U:W,3,0) -> 54.1 | F88: =VLOOKUP(A88,Q:R,2,0) -> #N/A | G88: =AVERAGE(E88:E93) -> 54.25 | Q88: 38442 | R88: 5.4046 | U88: 43496 | V88: 1.06 | W88: 53.2
A89: 42916 | B89: =VLOOKUP($A89,'框架指示的股债胜率（综合）'!$A:$Y,COLUMN(Y$1),0) -> 1.4666616 | D89: =VLOOKUP(A89,U:W,2,0) -> 3.1 | E89: =VLOOKUP(A89,U:W,3,0) -> 54.7 | F89: =VLOOKUP(A89,Q:R,2,0) -> 3.9293 | Q89: 38352 | R89: 8.0266 | U89: 43465 | V89: 1.5 | W89: 52.6
A90: 42886 | B90: =VLOOKUP($A90,'框架指示的股债胜率（综合）'!$A:$Y,COLUMN(Y$1),0) -> 1.3078428 | D90: =VLOOKUP(A90,U:W,2,0) -> 3.1 | E90: =VLOOKUP(A90,U:W,3,0) -> 54.1 | F90: =VLOOKUP(A90,Q:R,2,0) -> #N/A | Q90: 38260 | R90: 8.0115 | U90: 43434 | V90: 2.4 | W90: 52.8
A91: 42855 | B91: =VLOOKUP($A91,'框架指示的股债胜率（综合）'!$A:$Y,COLUMN(Y$1),0) -> 1.1350098 | D91: =VLOOKUP(A91,U:W,2,0) -> 3.28 | E91: =VLOOKUP(A91,U:W,3,0) -> 53.9 | F91: =VLOOKUP(A91,Q:R,2,0) -> #N/A | Q91: 38168 | R91: 6.5796 | U91: 43404 | V91: 2.82 | W91: 53.1
A92: 42825 | B92: =VLOOKUP($A92,'框架指示的股债胜率（综合）'!$A:$Y,COLUMN(Y$1),0) -> 0.95503167 | D92: =VLOOKUP(A92,U:W,2,0) -> 3.58 | E92: =VLOOKUP(A92,U:W,3,0) -> 54.7 | F92: =VLOOKUP(A92,Q:R,2,0) -> 4.6096 | Q92: 38077 | R92: 4.7219 | U92: 43373 | V92: 2.94 | W92: 54.1
A93: 42794 | B93: =VLOOKUP($A93,'框架指示的股债胜率（综合）'!$A:$Y,COLUMN(Y$1),0) -> 0.91551202 | D93: =VLOOKUP(A93,U:W,2,0) -> 3.6 | E93: =VLOOKUP(A93,U:W,3,0) -> 54 | F93: =VLOOKUP(A93,Q:R,2,0) -> #N/A | Q93: 37986 | R93: 3.3797 | U93: 43343 | V93: 3.02 | W93: 53.8
A94: 42735 | B94: =VLOOKUP($A94,'框架指示的股债胜率（综合）'!$A:$Y,COLUMN(Y$1),0) -> 0.8930291 | D94: =VLOOKUP(A94,U:W,2,0) -> 3.445927 | F94: =VLOOKUP(A94,Q:R,2,0) -> 2.5808 | Q94: 37894 | R94: 2.6434 | U94: 43312 | V94: 3.1 | W94: 53.6
A95: 42704 | B95: =VLOOKUP($A95,'框架指示的股债胜率（综合）'!$A:$Y,COLUMN(Y$1),0) -> 0.91936289 | D95: =VLOOKUP(A95,U:W,2,0) -> 2.6713548 | F95: =VLOOKUP(A95,Q:R,2,0) -> #N/A | Q95: 37802 | R95: 2.153 | U95: 43281 | V95: 3.02 | W95: 54.4
A96: 42674 | B96: =VLOOKUP($A96,'框架指示的股债胜率（综合）'!$A:$Y,COLUMN(Y$1),0) -> 1.0354389 | D96: =VLOOKUP(A96,U:W,2,0) -> 1.7375682 | F96: =VLOOKUP(A96,Q:R,2,0) -> #N/A | Q96: 37711 | R96: 2.0941 | U96: 43251 | V96: 2.72 | W96: 54.6
A97: 42643 | B97: =VLOOKUP($A97,'框架指示的股债胜率（综合）'!$A:$Y,COLUMN(Y$1),0) -> 1.0185305 | D97: =VLOOKUP(A97,U:W,2,0) -> 1.1921356 | F97: =VLOOKUP(A97,Q:R,2,0) -> 1.0499 | Q97: 37621 | R97: 1.0614 | U97: 43220 | V97: 2.44 | W97: 54.1
A98: 42613 | B98: =VLOOKUP($A98,'框架指示的股债胜率（综合）'!$A:$Y,COLUMN(Y$1),0) -> 1.0015158 | D98: =VLOOKUP(A98,U:W,2,0) -> 0.4838638 | F98: =VLOOKUP(A98,Q:R,2,0) -> #N/A | Q98: 37529 | R98: 0.6569 | U98: 43190 | V98: 2.5 | W98: 54
A99: 42582 | B99: =VLOOKUP($A99,'框架指示的股债胜率（综合）'!$A:$Y,COLUMN(Y$1),0) -> 0.83566346 | D99: =VLOOKUP(A99,U:W,2,0) -> 0.3790678 | F99: =VLOOKUP(A99,Q:R,2,0) -> #N/A | Q99: 37437 | R99: 0.3998 | U99: 43159 | V99: 3.22 | W99: 52.9
A100: 42551 | B100: =VLOOKUP($A100,'框架指示的股债胜率（综合）'!$A:$Y,COLUMN(Y$1),0) -> 0.42181896 | D100: =VLOOKUP(A100,U:W,2,0) -> 0.0877018 | F100: =VLOOKUP(A100,Q:R,2,0) -> 0.5832 | Q100: 37346 | R100: 0.2475 | U100: 43131 | V100: 2.62 | W100: 54.6
A101: 42521 | B101: =VLOOKUP($A101,'框架指示的股债胜率（综合）'!$A:$Y,COLUMN(Y$1),0) -> 0.088557293 | D101: =VLOOKUP(A101,U:W,2,0) -> 0.1033994 | F101: =VLOOKUP(A101,Q:R,2,0) -> #N/A | Q101: 37256 | R101: 1.0608 | U101: 43100 | V101: 3.04 | W101: 54.6
A102: 42490 | B102: =VLOOKUP($A102,'框架指示的股债胜率（综合）'!$A:$Y,COLUMN(Y$1),0) -> -0.046413846 | D102: =VLOOKUP(A102,U:W,2,0) -> 0.036719 | F102: =VLOOKUP(A102,Q:R,2,0) -> #N/A | Q102: 37164 | R102: 2.0303 | U102: 43069 | V102: 3.34 | W102: 54.6
A103: 42460 | B103: =VLOOKUP($A103,'框架指示的股债胜率（综合）'!$A:$Y,COLUMN(Y$1),0) -> -0.095347629 | D103: =VLOOKUP(A103,U:W,2,0) -> -0.3391654 | F103: =VLOOKUP(A103,Q:R,2,0) -> 0.2917 | Q103: 37072 | R103: 2.3571 | U103: 43039 | V103: 3.9 | W103: 53.9
A104: 42429 | B104: =VLOOKUP($A104,'框架指示的股债胜率（综合）'!$A:$Y,COLUMN(Y$1),0) -> -0.14708293 | D104: =VLOOKUP(A104,U:W,2,0) -> -0.58 | F104: =VLOOKUP(A104,Q:R,2,0) -> #N/A | Q104: 36981 | R104: 3.1262 | U104: 43008 | V104: 3.72 | W104: 55.1
A105: 42369 | B105: =VLOOKUP($A105,'框架指示的股债胜率（综合）'!$A:$Y,COLUMN(Y$1),0) -> -0.24823012 | D105: =VLOOKUP(A105,U:W,2,0) -> -1.4 | F105: =VLOOKUP(A105,Q:R,2,0) -> -0.3364 | Q105: 36891 | R105: 2.1577 | U105: 42978 | V105: 3.6 | W105: 53.7
... A110: 42216 | B110: =VLOOKUP($A110,'框架指示的股债胜率（综合）'!$A:$Y,COLUMN(Y$1),0) -> 0 | D110: =VLOOKUP(A110,U:W,2,0) -> -1.1593 | F110: =VLOOKUP(A110,Q:R,2,0) -> #N/A | Q110: 36433 | R110: -1.6207 | U110: 42825 | V110: 3.58 | W110: 54.7
Q111: 36341 | R111: -1.5175 | U111: 42794 | V111: 3.6 | W111: 54
Q112: 36250 | R112: -1.4936 | U112: 42766 | V112: 4.289433 | W112: 54
Q113: 36160 | R113: -1.6212 | U113: 42735 | V113: 3.445927 | W113: 0
Q114: 36068 | R114: -1.4677 | U114: 42704 | V114: 2.6713548 | W114: 0
Q115: 35976 | R115: -0.924 | U115: 42674 | V115: 1.7375682 | W115: 0
Q116: 35885 | R116: 0.7913 | U116: 42643 | V116: 1.1921356 | W116: 0
Q117: 35795 | R117: 0.3691 | U117: 42613 | V117: 0.4838638 | W117: 0
Q118: 35703 | R118: 1.46 | U118: 42582 | V118: 0.3790678 | W118: 0
Q119: 35611 | R119: 1.5976 | U119: 42551 | V119: 0.0877018 | W119: 0
Q120: 35520 | R120: 3.6241 | U120: 42521 | V120: 0.1033994 | W120: 0
Q121: 35430 | R121: 5.3103 | U121: 42490 | V121: 0.036719 | W121: 0
...

Sheet 周期整合计算
C3: 滞涨 | D3: 衰退 | E3: 复苏 | F3: 过热
B4: 综合景气指标 | C4: 周期1（景气值>0，方向下降） | D4: 周期2（景气值<0，方向下降） | E4: 周期3（景气值<0，方向上升） | F4: 周期4（景气值>0，方向上升） | G4: 周期
A5: 45688 | B5: =VLOOKUP(A5,'框架指示的股债胜率（综合）'!A:AA,25,0) -> -1.4195336 | C5: 0 | D5: 0 | E5: 1 | F5: 0 | G5: 周期3（景气值<0，方向上升）
A6: 45657 | B6: =VLOOKUP(A6,'框架指示的股债胜率（综合）'!A:AA,25,0) -> -1.7174815 | C6: 0 | D6: 0 | E6: 1 | F6: 0 | G6: 周期3（景气值<0，方向上升） | I6: 周期对照：
A7: 45626 | B7: =VLOOKUP(A7,'框架指示的股债胜率（综合）'!A:AA,25,0) -> -2.0424001 | C7: 0 | D7: 0 | E7: 1 | F7: 0 | G7: 周期3（景气值<0，方向上升） | J7: 周期2（景气值<0，方向下降） | K7: 衰退
A8: 45596 | B8: =VLOOKUP(A8,'框架指示的股债胜率（综合）'!A:AA,25,0) -> -2.3084846 | C8: 0 | D8: 0 | E8: 1 | F8: 0 | G8: 周期3（景气值<0，方向上升） | J8: 周期3（景气值<0，方向上升） | K8: 复苏
A9: 45565 | B9: =VLOOKUP(A9,'框架指示的股债胜率（综合）'!A:AA,25,0) -> -2.5968375 | C9: 0 | D9: 0 | E9: 1 | F9: 0 | G9: 周期3（景气值<0，方向上升） | J9: 周期4（景气值>0，方向上升） | K9: 过热
A10: 45535 | B10: =VLOOKUP(A10,'框架指示的股债胜率（综合）'!A:AA,25,0) -> -2.6485948 | C10: 0 | D10: 1 | E10: 0 | F10: 0 | G10: 周期3（景气值<0，方向上升） | J10: 周期1（景气值>0，方向下降） | K10: 滞涨
A11: 45504 | B11: =VLOOKUP(A11,'框架指示的股债胜率（综合）'!A:AA,25,0) -> -2.2078799 | C11: 0 | D11: 1 | E11: 0 | F11: 0 | G11: 周期2（景气值<0，方向下降）
A12: 45473 | B12: =VLOOKUP(A12,'框架指示的股债胜率（综合）'!A:AA,25,0) -> -2.0208268 | C12: 0 | D12: 1 | E12: 0 | F12: 0 | G12: 周期2（景气值<0，方向下降）
A13: 45443 | B13: =VLOOKUP(A13,'框架指示的股债胜率（综合）'!A:AA,25,0) -> -1.849816 | C13: 0 | D13: 1 | E13: 0 | F13: 0 | G13: 周期2（景气值<0，方向下降）
A14: 45412 | B14: =VLOOKUP(A14,'框架指示的股债胜率（综合）'!A:AA,25,0) -> -1.6840842 | C14: 0 | D14: 1 | E14: 0 | F14: 0 | G14: 周期2（景气值<0，方向下降）
A15: 45382 | B15: =VLOOKUP(A15,'框架指示的股债胜率（综合）'!A:AA,25,0) -> -1.2461303 | C15: 0 | D15: 1 | E15: 0 | F15: 0 | G15: 周期2（景气值<0，方向下降）
A16: 45351 | B16: =VLOOKUP(A16,'框架指示的股债胜率（综合）'!A:AA,25,0) -> -0.86496174 | C16: 0 | D16: 1 | E16: 0 | F16: 0 | G16: 周期2（景气值<0，方向下降）
A17: 45322 | B17: =VLOOKUP(A17,'框架指示的股债胜率（综合）'!A:AA,25,0) -> #N/A | C17: 0 | D17: 1 | E17: 0 | F17: 0 | G17: 周期2（景气值<0，方向下降）
A18: 45291 | B18: =VLOOKUP(A18,'框架指示的股债胜率（综合）'!A:AA,25,0) -> -0.77144221 | C18: 0 | D18: 1 | E18: 0 | F18: 0 | G18: 周期2（景气值<0，方向下降）
A19: 45260 | B19: =VLOOKUP(A19,'框架指示的股债胜率（综合）'!A:AA,25,0) -> -0.79189289 | C19: 0 | D19: 1 | E19: 0 | F19: 0 | G19: 周期2（景气值<0，方向下降）
A20: 45230 | B20: =VLOOKUP(A20,'框架指示的股债胜率（综合）'!A:AA,25,0) -> -0.64542371 | C20: 0 | D20: 1 | E20: 0 | F20: 0 | G20: 周期2（景气值<0，方向下降）
A21: 45199 | B21: =VLOOKUP(A21,'框架指示的股债胜率（综合）'!A:AA,25,0) -> -0.3905104 | C21: 0 | D21: 1 | E21: 0 | F21: 0 | G21: 周期2（景气值<0，方向下降）
A22: 45169 | B22: =VLOOKUP(A22,'框架指示的股债胜率（综合）'!A:AA,25,0) -> -0.40977378 | C22: 0 | D22: 1 | E22: 0 | F22: 0 | G22: 周期2（景气值<0，方向下降）
... A185: 40209 | B185: =VLOOKUP(A185,'框架指示的股债胜率（综合）'!A:AA,25,0) -> #N/A | C185: 1 | D185: 0 | E185: 0 | F185: 0 | G185: 周期1（景气值>0，方向下降）

Sheet 货币信用周期收益计算
B1: 货币信用周期 | D1: 阶段终点 | F1: 阶段起点 | H1: 阶段序号 | I1: 阶段起点 | J1: 阶段终点 | K1: 组合阶段 | L1: 经济周期 | V1: 881001.WI | W1: 000016.SH | X1: 000300.SH | Y1: 000905.SH | Z1: 000852.SH | AA1: CI005918.WI | AB1: CI005919.WI | AC1: CI005917.WI | AD1: CI005921.WI | AE1: CI005920.WI | AF1: 801010.SI | AG1: 801030.SI | AH1: 801040.SI | AI1: 801050.SI | AJ1: 801080.SI | AK1: 801110.SI | AL1: 801120.SI | AM1: 801130.SI | AN1: 801140.SI | AO1: 801150.SI | AP1: 801160.SI | AQ1: 801170.SI | AR1: 801180.SI | AS1: 801200.SI | AT1: 801210.SI | AU1: 801230.SI | AV1: 801710.SI | AW1: 801720.SI | AX1: 801730.SI | AY1: 801740.SI | AZ1: 801750.SI | BA1: 801760.SI | BB1: 801770.SI | BC1: 801780.SI | BD1: 801790.SI | BE1: 801880.SI | BF1: 801890.SI | BG1: 801950.SI | BH1: 801960.SI | BI1: 801970.SI | BJ1: 801980.SI | BK1: 000015.SH | BL1: 399321.SZ | BM1: 399324.SZ | BN1: 867001.WI | BO1: 000922.CSI | BP1: 861101.CJ | BQ1: 861102.CJ | BR1: 399314.SZ | BS1: 399315.SZ | BT1: 399316.SZ
A2: 45688 | B2: =VLOOKUP(A2,周期整合计算!A:G,7,0) -> 周期3（景气值<0，方向上升） | C2: =IF(ISNUMBER(D2),COUNTIF(D$2:D2,">0"),"") -> 1 | D2: =IF(B1=B2,"",A2) -> 45688 | E2: =IF(ISNUMBER(F2),COUNTIF(F$2:F2,">0"),"") | F2: =IF(B2=B3,"",A2) | H2: 1 | I2: =EOMONTH(VLOOKUP($H2,$E:$F,2,FALSE),-1)+1 -> 45505 | J2: =VLOOKUP($H2,$C:$D,2,FALSE) -> 45688 | K2: =VLOOKUP(VLOOKUP($H2,$C:$F,2,FALSE),A:B,2,FALSE) -> 周期3（景气值<0，方向上升） | L2: =VLOOKUP(K2,周期整合计算!J:K,2,0) -> 复苏 | O2: 所处阶段 | P2: 阶段起点 | Q2: 阶段终点 | R2: 个数 | S2: 总月数 | T2: 平均月数 | U2: 时期占比 | V2: 万得全A | W2: 上证50指数 | X2: 沪深300指数 | Y2: 中证500指数 | Z2: 中证1000指数 | AA2: 周期 | AB2: 消费 | AC2: 金融 | AD2: 稳定 | AE2: 成长 | AF2: 农林牧渔 | AG2: 基础化工 | AH2: 钢铁 | AI2: 有色金属 | AJ2: 电子 | AK2: 家用电器 | AL2: 食品饮料 | AM2: 纺织服饰 | AN2: 轻工制造 | AO2: 医药生物 | AP2: 公用事业 | AQ2: 交通运输 | AR2: 房地产 | AS2: 商贸零售 | AT2: 社会服务 | AU2: 综合 | AV2: 建筑材料 | AW2: 建筑装饰 | AX2: 电力设备 | AY2: 国防军工 | AZ2: 计算机 | BA2: 传媒 | BB2: 通信 | BC2: 银行 | BD2: 非银金融 | BE2: 汽车 | BF2: 机械设备 | BG2: 煤炭 | BH2: 石油石化 | BI2: 环保 | BJ2: 美容护理 | BK2: 红利指数 | BL2: 国证红利 | BM2: 深证红利 | BN2: 万得红利 | BO2: 中证红利 | BP2: 低估值指数(长江) | BQ2: 高估值指数(长江) | BR2: 巨潮大盘 | BS2: 巨潮中盘 | BT2: 巨潮小盘
A3: 45657 | B3: =VLOOKUP(A3,周期整合计算!A:G,7,0) -> 周期3（景气值<0，方向上升） | C3: =IF(ISNUMBER(D3),COUNTIF(D$2:D3,">0"),"") | D3: =IF(B2=B3,"",A3) | E3: =IF(ISNUMBER(F3),COUNTIF(F$2:F3,">0"),"") | F3: =IF(B3=B4,"",A3) | H3: 2 | I3: =EOMONTH(VLOOKUP($H3,$E:$F,2,FALSE),-1)+1 -> 45078 | J3: =VLOOKUP($H3,$C:$D,2,FALSE) -> 45504 | K3: =VLOOKUP(VLOOKUP($H3,$C:$F,2,FALSE),A:B,2,FALSE) -> 周期2（景气值<0，方向下降） | L3: =VLOOKUP(K3,周期整合计算!J:K,2,0) -> 衰退 | N3: 衰退 | O3: 衰退 | P3: 45078 | Q3: 45443 | R3: 5 | S3: =DATEDIF(P3,Q3,"M")+1 -> 12 | V3: =[1]!s_pq_pctchange(V$1,$P3,$Q3) -> -9.3936893 | W3: =[1]!s_pq_pctchange(W$1,$P3,$Q3) -> -1.2499852 | X3: =[1]!s_pq_pctchange(X$1,$P3,$Q3) -> -5.7553298 | Y3: =[1]!s_pq_pctchange(Y$1,$P3,$Q3) -> -12.223644 | Z3: =[1]!s_pq_pctchange(Z$1,$P3,$Q3) -> -18.386214 | AA3: =[1]!s_pq_pctchange(AA$1,$P3,$Q3) -> 4.6060163 | AB3: =[1]!s_pq_pctchange(AB$1,$P3,$Q3) -> -8.9396062 | AC3: =[1]!s_pq_pctchange(AC$1,$P3,$Q3) -> 2.8145633 | ... BT3: =[1]!s_pq_pctchange(BT$1,$P3,$Q3) -> -13.228906
A4: 45626 | B4: =VLOOKUP(A4,周期整合计算!A:G,7,0) -> 周期3（景气值<0，方向上升） | C4: =IF(ISNUMBER(D4),COUNTIF(D$2:D4,">0"),"") | D4: =IF(B3=B4,"",A4) | E4: =IF(ISNUMBER(F4),COUNTIF(F$2:F4,">0"),"") | F4: =IF(B4=B5,"",A4) | H4: 3 | I4: =EOMONTH(VLOOKUP($H4,$E:$F,2,FALSE),-1)+1 -> 44501 | J4: =VLOOKUP($H4,$C:$D,2,FALSE) -> 45077 | K4: =VLOOKUP(VLOOKUP($H4,$C:$F,2,FALSE),A:B,2,FALSE) -> 周期3（景气值<0，方向上升） | L4: =VLOOKUP(K4,周期整合计算!J:K,2,0) -> 复苏 | N4: 衰退 | P4: 44348 | Q4: 44500 | S4: =DATEDIF(P4,Q4,"M")+1 -> 5 | V4: =[1]!s_pq_pctchange(V$1,$P4,$Q4) -> 0.74693527 | W4: =[1]!s_pq_pctchange(W$1,$P4,$Q4) -> -10.491831 | X4: =[1]!s_pq_pctchange(X$1,$P4,$Q4) -> -7.9301131 | Y4: =[1]!s_pq_pctchange(Y$1,$P4,$Q4) -> 4.3618518 | Z4: =[1]!s_pq_pctchange(Z$1,$P4,$Q4) -> 8.3785057 | AA4: =[1]!s_pq_pctchange(AA$1,$P4,$Q4) -> 10.972973 | AB4: =[1]!s_pq_pctchange(AB$1,$P4,$Q4) -> -14.638137 | AC4: =[1]!s_pq_pctchange(AC$1,$P4,$Q4) -> -9.964841 | ... BT4: =[1]!s_pq_pctchange(BT$1,$P4,$Q4) -> 6.3736596
A5: 45596 | B5: =VLOOKUP(A5,周期整合计算!A:G,7,0) -> 周期3（景气值<0，方向上升） | C5: =IF(ISNUMBER(D5),COUNTIF(D$2:D5,">0"),"") | D5: =IF(B4=B5,"",A5) | E5: =IF(ISNUMBER(F5),COUNTIF(F$2:F5,">0"),"") | F5: =IF(B5=B6,"",A5) | H5: 4 | I5: =EOMONTH(VLOOKUP($H5,$E:$F,2,FALSE),-1)+1 -> 44348 | J5: =VLOOKUP($H5,$C:$D,2,FALSE) -> 44500 | K5: =VLOOKUP(VLOOKUP($H5,$C:$F,2,FALSE),A:B,2,FALSE) -> 周期2（景气值<0，方向下降） | L5: =VLOOKUP(K5,周期整合计算!J:K,2,0) -> 衰退 | N5: 衰退 | P5: 43191 | Q5: 43373 | S5: =DATEDIF(P5,Q5,"M")+1 -> 6 | V5: =[1]!s_pq_pctchange(V$1,$P5,$Q5) -> -16.029505 | W5: =[1]!s_pq_pctchange(W$1,$P5,$Q5) -> -4.2424287 | X5: =[1]!s_pq_pctchange(X$1,$P5,$Q5) -> -11.789998 | Y5: =[1]!s_pq_pctchange(Y$1,$P5,$Q5) -> -21.489219 | Z5: =[1]!s_pq_pctchange(Z$1,$P5,$Q5) -> -26.643389 | AA5: =[1]!s_pq_pctchange(AA$1,$P5,$Q5) -> -17.762534 | AB5: =[1]!s_pq_pctchange(AB$1,$P5,$Q5) -> -13.711584 | AC5: =[1]!s_pq_pctchange(AC$1,$P5,$Q5) -> -7.2954124 | ... BT5: =[1]!s_pq_pctchange(BT$1,$P5,$Q5) -> -23.702298
A6: 45565 | B6: =VLOOKUP(A6,周期整合计算!A:G,7,0) -> 周期3（景气值<0，方向上升） | C6: =IF(ISNUMBER(D6),COUNTIF(D$2:D6,">0"),"") | D6: =IF(B5=B6,"",A6) | E6: =IF(ISNUMBER(F6),COUNTIF(F$2:F6,">0"),"") | F6: =IF(B6=B7,"",A6) | H6: 5 | I6: =EOMONTH(VLOOKUP($H6,$E:$F,2,FALSE),-1)+1 -> 44136 | J6: =VLOOKUP($H6,$C:$D,2,FALSE) -> 44347 | K6: =VLOOKUP(VLOOKUP($H6,$C:$F,2,FALSE),A:B,2,FALSE) -> 周期1（景气值>0，方向下降） | L6: =VLOOKUP(K6,周期整合计算!J:K,2,0) -> 滞涨 | N6: 衰退 | P6: 41791 | Q6: 42004 | S6: =DATEDIF(P6,Q6,"M")+1 -> 7 | V6: =[1]!s_pq_pctchange(V$1,$P6,$Q6) -> 56.23847 | W6: =[1]!s_pq_pctchange(W$1,$P6,$Q6) -> 74.183521 | X6: =[1]!s_pq_pctchange(X$1,$P6,$Q6) -> 63.865708 | Y6: =[1]!s_pq_pctchange(Y$1,$P6,$Q6) -> 39.001911 | Z6: =[1]!s_pq_pctchange(Z$1,$P6,$Q6) -> 29.673362 | AA6: =[1]!s_pq_pctchange(AA$1,$P6,$Q6) -> 47.923118 | AB6: =[1]!s_pq_pctchange(AB$1,$P6,$Q6) -> 28.821734 | AC6: =[1]!s_pq_pctchange(AC$1,$P6,$Q6) -> 101.89344 | ... BT6: =[1]!s_pq_pctchange(BT$1,$P6,$Q6) -> 39.95656
A7: 45535 | B7: =VLOOKUP(A7,周期整合计算!A:G,7,0) -> 周期3（景气值<0，方向上升） | C7: =IF(ISNUMBER(D7),COUNTIF(D$2:D7,">0"),"") | D7: =IF(B6=B7,"",A7) | E7: =IF(ISNUMBER(F7),COUNTIF(F$2:F7,">0"),"") -> 1 | F7: =IF(B7=B8,"",A7) -> 45535 | H7: 6 | I7: =EOMONTH(VLOOKUP($H7,$E:$F,2,FALSE),-1)+1 -> 43891 | J7: =VLOOKUP($H7,$C:$D,2,FALSE) -> 44135 | K7: =VLOOKUP(VLOOKUP($H7,$C:$F,2,FALSE),A:B,2,FALSE) -> 周期4（景气值>0，方向上升） | L7: =VLOOKUP(K7,周期整合计算!J:K,2,0) -> 过热 | N7: 衰退 | P7: 40848 | Q7: 41060 | S7: =DATEDIF(P7,Q7,"M")+1 -> 7 | V7: =[1]!s_pq_pctchange(V$1,$P7,$Q7) -> -4.0188925 | W7: =[1]!s_pq_pctchange(W$1,$P7,$Q7) -> 0.69986847 | X7: =[1]!s_pq_pctchange(X$1,$P7,$Q7) -> -2.347228 | Y7: =[1]!s_pq_pctchange(Y$1,$P7,$Q7) -> -6.1452052 | Z7: =[1]!s_pq_pctchange(Z$1,$P7,$Q7) -> -10.379979 | AA7: =[1]!s_pq_pctchange(AA$1,$P7,$Q7) -> -10.033635 | AB7: =[1]!s_pq_pctchange(AB$1,$P7,$Q7) -> -4.9111948 | AC7: =[1]!s_pq_pctchange(AC$1,$P7,$Q7) -> 4.9640361 | ... BT7: =[1]!s_pq_pctchange(BT$1,$P7,$Q7) -> -7.6510965
A8: 45504 | B8: =VLOOKUP(A8,周期整合计算!A:G,7,0) -> 周期2（景气值<0，方向下降） | C8: =IF(ISNUMBER(D8),COUNTIF(D$2:D8,">0"),"") -> 2 | D8: =IF(B7=B8,"",A8) -> 45504 | E8: =IF(ISNUMBER(F8),COUNTIF(F$2:F8,">0"),"") | F8: =IF(B8=B9,"",A8) | H8: 7 | I8: =EOMONTH(VLOOKUP($H8,$E:$F,2,FALSE),-1)+1 -> 43374 | J8: =VLOOKUP($H8,$C:$D,2,FALSE) -> 43890 | K8: =VLOOKUP(VLOOKUP($H8,$C:$F,2,FALSE),A:B,2,FALSE) -> 周期3（景气值<0，方向上升） | L8: =VLOOKUP(K8,周期整合计算!J:K,2,0) -> 复苏 | N8: 复苏 | O8: 复苏 | P8: 45505 | Q8: 45688 | R8: 5 | S8: =DATEDIF(P9,Q9,"M")+1 -> 19 | V8: =[1]!s_pq_pctchange(V$1,$P8,$Q8) -> 16.497202 | W8: =[1]!s_pq_pctchange(W$1,$P8,$Q8) -> 8.7672774 | X8: =[1]!s_pq_pctchange(X$1,$P8,$Q8) -> 10.894439 | Y8: =[1]!s_pq_pctchange(Y$1,$P8,$Q8) -> 14.385389 | Z8: =[1]!s_pq_pctchange(Z$1,$P8,$Q8) -> 19.573985 | AA8: =[1]!s_pq_pctchange(AA$1,$P8,$Q8) -> 10.762717 | AB8: =[1]!s_pq_pctchange(AB$1,$P8,$Q8) -> 8.8874292 | AC8: =[1]!s_pq_pctchange(AC$1,$P8,$Q8) -> 21.096473 | ... BT8: =[1]!s_pq_pctchange(BT$1,$P8,$Q8) -> 14.628992
A9: 45473 | B9: =VLOOKUP(A9,周期整合计算!A:G,7,0) -> 周期2（景气值<0，方向下降） | C9: =IF(ISNUMBER(D9),COUNTIF(D$2:D9,">0"),"") | D9: =IF(B8=B9,"",A9) | E9: =IF(ISNUMBER(F9),COUNTIF(F$2:F9,">0"),"") | F9: =IF(B9=B10,"",A9) | H9: 8 | I9: =EOMONTH(VLOOKUP($H9,$E:$F,2,FALSE),-1)+1 -> 43191 | J9: =VLOOKUP($H9,$C:$D,2,FALSE) -> 43373 | K9: =VLOOKUP(VLOOKUP($H9,$C:$F,2,FALSE),A:B,2,FALSE) -> 周期2（景气值<0，方向下降） | L9: =VLOOKUP(K9,周期整合计算!J:K,2,0) -> 衰退 | N9: 复苏 | P9: 44501 | Q9: 45077 | S9: =DATEDIF(P10,Q10,"M")+1 -> 17 | V9: =[1]!s_pq_pctchange(V$1,$P9,$Q9) -> -13.990789 | W9: =[1]!s_pq_pctchange(W$1,$P9,$Q9) -> -23.686578 | X9: =[1]!s_pq_pctchange(X$1,$P9,$Q9) -> -22.617207 | Y9: =[1]!s_pq_pctchange(Y$1,$P9,$Q9) -> -13.879633 | Z9: =[1]!s_pq_pctchange(Z$1,$P9,$Q9) -> -11.152636 | AA9: =[1]!s_pq_pctchange(AA$1,$P9,$Q9) -> -14.639102 | AB9: =[1]!s_pq_pctchange(AB$1,$P9,$Q9) -> -13.755274 | AC9: =[1]!s_pq_pctchange(AC$1,$P9,$Q9) -> -9.6665436 | ... BT9: =[1]!s_pq_pctchange(BT$1,$P9,$Q9) -> -10.725585
A10: 45443 | B10: =VLOOKUP(A10,周期整合计算!A:G,7,0) -> 周期2（景气值<0，方向下降） | C10: =IF(ISNUMBER(D10),COUNTIF(D$2:D10,">0"),"") | D10: =IF(B9=B10,"",A10) | E10: =IF(ISNUMBER(F10),COUNTIF(F$2:F10,">0"),"") | F10: =IF(B10=B11,"",A10) | H10: 9 | I10: =EOMONTH(VLOOKUP($H10,$E:$F,2,FALSE),-1)+1 -> 42614 | J10: =VLOOKUP($H10,$C:$D,2,FALSE) -> 43190 | K10: =VLOOKUP(VLOOKUP($H10,$C:$F,2,FALSE),A:B,2,FALSE) -> 周期1（景气值>0，方向下降） | L10: =VLOOKUP(K10,周期整合计算!J:K,2,0) -> 滞涨 | N10: 复苏 | P10: 43374 | Q10: 43890 | S10: =DATEDIF(P11,Q11,"M")+1 -> 14 | V10: =[1]!s_pq_pctchange(V$1,$P10,$Q10) -> 17.134175 | W10: =[1]!s_pq_pctchange(W$1,$P10,$Q10) -> 8.2240751 | X10: =[1]!s_pq_pctchange(X$1,$P10,$Q10) -> 14.574108 | Y10: =[1]!s_pq_pctchange(Y$1,$P10,$Q10) -> 13.551297 | Z10: =[1]!s_pq_pctchange(Z$1,$P10,$Q10) -> 17.718977 | AA10: =[1]!s_pq_pctchange(AA$1,$P10,$Q10) -> 2.6299961 | AB10: =[1]!s_pq_pctchange(AB$1,$P10,$Q10) -> 24.939353 | AC10: =[1]!s_pq_pctchange(AC$1,$P10,$Q10) -> 11.587446 | ... BT10: =[1]!s_pq_pctchange(BT$1,$P10,$Q10) -> 16.099746
A11: 45412 | B11: =VLOOKUP(A11,周期整合计算!A:G,7,0) -> 周期2（景气值<0，方向下降） | C11: =IF(ISNUMBER(D11),COUNTIF(D$2:D11,">0"),"") | D11: =IF(B10=B11,"",A11) | E11: =IF(ISNUMBER(F11),COUNTIF(F$2:F11,">0"),"") | F11: =IF(B11=B12,"",A11) | H11: 10 | I11: =EOMONTH(VLOOKUP($H11,$E:$F,2,FALSE),-1)+1 -> 42430 | J11: =VLOOKUP($H11,$C:$D,2,FALSE) -> 42613 | K11: =VLOOKUP(VLOOKUP($H11,$C:$F,2,FALSE),A:B,2,FALSE) -> 周期4（景气值>0，方向上升） | L11: =VLOOKUP(K11,周期整合计算!J:K,2,0) -> 过热 | N11: 复苏 | P11: 42005 | Q11: 42429 | S11: =DATEDIF(P12,Q12,"M")+1 -> 4 | V11: =[1]!s_pq_pctchange(V$1,$P11,$Q11) -> -2.3633616 | W11: =[1]!s_pq_pctchange(W$1,$P11,$Q11) -> -24.673228 | X11: =[1]!s_pq_pctchange(X$1,$P11,$Q11) -> -18.570831 | Y11: =[1]!s_pq_pctchange(Y$1,$P11,$Q11) -> 0.52078132 | Z11: =[1]!s_pq_pctchange(Z$1,$P11,$Q11) -> 19.181293 | AA11: =[1]!s_pq_pctchange(AA$1,$P11,$Q11) -> 2.3119291 | AB11: =[1]!s_pq_pctchange(AB$1,$P11,$Q11) -> 9.6335162 | AC11: =[1]!s_pq_pctchange(AC$1,$P11,$Q11) -> -20.39922 | ... BT11: =[1]!s_pq_pctchange(BT$1,$P11,$Q11) -> 5.8088797
A12: 45382 | B12: =VLOOKUP(A12,周期整合计算!A:G,7,0) -> 周期2（景气值<0，方向下降） | C12: =IF(ISNUMBER(D12),COUNTIF(D$2:D12,">0"),"") | D12: =IF(B11=B12,"",A12) | E12: =IF(ISNUMBER(F12),COUNTIF(F$2:F12,">0"),"") | F12: =IF(B12=B13,"",A12) | H12: 11 | I12: =EOMONTH(VLOOKUP($H12,$E:$F,2,FALSE),-1)+1 -> 42005 | J12: =VLOOKUP($H12,$C:$D,2,FALSE) -> 42429 | K12: =VLOOKUP(VLOOKUP($H12,$C:$F,2,FALSE),A:B,2,FALSE) -> 周期3（景气值<0，方向上升） | L12: =VLOOKUP(K12,周期整合计算!J:K,2,0) -> 复苏 | N12: 复苏 | P12: 41061 | Q12: 41182 | S12: =DATEDIF(P13,Q13,"M")+1 -> 7 | V12: =[1]!s_pq_pctchange(V$1,$P12,$Q12) -> -10.413178 | W12: =[1]!s_pq_pctchange(W$1,$P12,$Q12) -> -10.611866 | X12: =[1]!s_pq_pctchange(X$1,$P12,$Q12) -> -12.877302 | Y12: =[1]!s_pq_pctchange(Y$1,$P12,$Q12) -> -14.754956 | Z12: =[1]!s_pq_pctchange(Z$1,$P12,$Q12) -> -13.835127 | AA12: =[1]!s_pq_pctchange(AA$1,$P12,$Q12) -> -15.922991 | AB12: =[1]!s_pq_pctchange(AB$1,$P12,$Q12) -> -7.2502151 | AC12: =[1]!s_pq_pctchange(AC$1,$P12,$Q12) -> -10.19747 | ... BT12: =[1]!s_pq_pctchange(BT$1,$P12,$Q12) -> -14.486073
A13: 45351 | B13: =VLOOKUP(A13,周期整合计算!A:G,7,0) -> 周期2（景气值<0，方向下降） | C13: =IF(ISNUMBER(D13),COUNTIF(D$2:D13,">0"),"") | D13: =IF(B12=B13,"",A13) | E13: =IF(ISNUMBER(F13),COUNTIF(F$2:F13,">0"),"") | F13: =IF(B13=B14,"",A13) | H13: 12 | I13: =EOMONTH(VLOOKUP($H13,$E:$F,2,FALSE),-1)+1 -> 41791 | J13: =VLOOKUP($H13,$C:$D,2,FALSE) -> 42004 | K13: =VLOOKUP(VLOOKUP($H13,$C:$F,2,FALSE),A:B,2,FALSE) -> 周期2（景气值<0，方向下降） | L13: =VLOOKUP(K13,周期整合计算!J:K,2,0) -> 衰退 | N13: 滞涨 | O13: 滞涨 | P13: 44136 | Q13: 44347 | R13: 4 | S13: =DATEDIF(P14,Q14,"M")+1 -> 19 | V13: =[1]!s_pq_pctchange(V$1,$P13,$Q13) -> 11.47933 | W13: =[1]!s_pq_pctchange(W$1,$P13,$Q13) -> 11.274322 | X13: =[1]!s_pq_pctchange(X$1,$P13,$Q13) -> 13.550385 | Y13: =[1]!s_pq_pctchange(Y$1,$P13,$Q13) -> 10.104104 | Z13: =[1]!s_pq_pctchange(Z$1,$P13,$Q13) -> 4.6567017 | AA13: =[1]!s_pq_pctchange(AA$1,$P13,$Q13) -> 18.39461 | AB13: =[1]!s_pq_pctchange(AB$1,$P13,$Q13) -> 15.746946 | AC13: =[1]!s_pq_pctchange(AC$1,$P13,$Q13) -> 3.9947466 | ... BT13: =[1]!s_pq_pctchange(BT$1,$P13,$Q13) -> 9.2231498
A14: 45322 | B14: =VLOOKUP(A14,周期整合计算!A:G,7,0) -> 周期2（景气值<0，方向下降） | C14: =IF(ISNUMBER(D14),COUNTIF(D$2:D14,">0"),"") | D14: =IF(B13=B14,"",A14) | E14: =IF(ISNUMBER(F14),COUNTIF(F$2:F14,">0"),"") | F14: =IF(B14=B15,"",A14) | H14: 13 | I14: =EOMONTH(VLOOKUP($H14,$E:$F,2,FALSE),-1)+1 -> 41487 | J14: =VLOOKUP($H14,$C:$D,2,FALSE) -> 41790 | K14: =VLOOKUP(VLOOKUP($H14,$C:$F,2,FALSE),A:B,2,FALSE) -> 周期1（景气值>0，方向下降） | L14: =VLOOKUP(K14,周期整合计算!J:K,2,0) -> 滞涨 | N14: 滞涨 | P14: 42614 | Q14: 43190 | S14: =DATEDIF(P15,Q15,"M")+1 -> 10 | V14: =[1]!s_pq_pctchange(V$1,$P14,$Q14) -> 1.2402893 | W14: =[1]!s_pq_pctchange(W$1,$P14,$Q14) -> 21.921384 | X14: =[1]!s_pq_pctchange(X$1,$P14,$Q14) -> 17.149617 | Y14: =[1]!s_pq_pctchange(Y$1,$P14,$Q14) -> -4.9652107 | Z14: =[1]!s_pq_pctchange(Z$1,$P14,$Q14) -> -23.077892 | AA14: =[1]!s_pq_pctchange(AA$1,$P14,$Q14) -> -4.9481873 | AB14: =[1]!s_pq_pctchange(AB$1,$P14,$Q14) -> 11.500174 | AC14: =[1]!s_pq_pctchange(AC$1,$P14,$Q14) -> 6.9461307 | ... BT14: =[1]!s_pq_pctchange(BT$1,$P14,$Q14) -> -14.973774
A15: 45291 | B15: =VLOOKUP(A15,周期整合计算!A:G,7,0) -> 周期2（景气值<0，方向下降） | C15: =IF(ISNUMBER(D15),COUNTIF(D$2:D15,">0"),"") | D15: =IF(B14=B15,"",A15) | E15: =IF(ISNUMBER(F15),COUNTIF(F$2:F15,">0"),"") | F15: =IF(B15=B16,"",A15) | H15: 14 | I15: =EOMONTH(VLOOKUP($H15,$E:$F,2,FALSE),-1)+1 -> 41183 | J15: =VLOOKUP($H15,$C:$D,2,FALSE) -> 41486 | K15: =VLOOKUP(VLOOKUP($H15,$C:$F,2,FALSE),A:B,2,FALSE) -> 周期4（景气值>0，方向上升） | L15: =VLOOKUP(K15,周期整合计算!J:K,2,0) -> 过热 | N15: 滞涨 | P15: 41487 | Q15: 41790 | S15: =DATEDIF(P16,Q16,"M")+1 -> 22 | V15: =[1]!s_pq_pctchange(V$1,$P15,$Q15) -> 7.7209277 | W15: =[1]!s_pq_pctchange(W$1,$P15,$Q15) -> -1.4673238 | X15: =[1]!s_pq_pctchange(X$1,$P15,$Q15) -> -1.6669699 | Y15: =[1]!s_pq_pctchange(Y$1,$P15,$Q15) -> 11.615414 | Z15: =[1]!s_pq_pctchange(Z$1,$P15,$Q15) -> 19.170642 | AA15: =[1]!s_pq_pctchange(AA$1,$P15,$Q15) -> 6.4368459 | AB15: =[1]!s_pq_pctchange(AB$1,$P15,$Q15) -> 8.6841335 | AC15: =[1]!s_pq_pctchange(AC$1,$P15,$Q15) -> 2.2719184 | ... BT15: =[1]!s_pq_pctchange(BT$1,$P15,$Q15) -> 11.644729
A16: 45260 | B16: =VLOOKUP(A16,周期整合计算!A:G,7,0) -> 周期2（景气值<0，方向下降） | C16: =IF(ISNUMBER(D16),COUNTIF(D$2:D16,">0"),"") | D16: =IF(B15=B16,"",A16) | E16: =IF(ISNUMBER(F16),COUNTIF(F$2:F16,">0"),"") | F16: =IF(B16=B17,"",A16) | H16: 15 | I16: =EOMONTH(VLOOKUP($H16,$E:$F,2,FALSE),-1)+1 -> 41061 | J16: =VLOOKUP($H16,$C:$D,2,FALSE) -> 41182 | K16: =VLOOKUP(VLOOKUP($H16,$C:$F,2,FALSE),A:B,2,FALSE) -> 周期3（景气值<0，方向上升） | L16: =VLOOKUP(K16,周期整合计算!J:K,2,0) -> 复苏 | N16: 滞涨 | P16: 40179 | Q16: 40847 | S16: =DATEDIF(P17,Q17,"M")+1 -> 8 | V16: =[1]!s_pq_pctchange(V$1,$P16,$Q16) -> -17.953733 | W16: =[1]!s_pq_pctchange(W$1,$P16,$Q16) -> -29.82806 | X16: =[1]!s_pq_pctchange(X$1,$P16,$Q16) -> -24.621219 | Y16: =[1]!s_pq_pctchange(Y$1,$P16,$Q16) -> -10.833119 | Z16: =[1]!s_pq_pctchange(Z$1,$P16,$Q16) -> -0.93701587 | AA16: =[1]!s_pq_pctchange(AA$1,$P16,$Q16) -> -15.350073 | AB16: =[1]!s_pq_pctchange(AB$1,$P16,$Q16) -> 0.36000378 | AC16: =[1]!s_pq_pctchange(AC$1,$P16,$Q16) -> -30.848348 | ... BT16: =[1]!s_pq_pctchange(BT$1,$P16,$Q16) -> -5.9180069
A17: 45230 | B17: =VLOOKUP(A17,周期整合计算!A:G,7,0) -> 周期2（景气值<0，方向下降） | C17: =IF(ISNUMBER(D17),COUNTIF(D$2:D17,">0"),"") | D17: =IF(B16=B17,"",A17) | E17: =IF(ISNUMBER(F17),COUNTIF(F$2:F17,">0"),"") | F17: =IF(B17=B18,"",A17) | H17: 16 | I17: 40179 | J17: =VLOOKUP($H17,$C:$D,2,FALSE) -> 41060 | K17: =VLOOKUP(VLOOKUP($H17,$C:$F,2,FALSE),A:B,2,FALSE) -> 周期2（景气值<0，方向下降） | L17: =VLOOKUP(K17,周期整合计算!J:K,2,0) -> 衰退 | N17: 过热 | O17: 过热 | P17: 43891 | Q17: 44135 | R17: 3 | S17: =DATEDIF(P18,Q18,"M")+1 -> 6 | V17: =[1]!s_pq_pctchange(V$1,$P17,$Q17) -> 17.490205 | W17: =[1]!s_pq_pctchange(W$1,$P17,$Q17) -> 16.282693 | X17: =[1]!s_pq_pctchange(X$1,$P17,$Q17) -> 19.169433 | Y17: =[1]!s_pq_pctchange(Y$1,$P17,$Q17) -> 12.110723 | Z17: =[1]!s_pq_pctchange(Z$1,$P17,$Q17) -> 10.904363 | AA17: =[1]!s_pq_pctchange(AA$1,$P17,$Q17) -> 18.168745 | AB17: =[1]!s_pq_pctchange(AB$1,$P17,$Q17) -> 37.525306 | AC17: =[1]!s_pq_pctchange(AC$1,$P17,$Q17) -> 6.0432257 | ... BT17: =[1]!s_pq_pctchange(BT$1,$P17,$Q17) -> 12.75471
A18: 45199 | B18: =VLOOKUP(A18,周期整合计算!A:G,7,0) -> 周期2（景气值<0，方向下降） | C18: =IF(ISNUMBER(D18),COUNTIF(D$2:D18,">0"),"") | D18: =IF(B17=B18,"",A18) | E18: =IF(ISNUMBER(F18),COUNTIF(F$2:F18,">0"),"") | F18: =IF(B18=B19,"",A18) | H18: 17 | N18: 过热 | P18: 42430 | Q18: 42613 | S18: =DATEDIF(P19,Q19,"M")+1 -> 10 | V18: =[1]!s_pq_pctchange(V$1,$P18,$Q18) -> 23.892305 | W18: =[1]!s_pq_pctchange(W$1,$P18,$Q18) -> 14.815332 | X18: =[1]!s_pq_pctchange(X$1,$P18,$Q18) -> 15.650128 | Y18: =[1]!s_pq_pctchange(Y$1,$P18,$Q18) -> 20.255864 | Z18: =[1]!s_pq_pctchange(Z$1,$P18,$Q18) -> 23.034221 | AA18: =[1]!s_pq_pctchange(AA$1,$P18,$Q18) -> 22.702165 | AB18: =[1]!s_pq_pctchange(AB$1,$P18,$Q18) -> 27.298311 | AC18: =[1]!s_pq_pctchange(AC$1,$P18,$Q18) -> 20.902518 | ... BT18: =[1]!s_pq_pctchange(BT$1,$P18,$Q18) -> 23.472072
A19: 45169 | B19: =VLOOKUP(A19,周期整合计算!A:G,7,0) -> 周期2（景气值<0，方向下降） | C19: =IF(ISNUMBER(D19),COUNTIF(D$2:D19,">0"),"") | D19: =IF(B18=B19,"",A19) | E19: =IF(ISNUMBER(F19),COUNTIF(F$2:F19,">0"),"") | F19: =IF(B19=B20,"",A19) | H19: 18 | N19: 过热 | P19: 41183 | Q19: 41486 | V19: =[1]!s_pq_pctchange(V$1,$P19,$Q19) -> 2.3761897 | W19: =[1]!s_pq_pctchange(W$1,$P19,$Q19) -> -6.7525597 | X19: =[1]!s_pq_pctchange(X$1,$P19,$Q19) -> -4.3646042 | Y19: =[1]!s_pq_pctchange(Y$1,$P19,$Q19) -> 7.2190282 | Z19: =[1]!s_pq_pctchange(Z$1,$P19,$Q19) -> 16.112956 | AA19: =[1]!s_pq_pctchange(AA$1,$P19,$Q19) -> -7.9481116 | AB19: =[1]!s_pq_pctchange(AB$1,$P19,$Q19) -> 4.2890119 | AC19: =[1]!s_pq_pctchange(AC$1,$P19,$Q19) -> 5.3405337 | ... BT19: =[1]!s_pq_pctchange(BT$1,$P19,$Q19) -> 8.8024404
A20: 45138 | B20: =VLOOKUP(A20,周期整合计算!A:G,7,0) -> 周期2（景气值<0，方向下降） | C20: =IF(ISNUMBER(D20),COUNTIF(D$2:D20,">0"),"") | D20: =IF(B19=B20,"",A20) | E20: =IF(ISNUMBER(F20),COUNTIF(F$2:F20,">0"),"") | F20: =IF(B20=B21,"",A20) | H20: 19 | R20: 个数 | S20: 总月数 | T20: 平均月数 | U20: 时期占比 | V20: 万得全A | W20: 上证50指数 | X20: 沪深300指数 | Y20: 中证500指数 | Z20: 中证1000指数 | AA20: 周期 | AB20: 消费 | AC20: 金融 | AD20: 稳定 | AE20: 成长 | AF20: 农林牧渔 | AG20: 基础化工 | AH20: 钢铁 | AI20: 有色金属 | AJ20: 电子 | AK20: 家用电器 | AL20: 食品饮料 | AM20: 纺织服饰 | AN20: 轻工制造 | AO20: 医药生物 | AP20: 公用事业 | AQ20: 交通运输 | AR20: 房地产 | AS20: 商贸零售 | AT20: 社会服务 | AU20: 综合 | AV20: 建筑材料 | AW20: 建筑装饰 | AX20: 电力设备 | AY20: 国防军工 | AZ20: 计算机 | BA20: 传媒 | BB20: 通信 | BC20: 银行 | BD20: 非银金融 | BE20: 汽车 | BF20: 机械设备 | BG20: 煤炭 | BH20: 石油石化 | BI20: 环保 | BJ20: 美容护理 | BK20: 红利指数 | BL20: 国证红利 | BM20: 深证红利 | BN20: 万得红利 | BO20: 中证红利 | BP20: 低估值指数(长江) | BQ20: 高估值指数(长江) | BR20: 巨潮大盘 | BS20: 巨潮中盘 | BT20: 巨潮小盘
A21: 45107 | B21: =VLOOKUP(A21,周期整合计算!A:G,7,0) -> 周期2（景气值<0，方向下降） | C21: =IF(ISNUMBER(D21),COUNTIF(D$2:D21,">0"),"") | D21: =IF(B20=B21,"",A21) | E21: =IF(ISNUMBER(F21),COUNTIF(F$2:F21,">0"),"") -> 2 | F21: =IF(B21=B22,"",A21) -> 45107 | H21: 20 | Q21: 衰退 | R21: =SUMIFS(R$3:R$19,$N$3:$N$19,$Q21) -> 5 | S21: =SUMIFS(S$3:S$19,$N$3:$N$19,$Q21) -> 37 | T21: =S21/R21 -> 7.4 | U21: =S21/SUM($S$21:$S$24) -> 0.21387283 | V21: =AVERAGEIFS(V$33:V$49,$N$3:$N$19,$Q21) -> 5.5086636 | W21: =AVERAGEIFS(W$33:W$49,$N$3:$N$19,$Q21) -> 11.779829 | X21: =AVERAGEIFS(X$33:X$49,$N$3:$N$19,$Q21) -> 7.2086078 | Y21: =AVERAGEIFS(Y$33:Y$49,$N$3:$N$19,$Q21) -> 0.70113889 | Z21: =AVERAGEIFS(Z$33:Z$49,$N$3:$N$19,$Q21) -> -3.4715431 | AA21: =AVERAGEIFS(AA$33:AA$49,$N$3:$N$19,$Q21) -> 7.1411878 | AB21: =AVERAGEIFS(AB$33:AB$49,$N$3:$N$19,$Q21) -> -2.6757577 | AC21: =AVERAGEIFS(AC$33:AC$49,$N$3:$N$19,$Q21) -> 18.482357 | ... BT21: =AVERAGEIFS(BT$33:BT$49,$N$3:$N$19,$Q21) -> 0.34958388
A22: 45077 | B22: =VLOOKUP(A22,周期整合计算!A:G,7,0) -> 周期3（景气值<0，方向上升） | C22: =IF(ISNUMBER(D22),COUNTIF(D$2:D22,">0"),"") -> 3 | D22: =IF(B21=B22,"",A22) -> 45077 | E22: =IF(ISNUMBER(F22),COUNTIF(F$2:F22,">0"),"") | F22: =IF(B22=B23,"",A22) | H22: 21 | O22: 绝对收益 | Q22: 复苏 | R22: =SUMIFS(R$3:R$19,$N$3:$N$19,$Q22) -> 5 | S22: =SUMIFS(S$3:S$19,$N$3:$N$19,$Q22) -> 61 | T22: =S22/R22 -> 12.2 | U22: =S22/SUM($S$21:$S$24) -> 0.35260116 | V22: =AVERAGEIFS(V$33:V$49,$N$3:$N$19,$Q22) -> 1.3728098 | W22: =AVERAGEIFS(W$33:W$49,$N$3:$N$19,$Q22) -> -8.3960639 | X22: =AVERAGEIFS(X$33:X$49,$N$3:$N$19,$Q22) -> -5.7193586 | Y22: =AVERAGEIFS(Y$33:Y$49,$N$3:$N$19,$Q22) -> -0.03542435 | Z22: =AVERAGEIFS(Z$33:Z$49,$N$3:$N$19,$Q22) -> 6.2972984 | AA22: =AVERAGEIFS(AA$33:AA$49,$N$3:$N$19,$Q22) -> -2.9714902 | AB22: =AVERAGEIFS(AB$33:AB$49,$N$3:$N$19,$Q22) -> 4.4909619 | AC22: =AVERAGEIFS(AC$33:AC$49,$N$3:$N$19,$Q22) -> -1.5158627 | ... BT22: =AVERAGEIFS(BT$33:BT$49,$N$3:$N$19,$Q22) -> 2.2651919
A23: 45046 | B23: =VLOOKUP(A23,周期整合计算!A:G,7,0) -> 周期3（景气值<0，方向上升） | C23: =IF(ISNUMBER(D23),COUNTIF(D$2:D23,">0"),"") | D23: =IF(B22=B23,"",A23) | E23: =IF(ISNUMBER(F23),COUNTIF(F$2:F23,">0"),"") | F23: =IF(B23=B24,"",A23) | H23: 22 | Q23: 过热 | R23: =SUMIFS(R$3:R$19,$N$3:$N$19,$Q23) -> 3 | S23: =SUMIFS(S$3:S$19,$N$3:$N$19,$Q23) -> 16 | T23: =S23/R23 -> 5.3333333 | U23: =S23/SUM($S$21:$S$24) -> 0.092485549 | V23: =AVERAGEIFS(V$33:V$49,$N$3:$N$19,$Q23) -> 14.586233 | W23: =AVERAGEIFS(W$33:W$49,$N$3:$N$19,$Q23) -> 8.1151554 | X23: =AVERAGEIFS(X$33:X$49,$N$3:$N$19,$Q23) -> 10.151652 | Y23: =AVERAGEIFS(Y$33:Y$49,$N$3:$N$19,$Q23) -> 13.195205 | Z23: =AVERAGEIFS(Z$33:Z$49,$N$3:$N$19,$Q23) -> 16.683847 | AA23: =AVERAGEIFS(AA$33:AA$49,$N$3:$N$19,$Q23) -> 10.974266 | AB23: =AVERAGEIFS(AB$33:AB$49,$N$3:$N$19,$Q23) -> 23.037543 | AC23: =AVERAGEIFS(AC$33:AC$49,$N$3:$N$19,$Q23) -> 10.762093 | ... BT23: =AVERAGEIFS(BT$33:BT$49,$N$3:$N$19,$Q23) -> 15.009741
A24: 45016 | B24: =VLOOKUP(A24,周期整合计算!A:G,7,0) -> 周期3（景气值<0，方向上升） | C24: =IF(ISNUMBER(D24),COUNTIF(D$2:D24,">0"),"") | D24: =IF(B23=B24,"",A24) | E24: =IF(ISNUMBER(F24),COUNTIF(F$2:F24,">0"),"") | F24: =IF(B24=B25,"",A24) | H24: 23 | Q24: 滞涨 | R24: =SUMIFS(R$3:R$19,$N$3:$N$19,$Q24) -> 4 | S24: =SUMIFS(S$3:S$19,$N$3:$N$19,$Q24) -> 59 | T24: =S24/R24 -> 14.75 | U24: =S24/SUM($S$21:$S$24) -> 0.34104046 | V24: =AVERAGEIFS(V$33:V$49,$N$3:$N$19,$Q24) -> 0.62170339 | W24: =AVERAGEIFS(W$33:W$49,$N$3:$N$19,$Q24) -> 0.47508047 | X24: =AVERAGEIFS(X$33:X$49,$N$3:$N$19,$Q24) -> 1.1029532 | Y24: =AVERAGEIFS(Y$33:Y$49,$N$3:$N$19,$Q24) -> 1.480297 | Z24: =AVERAGEIFS(Z$33:Z$49,$N$3:$N$19,$Q24) -> -0.046891041 | AA24: =AVERAGEIFS(AA$33:AA$49,$N$3:$N$19,$Q24) -> 1.1332988 | AB24: =AVERAGEIFS(AB$33:AB$49,$N$3:$N$19,$Q24) -> 9.0728143 | AC24: =AVERAGEIFS(AC$33:AC$49,$N$3:$N$19,$Q24) -> -4.408888 | ... BT24: =AVERAGEIFS(BT$33:BT$49,$N$3:$N$19,$Q24) -> -0.0059756089
A25: 44985 | B25: =VLOOKUP(A25,周期整合计算!A:G,7,0) -> 周期3（景气值<0，方向上升） | C25: =IF(ISNUMBER(D25),COUNTIF(D$2:D25,">0"),"") | D25: =IF(B24=B25,"",A25) | E25: =IF(ISNUMBER(F25),COUNTIF(F$2:F25,">0"),"") | F25: =IF(B25=B26,"",A25) | H25: 24
A26: 44957 | B26: =VLOOKUP(A26,周期整合计算!A:G,7,0) -> 周期3（景气值<0，方向上升） | C26: =IF(ISNUMBER(D26),COUNTIF(D$2:D26,">0"),"") | D26: =IF(B25=B26,"",A26) | E26: =IF(ISNUMBER(F26),COUNTIF(F$2:F26,">0"),"") | F26: =IF(B26=B27,"",A26) | H26: 25 | R26: 个数 | S26: 总月数 | T26: 平均月数 | U26: 时期占比 | V26: 万得全A | W26: 上证50指数 | X26: 沪深300指数 | Y26: 中证500指数 | Z26: 中证1000指数 | AA26: 周期 | AB26: 消费 | AC26: 金融 | AD26: 稳定 | AE26: 成长 | AF26: 农林牧渔 | AG26: 基础化工 | AH26: 钢铁 | AI26: 有色金属 | AJ26: 电子 | AK26: 家用电器 | AL26: 食品饮料 | AM26: 纺织服饰 | AN26: 轻工制造 | AO26: 医药生物 | AP26: 公用事业 | AQ26: 交通运输 | AR26: 房地产 | AS26: 商贸零售 | AT26: 社会服务 | AU26: 综合 | AV26: 建筑材料 | AW26: 建筑装饰 | AX26: 电力设备 | AY26: 国防军工 | AZ26: 计算机 | BA26: 传媒 | BB26: 通信 | BC26: 银行 | BD26: 非银金融 | BE26: 汽车 | BF26: 机械设备 | BG26: 煤炭 | BH26: 石油石化 | BI26: 环保 | BJ26: 美容护理 | BK26: 红利指数 | BL26: 国证红利 | BM26: 深证红利 | BN26: 万得红利 | BO26: 中证红利 | BP26: 低估值指数(长江) | BQ26: 高估值指数(长江) | BR26: 巨潮大盘 | BS26: 巨潮中盘 | BT26: 巨潮小盘
A27: 44926 | B27: =VLOOKUP(A27,周期整合计算!A:G,7,0) -> 周期3（景气值<0，方向上升） | C27: =IF(ISNUMBER(D27),COUNTIF(D$2:D27,">0"),"") | D27: =IF(B26=B27,"",A27) | E27: =IF(ISNUMBER(F27),COUNTIF(F$2:F27,">0"),"") | F27: =IF(B27=B28,"",A27) | H27: 26 | Q27: 衰退 | R27: =SUMIFS(R$3:R$19,$N$3:$N$19,$Q27) -> 5 | S27: =SUMIFS(S$3:S$19,$N$3:$N$19,$Q27) -> 37 | T27: =S27/R27 -> 7.4 | U27: =S27/SUM($S$21:$S$24) -> 0.21387283 | W27: =W21-$V21 -> 6.2711653 | X27: =X21-$V21 -> 1.6999442 | Y27: =Y21-$V21 -> -4.8075247 | Z27: =Z21-$V21 -> -8.9802067 | AA27: =AA21-$V21 -> 1.6325242 | AB27: =AB21-$V21 -> -8.1844213 | AC27: =AC21-$V21 -> 12.973694 | AD27: =AD21-$V21 -> 11.649308 | ... BT27: =BT21-$V21 -> -5.1590797
A28: 44895 | B28: =VLOOKUP(A28,周期整合计算!A:G,7,0) -> 周期3（景气值<0，方向上升） | C28: =IF(ISNUMBER(D28),COUNTIF(D$2:D28,">0"),"") | D28: =IF(B27=B28,"",A28) | E28: =IF(ISNUMBER(F28),COUNTIF(F$2:F28,">0"),"") | F28: =IF(B28=B29,"",A28) | H28: 27 | O28: 超额收益 | Q28: 复苏 | R28: =SUMIFS(R$3:R$19,$N$3:$N$19,$Q28) -> 5 | S28: =SUMIFS(S$3:S$19,$N$3:$N$19,$Q28) -> 61 | T28: =S28/R28 -> 12.2 | U28: =S28/SUM($S$21:$S$24) -> 0.35260116 | W28: =W22-$V22 -> -9.7688737 | X28: =X22-$V22 -> -7.0921684 | Y28: =Y22-$V22 -> -1.4082342 | Z28: =Z22-$V22 -> 4.9244886 | AA28: =AA22-$V22 -> -4.3443 | AB28: =AB22-$V22 -> 3.1181521 | AC28: =AC22-$V22 -> -2.8886725 | AD28: =AD22-$V22 -> -5.7442499 | ... BT28: =BT22-$V22 -> 0.89238212
A29: 44865 | B29: =VLOOKUP(A29,周期整合计算!A:G,7,0) -> 周期3（景气值<0，方向上升） | C29: =IF(ISNUMBER(D29),COUNTIF(D$2:D29,">0"),"") | D29: =IF(B28=B29,"",A29) | E29: =IF(ISNUMBER(F29),COUNTIF(F$2:F29,">0"),"") | F29: =IF(B29=B30,"",A29) | H29: 28 | Q29: 过热 | R29: =SUMIFS(R$3:R$19,$N$3:$N$19,$Q29) -> 3 | S29: =SUMIFS(S$3:S$19,$N$3:$N$19,$Q29) -> 16 | T29: =S29/R29 -> 5.3333333 | U29: =S29/SUM($S$21:$S$24) -> 0.092485549 | W29: =W23-$V23 -> -6.4710778 | X29: =X23-$V23 -> -4.4345811 | Y29: =Y23-$V23 -> -1.3910279 | Z29: =Z23-$V23 -> 2.0976137 | AA29: =AA23-$V23 -> -3.6119672 | AB29: =AB23-$V23 -> 8.4513097 | AC29: =AC23-$V23 -> -3.8241406 | AD29: =AD23-$V23 -> -7.8242854 | ... BT29: =BT23-$V23 -> 0.42350762
A30: 44834 | B30: =VLOOKUP(A30,周期整合计算!A:G,7,0) -> 周期3（景气值<0，方向上升） | C30: =IF(ISNUMBER(D30),COUNTIF(D$2:D30,">0"),"") | D30: =IF(B29=B30,"",A30) | E30: =IF(ISNUMBER(F30),COUNTIF(F$2:F30,">0"),"") | F30: =IF(B30=B31,"",A30) | H30: 29 | Q30: 滞涨 | R30: =SUMIFS(R$3:R$19,$N$3:$N$19,$Q30) -> 4 | S30: =SUMIFS(S$3:S$19,$N$3:$N$19,$Q30) -> 59 | T30: =S30/R30 -> 14.75 | U30: =S30/SUM($S$21:$S$24) -> 0.34104046 | W30: =W24-$V24 -> -0.14662292 | X30: =X24-$V24 -> 0.48124983 | Y30: =Y24-$V24 -> 0.85859361 | Z30: =Z24-$V24 -> -0.66859444 | AA30: =AA24-$V24 -> 0.5115954 | AB30: =AB24-$V24 -> 8.4511109 | AC30: =AC24-$V24 -> -5.0305913 | AD30: =AD24-$V24 -> -4.4765763 | ... BT30: =BT24-$V24 -> -0.627679
A31: 44804 | B31: =VLOOKUP(A31,周期整合计算!A:G,7,0) -> 周期3（景气值<0，方向上升） | C31: =IF(ISNUMBER(D31),COUNTIF(D$2:D31,">0"),"") | D31: =IF(B30=B31,"",A31) | E31: =IF(ISNUMBER(F31),COUNTIF(F$2:F31,">0"),"") | F31: =IF(B31=B32,"",A31) | H31: 30
A32: 44773 | B32: =VLOOKUP(A32,周期整合计算!A:G,7,0) -> 周期3（景气值<0，方向上升） | C32: =IF(ISNUMBER(D32),COUNTIF(D$2:D32,">0"),"") | D32: =IF(B31=B32,"",A32) | E32: =IF(ISNUMBER(F32),COUNTIF(F$2:F32,">0"),"") | F32: =IF(B32=B33,"",A32) | H32: 31
A33: 44742 | B33: =VLOOKUP(A33,周期整合计算!A:G,7,0) -> 周期3（景气值<0，方向上升） | C33: =IF(ISNUMBER(D33),COUNTIF(D$2:D33,">0"),"") | D33: =IF(B32=B33,"",A33) | E33: =IF(ISNUMBER(F33),COUNTIF(F$2:F33,">0"),"") | F33: =IF(B33=B34,"",A33) | H33: 32 | S33: 各指数收益的数值版 | V33: -9.3936893 | W33: -1.2499852 | X33: -5.7553298 | Y33: -12.223644 | Z33: -18.386214 | AA33: 4.6060163 | AB33: -8.9396062 | AC33: 2.8145633 | AD33: -2.0729171 | AE33: -21.26533 | AF33: -3.6209955 | AG33: -8.1374387 | AH33: -5.4312257 | AI33: 5.3467847 | AJ33: -13.495797 | AK33: 17.034894 | AL33: -9.4879572 | AM33: -5.8048045 | AN33: -11.325938 | AO33: -18.779457 | AP33: 1.3233817 | AQ33: -3.9361659 | AR33: -20.57693 | AS33: -24.941851 | AT33: -26.809836 | AU33: -24.994384 | AV33: -17.055372 | AW33: -18.217346 | AX33: -24.868016 | AY33: -15.049069 | AZ33: -31.122761 | BA33: -30.589754 | BB33: -6.78689 | BC33: 10.861163 | BD33: -7.7114362 | BE33: 5.686079 | BF33: -8.6832384 | BG33: 32.135158 | BH33: 6.8277451 | BI33: -14.578156 | BJ33: -26.86383 | BK33: 9.6940399 | BL33: 7.4233278 | BM33: -0.23097721 | BN33: 7.8990283 | BO33: 8.7314618 | BP33: 5.2096278 | BQ33: -24.983744 | BR33: -4.5564171 | BS33: -12.011956 | BT33: -13.228906
A34: 44712 | B34: =VLOOKUP(A34,周期整合计算!A:G,7,0) -> 周期3（景气值<0，方向上升） | C34: =IF(ISNUMBER(D34),COUNTIF(D$2:D34,">0"),"") | D34: =IF(B33=B34,"",A34) | E34: =IF(ISNUMBER(F34),COUNTIF(F$2:F34,">0"),"") | F34: =IF(B34=B35,"",A34) | H34: 33 | V34: 0.74693527 | W34: -10.491831 | X34: -7.9301131 | Y34: 4.3618518 | Z34: 8.3785057 | AA34: 10.972973 | AB34: -14.638137 | AC34: -9.964841 | AD34: 7.7795395 | AE34: 10.927326 | AF34: -7.6501187 | AG34: 19.36944 | AH34: 4.7435856 | AI34: 16.973682 | AJ34: 5.7096513 | AK34: -16.578508 | AL34: -16.471967 | AM34: -9.4090691 | AN34: -11.156303 | AO34: -17.429132 | AP34: 14.417948 | AQ34: -3.8294125 | AR34: -18.335859 | AS34: -7.058892 | AT34: -18.006169 | AU34: 3.9887304 | AV34: -15.237435 | AW34: 4.4597453 | AX34: 43.50978 | AY34: 13.516115 | AZ34: -3.969763 | BA34: -13.365148 | BB34: -0.34207348 | BC34: -12.158885 | BD34: -12.982357 | BE34: 17.191832 | BF34: 5.0263496 | BG34: 18.1337 | BH34: 9.5853014 | BI34: 1.8601064 | BJ34: -22.107893 | BK34: -4.5358014 | BL34: -12.081151 | BM34: -19.286732 | BN34: -5.2819579 | BO34: -4.6122851 | BP34: -8.3492491 | BQ34: -12.338759 | BR34: -7.3247282 | BS34: 1.2300282 | BT34: 6.3736596
A35: 44681 | B35: =VLOOKUP(A35,周期整合计算!A:G,7,0) -> 周期3（景气值<0，方向上升） | C35: =IF(ISNUMBER(D35),COUNTIF(D$2:D35,">0"),"") | D35: =IF(B34=B35,"",A35) | E35: =IF(ISNUMBER(F35),COUNTIF(F$2:F35,">0"),"") | F35: =IF(B35=B36,"",A35) | H35: 34 | V35: -16.029505 | W35: -4.2424287 | X35: -11.789998 | Y35: -21.489219 | Z35: -26.643389 | AA35: -17.762534 | AB35: -13.711584 | AC35: -7.2954124 | AD35: -10.528593 | AE35: -25.185689 | AF35: -16.175414 | AG35: -14.950686 | AH35: -7.8900843 | AI35: -27.129763 | AJ35: -29.726835 | AK35: -21.576794 | AL35: 2.0791405 | AM35: -24.886482 | AN35: -26.693476 | AO35: -16.76869 | AP35: -18.0724 | AQ35: -17.453684 | AR35: -23.831948 | AS35: -21.295689 | AT35: -4.7612827 | AU35: -29.112038 | AV35: -18.978897 | AW35: -17.81548 | AX35: -27.139376 | AY35: -18.624484 | AZ35: -21.172447 | BA35: -31.231291 | BB35: -25.050439 | BC35: -3.6277682 | BD35: -9.2560429 | BE35: -19.423512 | BF35: -23.557061 | BG35: -13.415885 | BH35: 1.6074822 | BI35: -30.917804 | BJ35: -20.220296 | BK35: -7.4837821 | BL35: -4.7513844 | BM35: -16.627122 | BN35: -7.9201826 | BO35: -10.716045 | BP35: -6.6215223 | BQ35: -19.602146 | BR35: -10.669584 | BS35: -21.224829 | BT35: -23.702298
A36: 44651 | B36: =VLOOKUP(A36,周期整合计算!A:G,7,0) -> 周期3（景气值<0，方向上升） | C36: =IF(ISNUMBER(D36),COUNTIF(D$2:D36,">0"),"") | D36: =IF(B35=B36,"",A36) | E36: =IF(ISNUMBER(F36),COUNTIF(F$2:F36,">0"),"") | F36: =IF(B36=B37,"",A36) | H36: 35 | V36: 56.23847 | W36: 74.183521 | X36: 63.865708 | Y36: 39.001911 | Z36: 29.673362 | AA36: 47.923118 | AB36: 28.821734 | AC36: 101.89344 | AD36: 95.20925 | AE36: 32.836099 | AF36: 31.228949 | AG36: 33.003802 | AH36: 92.593651 | AI36: 40.647116 | AJ36: 11.563052 | AK36: 30.284878 | AL36: 25.769253 | AM36: 37.837226 | AN36: 23.88836 | AO36: 18.004756 | AP36: 64.977873 | AQ36: 73.129482 | AR36: 64.533875 | AS36: 40.987084 | AT36: 26.922943 | AU36: 37.038067 | AV36: 47.177151 | AW36: 99.580279 | AX36: 30.668533 | AY36: 64.843173 | AZ36: 28.267881 | BA36: 16.257376 | BB36: 29.433127 | BC36: 67.178085 | BD36: 143.55742 | BE36: 35.440585 | BF36: 49.56379 | BG36: 50.174805 | BH36: 25.767686 | BI36: 46.588706 | BJ36: 12.82645 | BK36: 57.348125 | BL36: 72.479277 | BM36: 63.855431 | BN36: 0 | BO36: 56.416477 | BP36: 73.949163 | BQ36: 22.191706 | BR36: 64.859419 | BS36: 43.046298 | BT36: 39.95656
